Workbook

Sheet 개념
A1: Bricolage: analysis and refactoring - 삶의 비용과 효과를 재구성하는 방법
A2: bricoleur: 도구를 닥치는 대로 조합해 만드는 예술가 | D2: ‘브리콜레르(bricoleur)’는 레비스트로스의 『야생의 사고』에서 유래한 개념으로, 주어진 재료와 도구를 자유롭게 조합해 문제를 해결하는 ‘손재주꾼’ 또는 ‘현장형 실천형 지식인’을 뜻합니다. 아트앤스터디 +1 이 개념은 엔지니어링(설계·계획 중심)과 대비되며, 제한된 자원 속에서 즉흥적으로 창의적 해결책을 만드는 방식으로 설명됩니다.
A3: 요약 | B3: 적절한 제품을 구매하라
B4: 스스로 만들어라
B5: 노동하지말고, 설정만 비틀어서 5분이내 구현하라
A7: - 소모품은 물리적으로 소모되는 물질 (필터, 건전지, 세제 등) — 정기적으로 보충해야 하는 것
A8: - 병원비는 서비스 지출이자 유지보수 실패의 downstream 비용 — OPEX에 해당
A9: - 연간 몇회 구입하는 건은 시간을 1/12로 하고, 양을 N으로 한다. 그렇게 해야 계산이 간단하고, 직관적으로 식을 이해할 수 있다. 모두 수정
G11: =G12/F12 -> 0.31578947
F12: =COUNTA(F14:F70) -> 57 | G12: =COUNTA(G14:G70) -> 18
A13: 구분 | B13: 방법 | C13: 포인트 | D13: 사례 | E13: 분야 | F13: 원가절감 | G13: 가치제고 | H13: 개선 효과 | I13: 일반인 | J13: 일반인_활동 | K13: Bricoleur | L13: Bricoleur_활동 | P13: 일반인 (The Consumer) | Q13: Bricoleur (The Architect)
A14: 비용 절감 | B14: 1타 N피 | C14: 한 제품의 특징을 여러 분야에 적용 | D14: WD-40, 바세린, 니베아 크림 | E14: 생활 | F14: ○ | G14: ○ | H14: 내구성 개선 | I14: 15000 | J14: 용도별 전용 제품 복수 구매 | K14: 1500 | L14: 범용 제품 1개로 해결 | M14: =K14-I14 -> -13500 | P14: 목적별로 전용 하이엔드 제품을 각각 구매하여 공간과 비용을 낭비함. | Q14: 물질의 핵심 화학적·물리적 본질을 간파하여 하나의 자재로 일타십피함.
B15: positioning | C15: 저비용 position 확보 | D15: 중간에 낀 아파트 | E15: 주 | F15: ○ | I15: =300000*6/12 -> 150000 | J15: 외벽 한기 제거를 위한 가스 소비(동절기 6개월, 월 30만원) | K15: 0 | L15: 옆, 위, 아래 아파트의 온기 공유 | M15: =K15-I15 -> -150000 | P15: 브랜드와 대단지 프리미엄이라는 거품(10%)을 사기 위해 거대 영혼 가출 대출을 감사히 짊어짐. | Q15: 저비용 고효율 포지션을 명확히 장악하여 주거비의 고정 오버헤드를 물리적으로 컷(Cut)함.
B16: effectiveness | C16: 효과가 발생하는 부분에만 비용 투입 | D16: 온수매트 | E16: 주 | F16: ○ | I16: 150000 | J16: 안 쓰는 공간까지 보일러 풀가동 | K16: 30000 | L16: 동선 내 접촉 구역만 온수매트 타겟팅 | M16: =K16-I16 -> -120000 | P16: 보일러를 풀가동해 안 쓰는 방의 공기까지 데우며 가스비를 대기업에 덤핑함. | Q16: 내 피부와 신경계에 열이 닿는 실질적인 런타임 영역(온수매트)에만 비용을 집중 투입함.
B17: alternative | C17: 동일한 기능을 가지는 대체품 활용 | D17: 전열교환기 프레임에 스틸자 사용 | E17: 주 | F17: ○ | I17: 60000 | J17: 전용 정품 프레임 구입 및 교환(240만원/5년, 월 6만원) | K17: 5000 | L17: 스틸자 무한 재활용 | M17: =K17-I17 -> -55000
D18: 토마토로 과일 대체 | E18: 식 | F18: ○ | I18: 100000 | J18: 고가 제철/프리미엄 과일 | K18: 20000 | L18: 영양가 높은 토마토 통일 | M18: =K18-I18 -> -80000
D19: 모니터 거치대 대신 백과사전 | E19: 생활 | F19: ○ | I19: 20000 | J19: 브랜드 전용 거치대 구매 감가 | K19: 0 | L19: 기존 물성 활용 | M19: =K19-I19 -> -20000 | P19: 전용 모니터 거치대, 브랜드 소품을 카트에 담으며 포장재 쓰레기를 양산함. | Q19: 주위에 널린 고중량 물성(백과사전, 스틸자)을 팅커링(Tinkering)하여 기성품의 기능을 완벽히 대체함.
B20: DIY | C20: 고품질 제품 자작 | D20: 굵은 전선으로 고전류 오디오용 멀티탭 생산 | E20: 취미 | F20: ○ | G20: ○ | H20: spec 조절 가능 | I20: 0 | J20: 하이엔드 오디오 완제품 구매 감가 | K20: 10000 | L20: 부품 구매 후 자작 | M20: =K20-I20 -> 10000 | P20: 완제품에 붙은 브랜딩 마케팅 비용을 지불하며, 대기업 서비스(케어)의 노예가 됨. | Q20: 원재료 1%를 직접 소싱하고 빌드(Build)하여, 유통 마진을 파괴하고 최고 존엄의 럭셔리를 향유함.
D21: 게샤 원두를 사서 드립백 자작 | E21: 기호 | F21: ○ | G21: ○ | H21: 최상 기호품 향유 | I21: =5000*30 -> 150000 | J21: 브랜드 커피 전문점 사용(월 5000원 X 30회) | K21: =700*30 -> 21000 | L21: Top tier 생두/원두 소싱 후 직접 추출(700원 X 30회) | M21: =K21-I21 -> -129000
D22: 드립백을 사서 고급티백 자작 | E22: 기호 | F22: ○ | G22: ○ | H22: 최상 기호품 향유 | I22: =3000*10 -> 30000 | J22: 프리미엄 티 브랜드 완제품 구매(월 3000원 X10회) | K22: =50*30 -> 1500 | L22: 선물받은 차를 드립백으로 DIY | M22: =K22-I22 -> -28500
D23: LED 전구 + 한지로 조명만들기 | E23: 주 | F23: ○ | G23: ○ | H23: 고급스러운 분위기 | I23: =20000/20 -> 1000 | J23: 수입/디자이너 조명 구매 감가(20만원, 20개월 사용) | K23: =4000/20 -> 200 | L23: 부품 소싱 및 자작(전구 3천원, 프레임 천원) | M23: =K23-I23 -> -800
D24: 소니 모니터링 헤드폰 + 블루투스 리시버 | E24: 취미 | F24: ○ | I24: =600000/24 -> 25000 | J24: 배터리 수명 짧은 최신 무선 3년마다 기변 | K24: =300000/60 -> 5000 | L24: 유선 명기 + 블루투스 리시버 교체로 영구 사용 | M24: =K24-I24 -> -20000
D25: Self-hosting으로 구독료 제로화 | E25: IT | F25: ○ | G25: ○ | H25: IT 기술 강화 | I25: 50000 | J25: 스트리밍/클라우드 다중 구독 | K25: 5000 | L25: 전기세, 도메인 유지비 | M25: =K25-I25 -> -45000
C26: 서비스 비용 제거 | D26: 소형 포트 화분 구매후 육성 | E26: 취미 | F26: ○ | G26: ○ | H26: 식집사 체험 | I26: 30000 | J26: 대형 완성 화분 구매 및 폐기 반복 | K26: 3000 | L26: 소형 포트 육성 | M26: =K26-I26 -> -27000
D27: 조명, 힌지, 문고리 스스로 교환 | E27: 주 | F27: ○ | G27: ○ | H27: 부품선택 가능 | I27: 15000 | J27: 시공업체 출장비 및 마진 연환산 | K27: 3000 | L27: 인터넷 부품 원가 연환산 | M27: =K27-I27 -> -12000
D28: 비데 필터 자가 교환 | E28: 주 | F28: ○ | I28: 20000 | J28: 브랜드 렌탈 케어 서비스 | K28: 3000 | L28: 호환 필터 구입 | M28: =K28-I28 -> -17000
D29: 가스레인지 기름망 자가 세척 | E29: 주 | F29: ○ | I29: =100000/12 -> 8333.3333 | J29: 청소 서비스(년 2회, 회당 5만원) | K29: 1000 | L29: 세제 및 자가 노동 | M29: =K29-I29 -> -7333.3333
B30: 부품 교환 | C30: 부품을 교환하여 전체 set 수명 개선 | D30: PC에 ram/ssd 추가 | E30: IT | F30: ○ | G30: ○ | H30: 생산성 | I30: =1500000/24 -> 62500 | J30: 느려지면 완제품 교체 감가(150만원/2년) | K30: =100000/12 -> 8333.3333 | L30: 병목 부품만 업그레이드 | M30: =K30-I30 -> -54166.667 | P30: 아주 작은 부품 하나만 고장 나거나 느려져도 시스템 전체를 폐기하고 새로 구매함. | Q30: 병목(Bottleneck)이 발생한 노드만 정확히 짚어내어 교체(Patch)함으로써 전체 세트의 수명을 영구히 연장함.
D31: 전자제품 fuse 교환 | E31: 생활 | F31: ○ | I31: 10000 | J31: 공식 AS 호출 및 수리비 | K31: 200 | L31: 퓨즈 원가 | M31: =K31-I31 -> -9800
D32: 모바일 기기 케이스, 보호유리, 마우스 접점 등 | E32: 생활 | F32: ○ | I32: 15000 | J32: 대리점/브랜드 정품 구매 | K32: 2000 | L32: 부품 직구 | M32: =K32-I32 -> -13000
C33: 부품을 소모품화하여 사용감 개선 | D33: 다이소 신발깔창으로 자주 교환 | E33: 의 | F33: ○ | G33: ○ | H33: 쾌적함 | I33: 0 | J33: 신발 통교체 또는 세탁소 의뢰 | K33: 1000 | L33: 다이소 깔창 교체 | M33: =K33-I33 -> 1000
B34: 중고품 당근 | C34: 중고를 사서 초기 감가상각 비용 회피 | D34: 90~2000년대 오디오 컴포넌트 | E34: 취미 | F34: ○ | J34: 초기 신제품 감가상각 직격타 | K34: =7000000/120 -> 58333.333 | L34: 감가 끝난 명기 중고 방어 | M34: =K34-I34 -> 58333.333 | P34: 비닐도 안 뜯은 신제품의 초기 감가상각 비용을 온몸으로 두들겨 맞으며 자산을 탕진함. | Q34: 감가상각이 완전히 끝나 본질적인 가치만 남은 명작들을 당근마켓에서 주워와 생산성을 극상으로 레버리지함.
D35: 중형 카메라 및 렌즈 | E35: 취미 | F35: ○ | J35: 최신형 카메라 바디/렌즈 감가 | K35: =3500000/120 -> 29166.667 | L35: 중고품 소싱 및 재당근 방어 | M35: =K35-I35 -> 29166.667
D36: 맥 컴퓨터, 리눅스 미니 PC | E36: IT | F36: ○ | G36: ○ | H36: 생산성 | J36: 신형 출시마다 통기변 감가 | K36: =1300000/180 -> 7222.2222 | L36: 중고 맥/미니 PC 헌터 | M36: =K36-I36 -> 7222.2222
D37: 취미용품: 등산, 낚시, 골프채 등 | E37: 취미 | F37: ○ | I37: 100000 | J37: 유행 따라 신상 풀세트 구매 감가 | K37: 15000 | L37: 당근에서 검증된 중고 소싱 | M37: =K37-I37 -> -85000
D38: 보스턴 백 등 비일상 가방 | E38: 취미 | F38: ○ | I38: =250000/36 -> 6944.4444 | J38: 필요할 때마다 새 제품 구매 방치 | K38: =30000/36 -> 833.33333 | L38: 중고 거래 활용 | M38: =K38-I38 -> -6111.1111
D39: fitness 회원권 | E39: 취미 | F39: ○ | G39: ○ | H39: 건강 | I39: 100000 | J39: 정가 연간권 결제 후 유령 회원 | K39: =1200000*0.75*0.6/12 -> 45000 | L39: 당근마켓 양도권 활용 | M39: =K39-I39 -> -55000
B40: right spec | C40: 필요한 기능만 있는 제품을 구입하여 안쓰는 프리미엄 방지 | D40: 공기청정기: 샤오미+3rd party | E40: 주 | F40: ○ | I40: 40000 | J40: 하이엔드 브랜드 렌탈/구독료 | K40: =30000/60+10000*2/12 -> 2166.6667 | L40: 기본 스펙 + 호환 필터 자가교체 | M40: =K40-I40 -> -37833.333 | P40: 쓰지도 않는 프리미엄 기능과 센서가 덕지덕지 붙은 100만 원짜리 과보조 하이엔드 가전에 영혼을 빼앗김. | Q40: 콤팩트하고 이동성이 극대화된 기본 스펙만 취하고, 소모품은 호환 필터(3rd party)로 자가 관리하여 낭비를 차단함.
D41: 정수기: filter 자가 교환 | E41: 주 | F41: ○ | I41: 45000 | J41: 얼음/케어 포함 브랜드 렌탈 | K41: =198000/48+45000*2/12 -> 11625 | L41: 직수형 기본 스펙 + 자가 교체 | M41: =K41-I41 -> -33375
D42: 가습기: 샤오미 | E42: 주 | F42: ○ | I42: 20000 | J42: 복합식/과보조 기능 가습기 감가 | K42: =15000/24 -> 625 | L42: 자연기화식 기본 스펙 | M42: =K42-I42 -> -19375
D43: 마우스: 로지텍 기본, 키보드: 독거미 | E43: IT | F43: ○ | I43: 15000 | J43: 게이밍/프리미엄 잦은 교체 감가 | K43: =15000/36+40000/48 -> 1250 | L43: 가성비 최적화 기기 | M43: =K43-I43 -> -13750
D44: 내의: 패션이 아니므로 국산 대량 구입(러닝, 팬티, 양말 등) | E44: 의 | F44: ○ | I44: 20000 | J44: 브랜드/백화점 내의 낱개 구매 | K44: 3000 | L44: 품질 좋은 국산 대량 구매 통일 | M44: =K44-I44 -> -17000
D45: 이너: 잘 안보이므로 기능이 좋은 국산을 아울렛 매대에서 구입 | E45: 의 | F45: ○ | I45: =200000*4/24 -> 33333.333 | J45: 신상/브랜드 이너웨어 구매 | K45: =50000*4/24 -> 8333.3333 | L45: 매대 기능성 의류 소싱 | M45: =K45-I45 -> -25000
D46: 모니터는 120hz, 4K로 스펙 통일 | E46: IT | F46: ○ | G46: ○ | H46: 쾌적함 | I46: 30000 | J46: 오버스펙 게이밍/브랜드 감가 | K46: 10000 | L46: 최적 스펙 통일 방어 | M46: =K46-I46 -> -20000
D47: 아이패드는 일반형 wifi로 | E47: IT | F47: ○ | I47: =2000000/48 -> 41666.667 | J47: 프로/셀룰러 오버스펙 구매 감가 | K47: =520000/60 -> 8666.6667 | L47: 일반형 본질 스펙 유지 | M47: =K47-I47 -> -33000
C48: 필요한 기능에 지불 | D48: 놋쇠 수저, 세라믹 식기 | E48: 식 | F48: ○ | G48: ○ | H48: 쾌적 건강 | I48: 15000 | J48: 유행 타는 식기 세트 잦은 기변 | K48: =(60000+40000)/60 -> 1666.6667 | L48: 반영구적 실질 기능 식기 | M48: =K48-I48 -> -13333.333
C49: 고성능 PC로 IT 생산성 강화 | D49: Mac studio 등 CPU/RAM 집중투자 | E49: IT | F49: ○ | G49: ○ | H49: 쾌적 건강 | J49: 외형 겉멋 투자 후 잦은 병목/기변 | K49: =3600000/120 -> 30000 | L49: 64GB RAM 등 코어 스펙 집중 롱런 | M49: =K49-I49 -> 30000
B50: not over change | C50: 실질적 내구도를 보고, 소모품 교환 | D50: 엔진오일: 1L 채워주고, 교환(3만km보증이니 2.5만km만) | E50: 생활 | F50: ○ | I50: =240000/12 -> 20000 | J50: 센터의 과잉 정비 적용 | K50: =(240000+30000)/24 -> 11250 | L50: 데이터 기반 보충 후 적기 교환 | M50: =K50-I50 -> -8750 | P50: 대기업 정비소의 마케팅 스크립트(주기별 무조건 교체)에 속아 멀쩡한 자산을 조기 폐기함. | Q50: 실질적 내구도와 데이터(km)를 모니터링하며, 소모되는 코어(밑창, 오일)만 영리하게 부분 보수함.
D51: 비브람 밑창 교환(약간 빠르게) | E51: 의 | F51: ○ | I51: =200000/12 -> 16666.667 | J51: 밑창 닳으면 신발 폐기 및 재구입 | K51: =200000/48+36000/12 -> 7166.6667 | L51: 마모 전 선제적 보강 수명 연장 | M51: =K51-I51 -> -9500
B52: 유지보수 | C52: 사전 유지보수를 통한 고장 방지 | D52: 가죽제품 정기 컨디셔닝 | E52: 의 | F52: ○ | G52: ○ | I52: 30000 | J52: 갈라지고 부패하여 통폐기/재구입 | K52: 2000 | L52: 컨디셔너 도포로 반영구적 유지 | M52: =K52-I52 -> -28000 | P52: 고장 나거나 무뎌질 때까지 방치하다가 최악의 타이밍에 시스템 다운(System Down)을 맞이함. | Q52: 크론탭(Crontab)을 돌리듯 정기적인 사전 레이버(Labor)를 투입해 기기의 컨디션을 무결점으로 유지함.
D53: 시계 tool을 사서 배터리 교환 | E53: 생활 | F53: ○ | I53: 3000 | J53: 매장 방문 및 교체 수리비 | K53: 300 | L53: 건전지 부품 원가 | M53: =K53-I53 -> -2700
D54: 이케아 칼갈이로 칼, 가위 보수 | E54: 식 | F54: ○ | I54: 5000 | J54: 무뎌지면 버리고 새 세트 구매 | K54: 500 | L54: 툴 하나로 무한 보수 | M54: =K54-I54 -> -4500
B55: condensate | C55: 물을 섞어 쓰는 방식으로 용기, 운송비 절감 | D55: 알약 형식의 차유리 세정제 사용 | E55: 생활 | F55: ○ | I55: 10000 | J55: 대형 페트병 워셔액 지속 구매 | K55: 500 | L55: 알약 보충 + 수돗물 믹싱 | M55: =K55-I55 -> -9500 | P55: 무거운 액체와 플라스틱 병(페트병 음료)을 대량으로 사서 냉장고를 채우고, 산더미 같은 분리수거 쓰레기에 노동을 저당 잡힘. | Q55: 고농축 자산(알약 세정제, 차, 안동소주)만 소싱하고 로컬 인프라(정수기 물, 얼음)와 결합해 분리수거를 제로(0)화함.
D56: 녹차 Pet병 대신 녹차 타먹기 | E56: 기호 | F56: ○ | I56: 80000 | J56: 무거운 페트병 음료 박스 단위 쟁임 | K56: 5000 | L56: 찻잎/티백 + 정수기 직수 | M56: =K56-I56 -> -75000
D57: 맥주대신 독주+얼음 | E57: 기호 | F57: ○ | G57: ○ | I57: 120000 | J57: 부피 큰 맥주 잦은 구매/냉장고 부하 | K57: 30000 | L57: 안동 소주 등 고농축 + 얼음 | M57: =K57-I57 -> -90000
B58: simplify | C58: 생활명품 정기 구입을 통해 다른 지출 차단 | D58: 베트남 캐슈넛으로 견과류 통일 | E58: 기호 | F58: ○ | G58: ○ | I58: 120000 | J58: 온갖 프리미엄 간식 탐색 과소비 | K58: 10000 | L58: 고품질 벌크 통일 락온 | M58: =K58-I58 -> -110000 | P58: 마트에서 카트를 끌며 온갖 신상 과자와 기호품을 탐닉하느라 인지적 과부하와 과소비를 유발함. | Q58: 검증된 생활명품 딱 몇 가지만 데이터베이스에 락(Lock)해두고 정기 구입하여, 기호품 소비에 들어가는 뇌 연산 능력을 꺼버림.
D59: 에이스, 야채크래커로 과자 통일 | E59: 기호 | F59: ○ | I59: 80000 | J59: 마트 카트 신상 과자 무작위 담기 | K59: 10000 | L59: 검증된 클래식 라인 정기 소싱 | M59: =K59-I59 -> -70000
B60: sharing | C60: 소분을 통해 한 번 구매/여러 곳에서 사용 | D60: Personal care제품 소분용기 이용 | E60: 의 | F60: ○ | I60: 15000 | J60: 여행/운동용 트래블 키트 매번 구입 | K60: 1000 | L60: 본품 소분 | M60: =K60-I60 -> -14000 | P60: 대용량 제품을 사서 방치하다 유통기한이 지나 쓰레기통으로 버리는 '악성 재고 순환 체계'에 갇힘. | Q60: 대용량 자산을 해체해 호텔 용기 등에 감각적으로 소분함. 내 식탁은 콤팩트하게 만들고, 남은 가치는 지인에게 분배하여 비동기 리턴(보답) 자산으로 유동화함.
D61: 단위가 큰 후추, 소금, 소스류 소분하여 지인과 나눔 | E61: 식 | F61: ○ | I61: 10000 | J61: 악성 재고로 유통기한 경과 후 폐기 | K61: 0 | L61: 리턴 자산화 | M61: =K61-I61 -> -10000
B62: relocation | C62: IT기기 보직 변경으로 수명 연장 | D62: 오래된 아이맥은 인터넷, 유튜브 전용 | E62: IT | F62: ○ | I62: 40000 | J62: 기존 기기 폐기 후 서브 PC 구매 | K62: 0 | L62: 새로운 보직/임무 부여 | M62: =K62-I62 -> -40000 | P62: 신형 기기가 나오면 구형 기기는 서랍 속에 처박아 두어 가치를 0으로 만듦. | Q62: 구형 하드웨어의 보직을 변경(Repurposing)하여 전용 모듈(액자, 리모컨, 서버)로 완벽하게 리팩토링함.
D63: 오래된 테블릿은 전자 액자 | E63: IT | F63: ○ | I63: 10000 | J63: 전용 디지털 액자 추가 구매 감가 | K63: 0 | L63: 구형 런타임 환경 재활용 | M63: =K63-I63 -> -10000
D64: 오래된 아이폰은 리모컨으로 | E64: IT | F64: ○ | I64: 0 | J64: 스마트 리모컨/패널 추가 구매 | K64: 0 | L64: 스마트 홈 인터페이스 전용 | M64: =K64-I64 -> 0
D65: 오래된 맥북은 크램쉘 모드로 | E65: IT | F65: ○ | I65: 60000 | J65: 데스크탑 Mac 추가 구매 감가 | K65: 0 | L65: 본체로 활용하여 수명 연장 | M65: =K65-I65 -> -60000
D66: 지인의 잉여 물품 받아오기 | E66: 식 | F66: ○ | I66: 0 | J66: 필요 물품 무조건 새것 구매 | K66: 0 | L66: 유휴 자산 네트워크 활용 | M66: =K66-I66 -> 0
A67: 관리 | B67: 카드사 할인 | C67: 조건을 맞추려는 불필요한 소비 증가 | D67: 카드사 할인 카드는 1개만 운영 | E67: 관리 | F67: ○ | I67: 300000 | J67: 실적 채우기용 억지 과소비 누수 | K67: 0 | L67: 포트 1개로 한정하여 과소비 방어 | M67: =K67-I67 -> -300000 | P67: 카드 실적 조건을 맞추기 위해 억지로 불필요한 소비를 추가로 감행하는 연산 오류를 범함. | Q67: 카드사 마케팅 스크립트에 휘둘리지 않도록 포트를 딱 1개만 열어두고 트래픽을 단순화함.
B68: 구독 최적화 | C68: 매일 쓰는 제품만 구독 | D68: 자동차 리스, 정수기는 검토 가능 | E68: 관리 | F68: ○ | J68: 무분별한 렌탈 구독료 적자 | L68: 검증된 필수 인프라만 구독 | M68: =K68-I68 -> 0 | P68: "월 몇만 원"이라는 구독 경제의 교묘한 덫에 걸려 매달 고정 비용 파이프라인에서 피 같은 돈이 줄줄 새어나감. | Q68: 매일 쓰는 본질적 서비스가 아니면 접근 토큰을 만료(Expire)시키고, 자산 점유율을 엄격하게 통제함.
B69: 유효기간 | C69: 미리알림 app에 사전 등록 및 반복 | D69: 정수기/청정기 필터 교환 시기 | E69: 관리 | F69: ○ | J69: 교체 시기 도과로 기기 고장/성능 저하 | K69: 0 | L69: 마리 알림으로 즉각 자가 처리 | M69: =K69-I69 -> 0 | P69: 필터 교체 주기나 식재료 유통기한을 감으로 관리하다 타이밍을 놓쳐 시스템에 에러를 냄. | Q69: **'미리알림 100선 크론탭'**을 구축하여 알림이 울리면 고민 없이 1분 컷으로 자가 정비를 완료하는 자동화 루틴을 완비함.
D70: 식재료 유효기간 | E70: 관리 | F70: ○ | I70: 150000 | J70: 냉장고 블랙홀에서 썩혀 버리는 비용 | K70: 0 | L70: 알림 연동 즉시 소모 캐싱 | M70: =K70-I70 -> -150000
I72: =SUM(I14:I70) -> 2448444.4 | K72: =SUM(K14:K70) -> 431338.89 | M72: =SUM(M14:M70) -> -2017105.6
H73: 12 | I73: =I72*$H73 -> 29381333 | K73: =K72*$H73 -> 5176066.7 | M73: =M72*$H73 -> -24205267
A77: 구분 | B77: 방법 | C77: 사례 (본질) | D77: 일반인 (The Consumer) | E77: Bricoleur (The Architect)
A78: 비용 절감 | B78: 1타 N피 | C78: WD-40, 바세린 등 | D78: 목적별로 전용 하이엔드 제품을 각각 구매하여 공간과 비용을 낭비함. | E78: 물질의 핵심 화학적·물리적 본질을 간파하여 하나의 자재로 일타십피함.
B79: positioning | C79: 낀 아파트 (주거) | D79: 브랜드와 대단지 프리미엄이라는 거품(10%)을 사기 위해 거대 영혼 가출 대출을 감사히 짊어짐. | E79: 저비용 고효율 포지션을 명확히 장악하여 주거비의 고정 오버헤드를 물리적으로 컷(Cut)함.
B80: effectiveness | C80: 온수매트만 가동 | D80: 보일러를 풀가동해 안 쓰는 방의 공기까지 데우며 가스비를 대기업에 덤핑함. | E80: 내 피부와 신경계에 열이 닿는 실질적인 런타임 영역(온수매트)에만 비용을 집중 투입함.
B81: alternative | C81: 스틸자, 백과사전 등 | D81: 전용 모니터 거치대, 브랜드 소품을 카트에 담으며 포장재 쓰레기를 양산함. | E81: 주위에 널린 고중량 물성(백과사전, 스틸자)을 팅커링(Tinkering)하여 기성품의 기능을 완벽히 대체함.
B82: DIY | C82: 오디오 멀티탭, 드립백 자작, 자가 셸프 호스팅 등 | D82: 완제품에 붙은 브랜딩 마케팅 비용을 지불하며, 대기업 서비스(케어)의 노예가 됨. | E82: 원재료 1%를 직접 소싱하고 빌드(Build)하여, 유통 마진을 파괴하고 최고 존엄의 럭셔리를 향유함.
B83: 부품 교환 | C83: RAM/SSD 추가, 퓨즈 교환 등 | D83: 아주 작은 부품 하나만 고장 나거나 느려져도 시스템 전체를 폐기하고 새로 구매함. | E83: 병목(Bottleneck)이 발생한 노드만 정확히 짚어내어 교체(Patch)함으로써 전체 세트의 수명을 영구히 연장함.
B84: 중고품 당근 | C84: 오디오 컴포넌트, 카메라, 맥 컴퓨터 등 | D84: 비닐도 안 뜯은 신제품의 초기 감가상각 비용을 온몸으로 두들겨 맞으며 자산을 탕진함. | E84: 감가상각이 완전히 끝나 본질적인 가치만 남은 명작들을 당근마켓에서 주워와 생산성을 극상으로 레버리지함.
B85: right spec | C85: 샤오미 가전, 독거미 키보드, 아울렛 매대 이너 등 | D85: 쓰지도 않는 프리미엄 기능과 센서가 덕지덕지 붙은 100만 원짜리 과보조 하이엔드 가전에 영혼을 빼앗김. | E85: 콤팩트하고 이동성이 극대화된 기본 스펙만 취하고, 소모품은 호환 필터(3rd party)로 자가 관리하여 낭비를 차단함.
B86: not over change | C86: 엔진오일 보충만, 비브람 밑창 보수 | D86: 대기업 정비소의 마케팅 스크립트(주기별 무조건 교체)에 속아 멀쩡한 자산을 조기 폐기함. | E86: 실질적 내구도와 데이터(km)를 모니터링하며, 소모되는 코어(밑창, 오일)만 영리하게 부분 보수함.
B87: 유지보수 | C87: 가죽 정기 컨디셔닝, 이케아 칼갈이 | D87: 고장 나거나 무뎌질 때까지 방치하다가 최악의 타이밍에 시스템 다운(System Down)을 맞이함. | E87: 크론탭(Crontab)을 돌리듯 정기적인 사전 레이버(Labor)를 투입해 기기의 컨디션을 무결점으로 유지함.
B88: condensate | C88: 알약 세정제, 전통 독주+얼음 | D88: 무거운 액체와 플라스틱 병(페트병 음료)을 대량으로 사서 냉장고를 채우고, 산더미 같은 분리수거 쓰레기에 노동을 저당 잡힘. | E88: 고농축 자산(알약 세정제, 차, 안동소주)만 소싱하고 로컬 인프라(정수기 물, 얼음)와 결합해 분리수거를 제로(0)화함.
B89: simplify | C89: 캐슈넛, 크래커 통일 | D89: 마트에서 카트를 끌며 온갖 신상 과자와 기호품을 탐닉하느라 인지적 과부하와 과소비를 유발함. | E89: 검증된 생활명품 딱 몇 가지만 데이터베이스에 락(Lock)해두고 정기 구입하여, 기호품 소비에 들어가는 뇌 연산 능력을 꺼버림.
B90: sharing | C90: 개인 케어 제품, 후추·소금 소분 나눔 | D90: 대용량 제품을 사서 방치하다 유통기한이 지나 쓰레기통으로 버리는 '악성 재고 순환 체계'에 갇힘. | E90: 대용량 자산을 해체해 호텔 용기 등에 감각적으로 소분함. 내 식탁은 콤팩트하게 만들고, 남은 가치는 지인에게 분배하여 비동기 리턴(보답) 자산으로 유동화함.
B91: relocation | C91: 오래된 아이맥(유튜브용), 아이폰(리모컨) 등 | D91: 신형 기기가 나오면 구형 기기는 서랍 속에 처박아 두어 가치를 0으로 만듦. | E91: 구형 하드웨어의 보직을 변경(Repurposing)하여 전용 모듈(액자, 리모컨, 서버)로 완벽하게 리팩토링함.
A92: 관리 | B92: 카드사 할인 | C92: 할인 카드 1개만 운영 | D92: 카드 실적 조건을 맞추기 위해 억지로 불필요한 소비를 추가로 감행하는 연산 오류를 범함. | E92: 카드사 마케팅 스크립트에 휘둘리지 않도록 포트를 딱 1개만 열어두고 트래픽을 단순화함.
B93: 구독 최적화 | C93: 자동차 리스, 정수기 등 검토 | D93: "월 몇만 원"이라는 구독 경제의 교묘한 덫에 걸려 매달 고정 비용 파이프라인에서 피 같은 돈이 줄줄 새어나감. | E93: 매일 쓰는 본질적 서비스가 아니면 접근 토큰을 만료(Expire)시키고, 자산 점유율을 엄격하게 통제함.
B94: 유효기간 | C94: 미리알림 앱 사전 등록 및 반복 | D94: 필터 교체 주기나 식재료 유통기한을 감으로 관리하다 타이밍을 놓쳐 시스템에 에러를 냄. | E94: **'미리알림 100선 크론탭'**을 구축하여 알림이 울리면 고민 없이 1분 컷으로 자가 정비를 완료하는 자동화 루틴을 완비함.

Sheet 지출차이
A1: 구분 | B1: 방법 | C1: 포인트 | D1: 사례 | E1: 분야 | F1: 설계자 (Architect) | G1: 설계자_활동 | H1: 일반인 (Consumer) | I1: 일반인_활동 | J1: 노동자 (Laborer) | K1: 노동자_활동 | L1: 설계자-일반인 | M1: 설계자-노동자
A2: 비용 절감 | B2: 1타 N피 | C2: 한 제품 특징 여러 분야 적용 | D2: WD-40, 바세린, 니베아 크림 | E2: 생활 | F2: 1500 | G2: 범용 제품 1개로 해결 | H2: 15000 | I2: 용도별 전용 제품 복수 구매 | J2: 15000 | K2: 일반인과 동일하게 각각 구매 | L2: =F2-H2 -> -13500 | M2: =F2-J2 -> -13500
B3: positioning | C3: 저비용 position 확보 | D3: 중간에 낀 아파트 | E3: 주 | F3: 0 | G3: 옆/위/아래 아파트 온기 공유 | H3: 150000 | I3: 외벽 한기 제거용 가스 소비 | J3: 150000 | K3: 일반인과 동일한 가스 소비 | L3: =F3-H3 -> -150000 | M3: =F3-J3 -> -150000
B4: effectiveness | C4: 효과 발생 부분에만 비용 투입 | D4: 온수매트 | E4: 주 | F4: 30000 | G4: 동선 내 접촉 구역만 온수매트 | H4: 150000 | I4: 안 쓰는 공간까지 보일러 풀가동 | J4: 150000 | K4: 일반인과 동일하게 전체 가동 | L4: =F4-H4 -> -120000 | M4: =F4-J4 -> -120000
B5: alternative | C5: 동일 기능 가지는 대체품 활용 | D5: 전열교환기 프레임에 스틸자 사용 | E5: 주 | F5: 5000 | G5: 스틸자 5분 튜닝 무한 재활용 | H5: 60000 | I5: 전용 정품 프레임 구입 및 교환 | J5: 30000 | K5: 최저가 호환 프레임 검색에 2시간 소모 | L5: =F5-H5 -> -55000 | M5: =F5-J5 -> -25000
D6: 토마토로 과일 대체 | E6: 식 | F6: 20000 | G6: 영양가 높은 토마토 통일 | H6: 100000 | I6: 고가 제철/프리미엄 과일 구매 | J6: 60000 | K6: 마트 마감 세일 과자/과일 수령 노동 | L6: =F6-H6 -> -80000 | M6: =F6-J6 -> -40000
D7: 모니터 거치대 대신 백과사전 | E7: 생활 | F7: 0 | G7: 기존 물성 활용 | H7: 20000 | I7: 브랜드 전용 거치대 구매 감가 | J7: 10000 | K7: 당근 구형 거치대 직거래 거래 매몰 | L7: =F7-H7 -> -20000 | M7: =F7-J7 -> -10000
B8: DIY | C8: 고품질 제품 자작 | D8: 오디오용 멀티탭 생산 (굵은 전선) | E8: 취미 | F8: 10000 | G8: 부품 소싱 후 5분 내 결선 자작 | H8: 0 | I8: 완제품 구매 안 함 (관심 없음) | J8: 40000 | K8: 자작 카페 글 보며 주말 내내 납땜 노동 | L8: =F8-H8 -> 10000 | M8: =F8-J8 -> -30000
D9: 게샤 원두를 사서 드립백 자작 | E9: 기호 | F9: 21000 | G9: Top tier 원두 소싱 직접 추출 | H9: 150000 | I9: 브랜드 커피 전문점 무심코 이용 | J9: 60000 | K9: 가성비 저가 커피숍 찾아 원정 통근 | L9: =F9-H9 -> -129000 | M9: =F9-J9 -> -39000
D10: 드립백을 사서 고급티백 자작 | E10: 기호 | F10: 1500 | G10: 선물받은 차를 드립백으로 DIY | H10: 30000 | I10: 프리미엄 티 브랜드 완제품 구매 | J10: 15000 | K10: 마트 보급형 현미녹차 대량 구매 | L10: =F10-H10 -> -28500 | M10: =F10-J10 -> -13500
D11: LED 전구 + 한지로 조명만들기 | E11: 주 | F11: 200 | G11: 부품 소싱 및 5분 자작 | H11: 1000 | I11: 수입/디자이너 조명 구매 감가 | J11: 0 | K11: 인테리어 포기 (불 끄고 삶) | L11: =F11-H11 -> -800 | M11: =F11-J11 -> 200
D12: 소니 헤드폰 + 블루투스 리시버 | E12: 취미 | F12: 5000 | G12: 유선 명기 + 리시버 교체 영구 사용 | H12: 25000 | I12: 배터리 수명 짧은 무선 기기 기변 | J12: 15000 | K12: 짝퉁 가성비 무선 이어폰 잦은 고장교체 | L12: =F12-H12 -> -20000 | M12: =F12-J12 -> -10000
D13: Self-hosting으로 구독료 제로화 | E13: IT | F13: 5000 | G13: 전기세, 도메인 유지비 | H13: 50000 | I13: 스트리밍/클라우드 다중 구독 | J13: 20000 | K13: 무료 우회 결제/웹 서핑 시간 낭비 | L13: =F13-H13 -> -45000 | M13: =F13-J13 -> -15000
C14: 서비스 비용 제거 | D14: 소형 포트 화분 구매 후 육성 | E14: 취미 | F14: 3000 | G14: 소형 포트 육성 | H14: 30000 | I14: 대형 완성 화분 구매 및 폐기 반복 | J14: 15000 | K14: 산이나 들에서 흙 파오기 육체 노동 | L14: =F14-H14 -> -27000 | M14: =F14-J14 -> -12000
D15: 조명, 힌지, 문고리 스스로 교환 | E15: 주 | F15: 3000 | G15: 인터넷 부품 원가 연환산 (5분 컷) | H15: 15000 | I15: 시공업체 출장비 및 마진 연환산 | J15: 3000 | K15: 주말 하루 통째로 반납하여 시공 노동 | L15: =F15-H15 -> -12000 | M15: =F15-J15 -> 0
D16: 비데 필터 자가 교환 | E16: 주 | F16: 3000 | G16: 호환 필터 구입 (원터치 1분 교체) | H16: 20000 | I16: 브랜드 렌탈 케어 서비스 상납 | J16: 3000 | K16: 스패너 들고 고전하며 필터 수동 조립 | L16: =F16-H16 -> -17000 | M16: =F16-J16 -> 0
D17: 가스레인지 기름망 자가 세척 | E17: 주 | F17: 1000 | G17: 과탄산소다 전용 세제 5분 불림 세척 | H17: 8333 | I17: 청소 업체 호출 서비스 | J17: 1000 | K17: 철수세미로 손목 나갈 때까지 박박 문지름 | L17: =F17-H17 -> -7333 | M17: =F17-J17 -> 0
B18: 부품 교환 | C18: 부품 교환하여 전체 set 수명 개선 | D18: PC에 ram/ssd 추가 | E18: IT | F18: 8333 | G18: 병목 부품만 깔끔하게 정밀 업그레이드 | H18: 62500 | I18: 느려지면 완제품 교체 감가 상납 | J18: 30000 | K18: 사양 맞추려 밤새 커뮤니티 정독 노동 | L18: =F18-H18 -> -54167 | M18: =F18-J18 -> -21667
D19: 전자제품 fuse 교환 | E19: 생활 | F19: 200 | G19: 퓨즈 원가 직구 세팅 | H19: 10000 | I19: 공식 AS 호출비 및 수리비 지불 | J19: 5000 | K19: 동네 전포 다 뒤져가며 부품 구하러 다님 | L19: =F19-H19 -> -9800 | M19: =F19-J19 -> -4800
D20: 모바일 기기 케이스, 보호유리 보수 | E20: 생활 | F20: 2000 | G20: 부품 직구 사전 구비 | H20: 15000 | I20: 대리점/브랜드 정품 비싸게 구매 | J20: 2000 | K20: 가성비 알리 배송 한 달 기다림 대기 매몰 | L20: =F20-H20 -> -13000 | M20: =F20-J20 -> 0
C21: 부품을 소모품화하여 사용감 개선 | D21: 다이소 신발깔창으로 자주 교환 | E21: 의 | F21: 1000 | G21: 다이소 깔창 교체로 쾌적 유지 | H21: 0 | I21: 일반인은 미수행 (신발 조기 폐기) | J21: 0 | K21: 노동자도 미수행 (그냥 참고 신음) | L21: =F21-H21 -> 1000 | M21: =F21-J21 -> 1000
B22: 중고품 당근 | C22: 중고 사서 초기 감가상각 회피 | D22: 90~2000년대 오디오 컴포넌트 | E22: 취미 | F22: 58333 | G22: 감가 끝난 명기 중고 데이터 기반 방어 | H22: 0 | I22: 일반인 기준 제외 (관심 없음) | J22: 20000 | K22: 당근 키워드 알림 보며 무한 잠복 스트레스받다가 최신 국내, 중국산 오디오 구입 | L22: =F22-H22 -> 58333 | M22: =F22-J22 -> 38333
D23: 중형 카메라 및 렌즈 | E23: 취미 | F23: 29167 | G23: 중고품 소싱 및 명징한 재당근 방어 | H23: 0 | I23: 일반인 기준 제외 (관심 없음) | J23: 10000 | K23: 밤낮으로 장터 매물 사기 검증 스트레스로 slr카메라, 렌즈 구입후 호환 지옥 | L23: =F23-H23 -> 29167 | M23: =F23-J23 -> 19167
D24: 맥 컴퓨터, 리눅스 미니 PC | E24: IT | F24: 7222 | G24: 중고 맥/미니 PC 가성비 헌터 | H24: 0 | I24: 일반인 기준 제외 (관심 없음) | J24: 5000 | K24: 고장 난 벽돌 매물 주워와 고치느라 고생 | L24: =F24-H24 -> 7222 | M24: =F24-J24 -> 2222
D25: 취미용품: 등산, 낚시, 골프채 등 | E25: 취미 | F25: 15000 | G25: 당근에서 검증된 명품 중고 소싱 | H25: 100000 | I25: 유행 따라 신상 풀세트 구매 감가 | J25: 40000 | K25: 상태 불량 매물 잘못 사서 이중 지출 고생 | L25: =F25-H25 -> -85000 | M25: =F25-J25 -> -25000
D26: 보스턴 백 등 비일상 가방 | E26: 취미 | F26: 833 | G26: 중고 거래 영리한 활용 | H26: 6944 | I26: 필요할 때마다 새 제품 구매 방치 | J26: 4000 | K26: 중고 직거래하러 왕복 1시간 운전 노동 | L26: =F26-H26 -> -6111 | M26: =F26-J26 -> -3167
D27: fitness 회원권 | E27: 취미 | F27: 45000 | G27: 당근마켓 양도권 스마트 활용 | H27: 100000 | I27: 정가 연간권 결제 후 유령 회원 | J27: 60000 | K27: 헬스장 거리 멀어도 무조건 싼 곳 결제 | L27: =F27-H27 -> -55000 | M27: =F27-J27 -> -15000
B28: right spec | C28: 필요한 기능만 있는 제품 구입 | D28: 공기청정기: 샤오미+3rd party | E28: 주 | F28: 2167 | G28: 기본 스펙 + 호환 필터 자가교체 | H28: 40000 | I28: 하이엔드 브랜드 렌탈/구독료 상납 | J28: 10000 | K28: 필터 물세척해서 쓰려다 성능 망가뜨림 | L28: =F28-H28 -> -37833 | M28: =F28-J28 -> -7833
D29: 정수기: filter 자가 교환 | E29: 주 | F29: 11625 | G29: 직수형 기본 스펙 + 자가 교체 | H29: 45000 | I29: 얼음/케어 포함 브랜드 렌탈 상납 | J29: 20000 | K29: 생수 최저가 검색 후 매번 문앞 이동 노동 | L29: =F29-H29 -> -33375 | M29: =F29-J29 -> -8375
D30: 가습기: 샤오미 | E30: 주 | F30: 625 | G30: 자연기화식 기본 스펙 설정 분해 세척 | H30: 20000 | I30: 복합식/과보조 기능 가습기 감가 상납 | J30: 10000 | K30: 수동 세척 힘든 구조 매일 닦느라 고생 | L30: =F30-H30 -> -19375 | M30: =F30-J30 -> -9375
D31: 마우스: 로지텍 기본, 키보드: 독거미 | E31: IT | F31: 1250 | G31: 가성비 최적화 명기 기기 세팅 | H31: 15000 | I31: 게이밍/프리미엄 잦은 교체 감가 | J31: 8000 | K31: 피시방 중고 마우스 주워와 고쳐 씀 | L31: =F31-H31 -> -13750 | M31: =F31-J31 -> -6750
D32: 내의: 국산 대량 구입 통일 | E32: 의 | F32: 3000 | G32: 품질 좋은 국산 대량 구매 통일 | H32: 20000 | I32: 브랜드/백화점 내의 낱개 구매 누수 | J32: 10000 | K32: 다이소 초저가 내의 사서 금방 늘어남 | L32: =F32-H32 -> -17000 | M32: =F32-J32 -> -7000
D33: 이너: 아울렛 매대 기능성 구입 | E33: 의 | F33: 8333 | G33: 매대 기능성 의류 원가 소싱 | H33: 33333 | I33: 신상/브랜드 이너웨어 구매 페이로드 | J33: 15000 | K33: 구제 시장 뒤져가며 옷 고르는 시간 낭비 | L33: =F33-H33 -> -25000 | M33: =F33-J33 -> -6667
D34: 모니터는 120hz, 4K로 스펙 통일 | E34: IT | F34: 10000 | G34: Eizo 등 최적 스펙 통일 방어 | H34: 30000 | I34: 오버스펙 게이밍/브랜드 감가 상납 | J34: 20000 | K34: 중고 깨진 모니터 들고 와 수리 시도 | L34: =F34-H34 -> -20000 | M34: =F34-J34 -> -10000
D35: 아이패드는 일반형 wifi로 | E35: IT | F35: 8667 | G35: 일반형 본질 스펙 영리한 유지 | H35: 41667 | I35: 프로/셀룰러 사고 밥 먹을 때 유튜브 거치 | J35: 20000 | K35: 가성비 중국산 탭 샀다가 벽돌 되어 방치 | L35: =F35-H35 -> -33000 | M35: =F35-J35 -> -11333
C36: 필요한 기능에 지불 | D36: 놋쇠 수저, 세라믹 식기 | E36: 식 | F36: 1667 | G36: 반영구적 실질 기능 명품 식기 | H36: 15000 | I36: 유행 타는 식기 세트 잦은 기변 누수 | J36: 5000 | K36: 다이소 플라스틱 식기 유해물질 노출 위험 | L36: =F36-H36 -> -13333 | M36: =F36-J36 -> -3333
C37: 고성능 PC로 IT 생산성 강화 | D37: Mac studio 등 CPU/RAM 집중투자 | E37: IT | F37: 30000 | G37: 64GB RAM 코어 집중 롱런 설계 | H37: 0 | I37: 일반인 기준 제외 (윈도우 놋북 한대 끝) | J37: 10000 | K37: 조립 PC 호환성 꼬여 주말 내내 포맷 반복 | L37: =F37-H37 -> 30000 | M37: =F37-J37 -> 20000
B38: not over change | C38: 실질적 내구도 보고 소모품 교환 | D38: 엔진오일: 데이터 기반 보충/적기교환 | E38: 생활 | F38: 11250 | G38: 데이터 기반 보충 후 적기 교환 | H38: 20000 | I38: 센터의 과잉 정비 스크립트 그대로 수행 | J38: 15000 | K38: 공임나라 최저가 찾으려 원정 정비 노동 | L38: =F38-H38 -> -8750 | M38: =F38-J38 -> -3750
D39: 비브람 밑창 교환 | E39: 의 | F39: 7167 | G39: 마모 전 선제적 보강 수명 연장 | H39: 16667 | I39: 밑창 닳으면 신발 통째 폐기 및 재구입 | J39: 10000 | K39: 셀프작업하다 집안에 냄새 가득 노동 | L39: =F39-H39 -> -9500 | M39: =F39-J39 -> -2833
B40: 유지보수 | C40: 사전 유지보수 통한 고장 방지 | D40: 가죽제품 정기 컨디셔닝 | E40: 의 | F40: 2000 | G40: 컨디셔너 도포로 반영구적 유지 | H40: 30000 | I40: 갈라지고 부패하여 통폐기/재구입 | J40: 15000 | K40: 다이소 구두약으로 문지르다 가죽 망가뜨림 | L40: =F40-H40 -> -28000 | M40: =F40-J40 -> -13000
D41: 시계 tool 사서 배터리 자가교환 | E41: 생활 | F41: 300 | G41: 건전지 부품 원가 세팅 | H41: 3000 | I41: 매장 방문 및 과도한 교체 수리비 지불 | J41: 2000 | K41: 이쑤시개로 뜯다 시계 기스 내고 고장 | L41: =F41-H41 -> -2700 | M41: =F41-J41 -> -1700
D42: 이케아 칼갈이로 칼, 가위 보수 | E42: 식 | F42: 500 | G42: 툴 하나로 10초 무한 보수 | H42: 5000 | I42: 무뎌지면 버리고 새 세트 구매 | J42: 3000 | K42: 숫돌에 물 부어가며 주말 내내 칼 가는 노동 | L42: =F42-H42 -> -4500 | M42: =F42-J42 -> -2500
B43: condensate | C43: 물 섞어 쓰는 방식으로 비용 절감 | D43: 알약 형식 차유리 세정제 사용 | E43: 생활 | F43: 500 | G43: 알약 보충 + 수돗물 믹싱 | H43: 10000 | I43: 대형 페트병 워셔액 매번 구매/이동 | J43: 5000 | K43: 폐차장이나 정비소 잉여 워셔액 구걸 트래픽 | L43: =F43-H43 -> -9500 | M43: =F43-J43 -> -4500
D44: 녹차 Pet병 대신 녹차 타먹기 | E44: 기호 | F44: 5000 | G44: 찻잎/티백 + 정수기 직수 활용 | H44: 80000 | I44: 무거운 페트병 음료 박스 단위 구매/노동 | J44: 40000 | K44: 저가 보급형 대용량 현미녹차 쟁여두기 | L44: =F44-H44 -> -75000 | M44: =F44-J44 -> -35000
D45: 맥주대신 독주+얼음 | E45: 기호 | F45: 30000 | G45: 안동 소주 등 고농축 + 얼음 | H45: 120000 | I45: 부피 큰 맥주 구매 및 페트병 분리수거 지옥 | J45: 60000 | K45: 초저가 발포주 대량 구매하여 배부름 가중 | L45: =F45-H45 -> -90000 | M45: =F45-J45 -> -30000
B46: simplify | C46: 생활명품 정기 구입 다른 지출 차단 | D46: 베트남 캐슈넛으로 견과류 통일 | E46: 기호 | F46: 10000 | G46: 고품질 벌크 통일 락온 | H46: 120000 | I46: 온갖 프리미엄 간식 탐색 과소비 | J46: 60000 | K46: 최저가 못난이 견과류 검색, 안먹고 버림 | L46: =F46-H46 -> -110000 | M46: =F46-J46 -> -50000
D47: 에이스, 야채크래커로 과자 통일 | E47: 기호 | F47: 10000 | G47: 검증된 클래식 라인 정기 소싱 | H47: 80000 | I47: 마트 카트 신상 과자 무작위 담기 | J47: 40000 | K47: 세계과자할인점 투어 원정 소비 노동 | L47: =F47-H47 -> -70000 | M47: =F47-J47 -> -30000
B48: sharing | C48: 소분 통해 한 번 구매/여러 곳 사용 | D48: Personal care제품 소분용기 이용 | E48: 의 | F48: 1000 | G48: 본품 용기 소분화 | H48: 15000 | I48: 여행/운동용 트래블 키트 매번 구매 누수 | J48: 5000 | K48: 대용량 통째로 가방에 무겁게 들고 다님 | L48: =F48-H48 -> -14000 | M48: =F48-J48 -> -4000
D49: 단위 큰 후추, 소금 소분 지인 나눔 | E49: 식 | F49: 0 | G49: 리턴 자산화 (나눔 후 폐기 제로) | H49: 10000 | I49: 악성 재고로 유통기한 경과 후 폐기 | J49: 10000 | K49: 굳어버린 양념 억지로 쓰다 음식 망침 | L49: =F49-H49 -> -10000 | M49: =F49-J49 -> -10000
B50: relocation | C50: IT기기 보직 변경으로 수명 연장 | D50: 오래된 아이맥 인터넷/유튜브 전용 | E50: IT | F50: 0 | G50: 새로운 보직/임무 부여 (모듈화) | H50: 40000 | I50: 기존 기기 고장 시 폐기 후 서브 PC 구매 | J50: 20000 | K50: 고장 난 모니터 부품 교체하려다 완전 고장 | L50: =F50-H50 -> -40000 | M50: =F50-J50 -> -20000
D51: 오래된 태블릿은 전자 액자 | E51: IT | F51: 0 | G51: 구형 런타임 환경 재활용 | H51: 10000 | I51: 전용 디지털 액자 추가 구매 감가 | J51: 5000 | K51: 중고로 단돈 만 원에 팔려고 왕복 직거래 | L51: =F51-H51 -> -10000 | M51: =F51-J51 -> -5000
D52: 오래된 아이폰은 리모컨으로 | E52: IT | F52: 0 | G52: 스마트 홈 인터페이스 전용 | H52: 0 | I52: 스마트 리모컨 추가 구매 안 함 | J52: 0 | K52: 노동자도 스마트 홈 포기 | L52: =F52-H52 -> 0 | M52: =F52-J52 -> 0
D53: 오래된 맥북은 크램쉘 모드로 | E53: IT | F53: 0 | G53: 본체로 활용하여 수명 연장 | H53: 60000 | I53: 데스크탑 Mac 추가 구매 감가상각 상납 | J53: 30000 | K53: 사양 부족한 서브 노트북 붙잡고 부팅 대기 | L53: =F53-H53 -> -60000 | M53: =F53-J53 -> -30000
D54: 지인의 잉여 물품 받아오기 | E54: 식 | F54: 0 | G54: 유휴 자산 네트워크 정확히 활용 | H54: 0 | I54: 필요 물품 새것 무조건 구매 안 함 | J54: 0 | K54: 필요 없는 유휴 쓰레기까지 받아와 방치 | L54: =F54-H54 -> 0 | M54: =F54-J54 -> 0
A55: 관리 | B55: 카드사 할인 | C55: 조건을 맞추려는 불필요 소비 증가 | D55: 카드사 할인 카드는 1개만 운영 | E55: 관리 | F55: 0 | G55: 포트 1개 한정 과소비 사전 차단 | H55: 300000 | I55: 실적 채우기용 억지 과소비 누수 | J55: 150000 | K55: 카드 5개 실적 쪼개기 계산하느라 인지 폭발 | L55: =F55-H55 -> -300000 | M55: =F55-J55 -> -150000
B56: 구독 최적화 | C56: 매일 쓰는 제품만 구독 | D56: 자동차 리스, 정수기는 검토 가능 | E56: 관리 | F56: 0 | G56: 필수 인프라 외 접근 토큰 만료 | H56: 0 | I56: 무분별한 렌탈 구독 무수행 | J56: 0 | K56: 구독 혜택 뽕 뽑으려 밤새 의무 시청 피로 | L56: =F56-H56 -> 0 | M56: =F56-J56 -> 0
B57: 유효기간 | C57: 미리알림 app 사전 등록 및 반복 | D57: 정수기/청정기 필터 교환 시기 | E57: 관리 | F57: 0 | G57: 미리 알림 트리거로 즉각 자가 정비 | H57: 0 | I57: 교체 시기 도과 에러 방치 | J57: 0 | K57: 주기 기억 못 해 찜찜해하며 방치 | L57: =F57-H57 -> 0 | M57: =F57-J57 -> 0
D58: 식재료 유효기간 | E58: 관리 | F58: 0 | G58: 알림 연동 즉시 소모 캐싱 | H58: 150000 | I58: 냉장고 블랙홀에서 썩혀 버리는 비용 상납 | J58: 50000 | K58: 유통기한 지난 음식 아깝다고 먹다 배탈 | L58: =F58-H58 -> -150000 | M58: =F58-J58 -> -50000
A59: 합계 | F59: =SUM(F2:F58) -> 431339 | H59: =SUM(H2:H58) -> 2448444 | J59: =SUM(J2:J58) -> 1411000 | L59: =SUM(L2:L58) -> -2017105 | M59: =SUM(M2:M58) -> -979661

Sheet 자산차이
A1: 목차 | B1: 내용 | C1: 페이지
A2: 서문 | B2: 집필 목적: 설명이 아닌 공감대 형성, 계산/미리알림 양식 공유를 통한 실행 관리 | C2: 3 | F2: 천원 | G2: 기초 | H2: 지출항목 연계 | J2: 수익 | K2: random | L2: -0.02 | M2: 기말
A3: 지출 관리 | B3: 개념, 3개의 타입, 지출 형태 및 결과표 | C3: 10 | F3: year | G3: 일반인 | H3: 노동자 | I3: 설계자 | J3: 일반인 | K3: 노동자 | L3: 설계자 | M3: 일반인 | N3: 노동자 | O3: 설계자
A4: 지출관리 방법론 | B4: 비용절감 14개, 관리 3개 각각에 대한 설명 및 사례 제시 | C4: 34 | F4: 2 | G4: =D29*12 -> 13200 | H4: =E29*12 -> 24000 | I4: =F29*12 -> 37200 | J4: =G4*RANDBETWEEN(-10, 10)/100 -> 924 | K4: =H4*RANDBETWEEN(-10, 10)/100 -> -1680 | L4: =I4*L$2 -> -744 | M4: =G4+J4 -> 14124 | N4: =H4+K4 -> 22320 | O4: =I4+L4 -> 36456
A5: 시간 관리 | B5: 개념, 3개의 타입, 지출 형태 및 결과표 | C5: 4 | F5: 3 | G5: =G$4+M4 -> 27324 | H5: =H$4+N4 -> 46320 | I5: =I$4+O4 -> 73656 | J5: =G5*RANDBETWEEN(-10, 10)/100 -> -2185.92 | K5: =H5*RANDBETWEEN(-10, 10)/100 -> -2779.2 | L5: =I5*L$2 -> -1473.12 | M5: =G5+J5 -> 25138.08 | N5: =H5+K5 -> 43540.8 | O5: =I5+L5 -> 72182.88
A6: Resource | B6: 관리 결과 시간/비용 변화 도표(as is vs. to be를 input, consumption, balance로 표현) | C6: 2 | F6: 4 | G6: =G$4+M5 -> 38338.08 | H6: =H$4+N5 -> 67540.8 | I6: =I$4+O5 -> 109382.88 | J6: =G6*RANDBETWEEN(-10, 10)/100 -> 766.7616 | K6: =H6*RANDBETWEEN(-10, 10)/100 -> -3377.04 | L6: =I6*L$2 -> -2187.6576 | M6: =G6+J6 -> 39104.842 | N6: =H6+K6 -> 64163.76 | O6: =I6+L6 -> 107195.22
A7: 시간 | B7: 활용 개념과 5대 과제 | C7: 3 | F7: 5 | G7: =G$4+M6 -> 52304.842 | H7: =H$4+N6 -> 88163.76 | I7: =I$4+O6 -> 144395.22 | J7: =G7*RANDBETWEEN(-10, 10)/100 -> 0 | K7: =H7*RANDBETWEEN(-10, 10)/100 -> 8816.376 | L7: =I7*L$2 -> -2887.9044 | M7: =G7+J7 -> 52304.842 | N7: =H7+K7 -> 96980.136 | O7: =I7+L7 -> 141507.32
B8: 선순환 효과 | C8: 4 | F8: 6 | G8: =G$4+M7 -> 65504.842 | H8: =H$4+N7 -> 120980.14 | I8: =I$4+O7 -> 178707.32 | J8: =G8*RANDBETWEEN(-10, 10)/100 -> -655.04842 | K8: =H8*RANDBETWEEN(-10, 10)/100 -> -12098.014 | L8: =I8*L$2 -> -3574.1464 | M8: =G8+J8 -> 64849.793 | N8: =H8+K8 -> 108882.12 | O8: =I8+L8 -> 175133.17
B9: 나에 대한 선물주기 | C9: 2 | F9: 7 | G9: =G$4+M8 -> 78049.793 | H9: =H$4+N8 -> 132882.12 | I9: =I$4+O8 -> 212333.17 | J9: =G9*RANDBETWEEN(-10, 10)/100 -> 780.49793 | K9: =H9*RANDBETWEEN(-10, 10)/100 -> -2657.6424 | L9: =I9*L$2 -> -4246.6634 | M9: =G9+J9 -> 78830.291 | N9: =H9+K9 -> 130224.48 | O9: =I9+L9 -> 208086.51
B10: 합계 | C10: =SUM(C2:C9) -> 62 | F10: 8 | G10: =G$4+M9 -> 92030.291 | H10: =H$4+N9 -> 154224.48 | I10: =I$4+O9 -> 245286.51 | J10: =G10*RANDBETWEEN(-10, 10)/100 -> 4601.5146 | K10: =H10*RANDBETWEEN(-10, 10)/100 -> -4626.7344 | L10: =I10*L$2 -> -4905.7302 | M10: =G10+J10 -> 96631.806 | N10: =H10+K10 -> 149597.75 | O10: =I10+L10 -> 240380.78
F11: 9 | G11: =G$4+M10 -> 109831.81 | H11: =H$4+N10 -> 173597.75 | I11: =I$4+O10 -> 277580.78 | J11: =G11*RANDBETWEEN(-10, 10)/100 -> -2196.6361 | K11: =H11*RANDBETWEEN(-10, 10)/100 -> 1735.9775 | L11: =I11*L$2 -> -5551.6156 | M11: =G11+J11 -> 107635.17 | N11: =H11+K11 -> 175333.72 | O11: =I11+L11 -> 272029.16
F12: 10 | G12: =G$4+M11 -> 120835.17 | H12: =H$4+N11 -> 199333.72 | I12: =I$4+O11 -> 309229.16 | J12: =G12*RANDBETWEEN(-10, 10)/100 -> 6041.7585 | K12: =H12*RANDBETWEEN(-10, 10)/100 -> -9966.6862 | L12: =I12*L$2 -> -6184.5832 | M12: =G12+J12 -> 126876.93 | N12: =H12+K12 -> 189367.04 | O12: =I12+L12 -> 303044.58
F13: 11 | G13: =G$4+M12 -> 140076.93 | H13: =H$4+N12 -> 213367.04 | I13: =I$4+O12 -> 340244.58 | J13: =G13*RANDBETWEEN(-10, 10)/100 -> 2801.5386 | K13: =H13*RANDBETWEEN(-10, 10)/100 -> 12802.022 | L13: =I13*L$2 -> -6804.8916 | M13: =G13+J13 -> 142878.47 | N13: =H13+K13 -> 226169.06 | O13: =I13+L13 -> 333439.69
F14: 12 | G14: =G$4+M13 -> 156078.47 | H14: =H$4+N13 -> 250169.06 | I14: =I$4+O13 -> 370639.69 | J14: =G14*RANDBETWEEN(-10, 10)/100 -> -14047.062 | K14: =H14*RANDBETWEEN(-10, 10)/100 -> -20013.525 | L14: =I14*L$2 -> -7412.7938 | M14: =G14+J14 -> 142031.4 | N14: =H14+K14 -> 230155.53 | O14: =I14+L14 -> 363226.89
F15: 13 | G15: =G$4+M14 -> 155231.4 | H15: =H$4+N14 -> 254155.53 | I15: =I$4+O14 -> 400426.89 | J15: =G15*RANDBETWEEN(-10, 10)/100 -> 9313.8843 | K15: =H15*RANDBETWEEN(-10, 10)/100 -> 12707.777 | L15: =I15*L$2 -> -8008.5379 | M15: =G15+J15 -> 164545.29 | N15: =H15+K15 -> 266863.31 | O15: =I15+L15 -> 392418.36
F16: 14 | G16: =G$4+M15 -> 177745.29 | H16: =H$4+N15 -> 290863.31 | I16: =I$4+O15 -> 429618.36 | J16: =G16*RANDBETWEEN(-10, 10)/100 -> 5332.3587 | K16: =H16*RANDBETWEEN(-10, 10)/100 -> 8725.8993 | L16: =I16*L$2 -> -8592.3671 | M16: =G16+J16 -> 183077.65 | N16: =H16+K16 -> 299589.21 | O16: =I16+L16 -> 421025.99
F17: 15 | G17: =G$4+M16 -> 196277.65 | H17: =H$4+N16 -> 323589.21 | I17: =I$4+O16 -> 458225.99 | J17: =G17*RANDBETWEEN(-10, 10)/100 -> 17664.988 | K17: =H17*RANDBETWEEN(-10, 10)/100 -> -16179.461 | L17: =I17*L$2 -> -9164.5198 | M17: =G17+J17 -> 213942.64 | N17: =H17+K17 -> 307409.75 | O17: =I17+L17 -> 449061.47
F18: 16 | G18: =G$4+M17 -> 227142.64 | H18: =H$4+N17 -> 331409.75 | I18: =I$4+O17 -> 486261.47 | J18: =G18*RANDBETWEEN(-10, 10)/100 -> -6814.2791 | K18: =H18*RANDBETWEEN(-10, 10)/100 -> 33140.975 | L18: =I18*L$2 -> -9725.2294 | M18: =G18+J18 -> 220328.36 | N18: =H18+K18 -> 364550.72 | O18: =I18+L18 -> 476536.24
F19: 17 | G19: =G$4+M18 -> 233528.36 | H19: =H$4+N18 -> 388550.72 | I19: =I$4+O18 -> 513736.24 | J19: =G19*RANDBETWEEN(-10, 10)/100 -> -21017.552 | K19: =H19*RANDBETWEEN(-10, 10)/100 -> 38855.072 | L19: =I19*L$2 -> -10274.725 | M19: =G19+J19 -> 212510.8 | N19: =H19+K19 -> 427405.8 | O19: =I19+L19 -> 503461.51
F20: 18 | G20: =G$4+M19 -> 225710.8 | H20: =H$4+N19 -> 451405.8 | I20: =I$4+O19 -> 540661.51 | J20: =G20*RANDBETWEEN(-10, 10)/100 -> -2257.108 | K20: =H20*RANDBETWEEN(-10, 10)/100 -> -40626.522 | L20: =I20*L$2 -> -10813.23 | M20: =G20+J20 -> 223453.7 | N20: =H20+K20 -> 410779.28 | O20: =I20+L20 -> 529848.28
F21: 19 | G21: =G$4+M20 -> 236653.7 | H21: =H$4+N20 -> 434779.28 | I21: =I$4+O20 -> 567048.28 | J21: =G21*RANDBETWEEN(-10, 10)/100 -> -2366.537 | K21: =H21*RANDBETWEEN(-10, 10)/100 -> -26086.757 | L21: =I21*L$2 -> -11340.966 | M21: =G21+J21 -> 234287.16 | N21: =H21+K21 -> 408692.52 | O21: =I21+L21 -> 555707.32
F22: 20 | G22: =G$4+M21 -> 247487.16 | H22: =H$4+N21 -> 432692.52 | I22: =I$4+O21 -> 592907.32 | J22: =G22*RANDBETWEEN(-10, 10)/100 -> -4949.7432 | K22: =H22*RANDBETWEEN(-10, 10)/100 -> 17307.701 | L22: =I22*L$2 -> -11858.146 | M22: =G22+J22 -> 242537.42 | N22: =H22+K22 -> 450000.22 | O22: =I22+L22 -> 581049.17
F23: 21 | G23: =G$4+M22 -> 255737.42 | H23: =H$4+N22 -> 474000.22 | I23: =I$4+O22 -> 618249.17 | J23: =G23*RANDBETWEEN(-10, 10)/100 -> -2557.3742 | K23: =H23*RANDBETWEEN(-10, 10)/100 -> -9480.0044 | L23: =I23*L$2 -> -12364.983 | M23: =G23+J23 -> 253180.04 | N23: =H23+K23 -> 464520.22 | O23: =I23+L23 -> 605884.19
D25: 일반인 | E25: 노동자 | F25: 설계자
C26: 수입 | D26: 5000 | E26: 5000 | F26: 5000
C27: 제어 지출 | D27: 2400 | E27: 1500 | F27: 400
C28: 고정 지출 | D28: 1500 | E28: 1500 | F28: 1500
C29: Balance | D29: =D26-D27-D28 -> 1100 | E29: =E26-E27-E28 -> 2000 | F29: =F26-F27-F28 -> 3100

Sheet 매핑초안
A1: 대분류 | B1: 소분류 | C1: 항목명 | D1: 방법 | E1: 설계자 접근 핵심 | F1: 설계자_월 | G1: 일반인_월 | H1: 노동자_월 | I1: 싱글남 | J1: 싱글여 | K1: 커플 | L1: 가족(육아) | M1: 시니어 | N1: 평가
A2: 주거 | B2: 위치/임대 | C2: 위치 포지셔닝 | D2: positioning | E2: 교통+생활권 균형 잡힌 중간 위치 선택 | F2: 0 | G2: 150000 | H2: 150000 | I2: ○ | J2: ○ | K2: ○ | L2: ○ | M2: ○ | N2: drop: 너무 오지랍임
A3: 주거 | B3: 냉난방 | C3: 효과 부위만 투자 | D3: effectiveness | E3: 온수매트로 방 전체 난방 대신 국소 난방 | F3: 30000 | G3: 150000 | H3: 150000 | I3: ○ | J3: ○ | K3: ○ | L3: ○ | M3: ○
A4: 주거 | B4: 가구/인테리어 | C4: 대체품·중고 | D4: alternative | E4: 전열교환기 프레임에 스틸자 / 이케아+중고 조합 | F4: 5000 | G4: 60000 | H4: 30000 | I4: ○ | J4: ○ | K4: ○ | L4: ○ | M4: ○
A5: 주거 | B5: 가구/인테리어 | C5: ikea mulig | D5: right spec | E5: 이케아 mulig 행거는 저가, 최소 공간, 건조대 활용 가능 | F5: =19800/12/10 -> 165 | G5: =250000/12/2 -> 10416.667 | H5: =160000/12/2 -> 6666.6667 | I5: ○ | J5: ○ | K5: ○ | L5: ○ | M5: ○ | N5: 신규
A6: 주거 | B6: 공기청정기 | C6: right spec | D6: right spec | E6: 샤오미 + 3rd party 필터 직접 교체 | F6: 2167 | G6: 40000 | H6: 10000 | I6: ○ | J6: ○ | K6: ○ | L6: ○ | M6: ○
A7: 주거 | B7: 정수기 | C7: 부품 교환 | D7: 부품 교환 | E7: 필터 직구 후 자가 교환 (렌탈 불필요) | F7: 11625 | G7: 45000 | H7: 20000 | I7: ○ | J7: ○ | K7: ○ | L7: ○ | M7: ○
A8: 주거 | B8: 가습기 | C8: right spec | D8: right spec | E8: 샤오미 저가형으로 충분 | F8: 625 | G8: 20000 | H8: 10000 | I8: ○ | J8: ○ | K8: ○ | L8: ○ | M8: ○
A9: 주거 | B9: 조명 | C9: DIY | D9: DIY | E9: LED 전구 + 한지로 직접 제작 | F9: 200 | G9: 1000 | H9: 0 | I9: ○ | J9: ○ | K9: ○ | L9: ○ | M9: ○
A10: 주거 | B10: 유지보수 (조명·힌지·문고리) | C10: 직접 교환 | D10: 유지보수 | E10: 공구 구비 후 셀프 교체 | F10: 3000 | G10: 15000 | H10: 3000 | I10: ○ | J10: ○ | K10: ○ | L10: ○ | M10: ○
A11: 주거 | B11: 비데 필터 | C11: 자가 교환 | D11: 부품 교환 | E11: 필터 직구 후 직접 교체 | F11: 3000 | G11: 20000 | H11: 3000 | I11: ○ | J11: ○ | K11: ○ | L11: ○ | M11: ○
A12: 주거 | B12: 가스레인지 | C12: 자가 세척 | D12: 유지보수 | E12: 기름망 직접 세척 (청소업체 불필요) | F12: 1000 | G12: 8333 | H12: 1000 | I12: ○ | J12: ○ | K12: ○ | L12: ○ | M12: ○
A13: 주거 | B13: 통신비 | C13: 공기계+알뜰폰 | D13: right spec | E13: 공기계 구입 후 알뜰폰 조합 / 아이폰 계약 만료 후 장기 사용 | F13: 15000 | G13: 80000 | H13: 40000 | I13: ○ | J13: ○ | K13: ○ | L13: ○ | M13: ○
A14: 주거 | B14: 청소·세탁용품 | C14: condensate | D14: condensate | E14: 농축 세제 소분 / 다회용 행주로 키친타올 대체 | F14: 5000 | G14: 30000 | H14: 15000 | I14: ○ | J14: ○ | K14: ○ | L14: ○ | M14: ○
A15: 주거 | B15: 청소기 | C15: right spec | D15: right spec | E15: 신일 등 저가 무선 청소기 (다이슨 대비 동일 효과) | F15: 15000 | G15: 80000 | H15: 30000 | I15: ○ | J15: ○ | K15: ○ | L15: ○ | M15: ○
A16: 주거 | B16: 침구 | C16: 솜이불 기준 | D16: right spec | E16: 솜이불 사용 (no goose down) — 내용연한 유사, 촉감 좋고 털 날림 없음 | F16: 5000 | G16: 50000 | H16: 20000 | I16: ○ | J16: ○ | K16: ○ | L16: ○ | M16: ○
A17: 교통 | B17: 자동차 보험 | C17: 마일리지+운전점수+블랙박스 | D17: right spec | E17: 다이렉트 보험 + 마일리지·운전점수·블랙박스 할인 적용 | F17: 30000 | G17: 80000 | H17: 60000 | I17: ○ | J17: ○ | K17: ○ | L17: ○ | M17: △
... A24: 식 | B24: 건강보조제·비타민 | C24: 흡수율 기반 최소 섭취 | D24: right spec | E24: 성분표 기반 선택 / 흡수율 감안해 직관 대비 1/2만 섭취 | F24: 15000 | G24: 60000 | H24: 30000 | I24: ○ | J24: ○ | K24: ○ | L24: △ | M24: ○
A25: 의 | B25: 속옷·내의 (남성) | C25: 대량 통일 구입 | D25: simplify | E25: 국산 국민내의 대량 구입(좋은 사람들, BYC 등) | F25: 3000 | G25: 20000 | H25: 10000 | I25: ○
A26: 의 | B26: 아우터·이너 | C26: 아울렛 | D26: right spec | E26: 기능성 이너 아울렛 매대 구입 | F26: 8333 | G26: 33333 | H26: 15000 | I26: ○ | J26: ○ | K26: ○ | L26: ○ | M26: ○
A27: 의 | B27: 신발 밑창 | C27: 수선 | D27: 유지보수 | E27: 비브람 밑창 교환으로 신발 수명 연장 | F27: 7167 | G27: 16667 | H27: 10000 | I27: ○ | J27: ○ | K27: ○ | L27: ○ | M27: ○
A28: 의 | B28: 가죽제품 | C28: 유지보수 | D28: 유지보수 | E28: 가죽 정기 컨디셔닝으로 수명 연장 | F28: 2000 | G28: 30000 | H28: 15000 | I28: ○ | J28: ○ | K28: ○ | L28: ○ | M28: ○
A29: 의 | B29: 개인용품 (샴푸·바디워시) | C29: 소분 용기 활용 | D29: sharing | E29: 대용량 구입 후 소분 용기 이용 | F29: 1000 | G29: 15000 | H29: 5000 | I29: ○ | J29: ○ | K29: ○ | L29: ○ | M29: ○
A30: 의 | B30: 면도기·면도날 (남성) | C30: 질레트+고무판+클렌징폼 | D30: right spec | E30: 고품질 질레트 대량 구입 + 고무판으로 날 수명 연장 + 클렌징폼을 면도크림 대용 | F30: 3000 | G30: 15000 | H30: 8000 | I30: ○
A31: 의 | B31: 화장품 기초 (스킨·로션·세럼) | C31: 성분 기반 더마 브랜드 | D31: right spec | E31: 닥터지·코스알엑스·바이오더마·세타필 등 (백화점 프리미엄 불필요) | J31: ○ | K31: ○ | L31: ○
A32: 의 | B32: 화장품 색조 | C32: minimalist 1세트 | D32: simplify | E32: daily 1세트로 통일 / 단종 임박 할인 구입 | J32: ○ | K32: ○ | L32: ○
A33: 의 | B33: 헤어케어 (염색·펌) | C33: 홈 트리트먼트 병행 | D33: not over change | E33: 미용실 주기 늘리기 + 홈 트리트먼트로 보완 | J33: ○ | K33: ○ | L33: ○
A34: 건강 | B34: 치과 예방 | C34: 물리적 예방 관리 | D34: effectiveness | E34: 이쑤시개·치실·물분사기로 일상 물리적 관리 → 치과 방문 빈도 최소화 | F34: 5000 | G34: 30000 | H34: 10000 | I34: ○ | J34: ○ | K34: ○ | L34: ○ | M34: ○
A35: 건강 | B35: 안경·렌즈 | C35: 고가 1개 장기 사용 | D35: right spec | E35: 고품질 안경 1개 장기 사용 / 렌즈는 온라인 직구 | F35: 5000 | G35: 30000 | H35: 15000 | I35: ○ | J35: ○ | K35: ○ | L35: ○ | M35: ○ | N35: 렌즈 구매 요령 필요한가? 보통은 안경 or 라식 아닌가?
A36: 기호 | B36: 커피 | C36: DIY | D36: DIY | E36: 게샤 등 고품질 원두 직접 드립 / 드립백 자작 or 드립 필터만 구매 | F36: 22500 | G36: 180000 | H36: 75000 | I36: ○ | J36: ○ | K36: ○ | L36: ○ | M36: ○
A37: 기호 | B37: 차·음료 | C37: condensate | D37: condensate | E37: 녹차 티백도 좋지만, 티백 구입하여 자작하면 품질이 더 나음 | F37: 5000 | G37: 80000 | H37: 40000 | I37: ○ | J37: ○ | K37: ○ | L37: ○ | M37: ○
A38: 기호 | B38: 주류 | C38: right spec | D38: right spec | E38: 독주(안동소주, VSOP 꼬냑) +얼음 : 낮은 부피, 안주 과식 방지 | F38: 30000 | G38: 120000 | H38: 60000 | I38: ○ | J38: △ | K38: △ | L38: X | M38: △
A39: 기호 | B39: 간식·견과류 | C39: simplify | D39: simplify | E39: 캐슈넛·야채크래커 등 통일하여 대용량 구입 | F39: 20000 | G39: 200000 | H39: 100000 | I39: ○ | J39: ○ | K39: ○ | L39: △ | M39: ○
A40: 취미 | B40: 오디오 | C40: 중고+DIY | D40: 중고품 당근 | E40: 90~2000년대 중고 오디오 컴포넌트 | F40: 58333 | G40: 0 | H40: 20000 | I40: ○ | J40: △ | K40: △ | L40: X | M40: △
A41: 취미 | B41: 사진·카메라 | C41: 중고 | D41: 중고품 당근 | E41: 중형 카메라·렌즈 중고 구입 | F41: 29167 | G41: 0 | H41: 10000 | I41: ○ | J41: ○ | K41: △ | L41: X | M41: △
A42: 취미 | B42: 스포츠 용품 | C42: 중고+right spec | D42: 중고품 당근 | E42: 등산·낚시·골프채 중고 구입 | F42: 15000 | G42: 100000 | H42: 40000 | I42: ○ | J42: ○ | K42: ○ | L42: △ | M42: ○
A43: 취미 | B43: 비일상 가방 | C43: 중고 | D43: 중고품 당근 | E43: 보스턴백 등 중고 구입 | F43: 833 | G43: 6944 | H43: 4000 | I43: ○ | J43: ○ | K43: ○ | L43: △ | M43: ○
A44: 취미 | B44: 피트니스 | C44: right spec | D44: positioning | E44: 아파트 헬스장 | F44: 45000 | G44: 100000 | H44: 60000 | I44: ○ | J44: ○ | K44: ○ | L44: △ | M44: ○
A45: 취미 | B45: 피트니스 | C45: 의사 결정 후 구입 | D45: flexibility | E45: 연간 회원권 중고 구입 | N45: 추가
A46: 취미 | B46: 반려식물 | C46: DIY | D46: DIY | E46: 소형 포트 화분 직접 육성 | F46: 3000 | G46: 30000 | H46: 15000 | I46: ○ | J46: ○ | K46: ○ | L46: ○ | M46: ○
A47: 취미 | B47: 여성 취미 (공예·요가·필라테스) | C47: 원데이 우선 | D47: right spec | E47: 원데이 클래스로 먼저 체험 → 정기 등록 결정 | J47: ○ | K47: ○ | L47: ○
A48: 취미 | B48: 반려동물 사료 | C48: right spec | D48: right spec | E48: 성분표 기반 선택 / 대용량 직구 | F48: 30000 | G48: 60000 | H48: 40000 | I48: △ | J48: △ | K48: △ | L48: △ | M48: △
A49: 취미 | B49: 반려동물 병원 | C49: 예방 중심 | D49: effectiveness | E49: 예방접종·정기검진 준수로 치료비 예방 | F49: 10000 | G49: 30000 | H49: 15000 | I49: △ | J49: △ | K49: △ | L49: △ | M49: △
A50: 취미 | B50: 반려동물 미용 | C50: DIY | D50: DIY | E50: 셀프 목욕·빗질 (반려동물과의 시간으로 인식) | F50: 5000 | G50: 30000 | H50: 10000 | I50: △ | J50: △ | K50: △ | L50: △ | M50: △
A51: IT | B51: PC 업그레이드 | C51: 부품 교환 | D51: 부품 교환 | E51: RAM/SSD 추가로 교체 없이 수명 연장 | F51: 8333 | G51: 62500 | H51: 30000 | I51: ○ | J51: ○ | K51: ○ | L51: ○ | M51: △
A52: IT | B52: Self-hosting | C52: DIY | D52: DIY | E52: Nextcloud 등으로 클라우드 구독료 제로화 | F52: 5000 | G52: 50000 | H52: 20000 | I52: ○ | J52: △ | K52: △ | L52: X | M52: △
A53: IT | B53: 마우스·키보드 | C53: right spec | D53: right spec | E53: 로지텍 기본·독거미 키보드 | F53: 1250 | G53: 15000 | H53: 8000 | I53: ○ | J53: ○ | K53: ○ | L53: ○ | M53: △
A54: IT | B54: 모니터 | C54: right spec | D54: right spec | E54: 120hz 4K 한번 구입 후 장기 사용 | F54: 10000 | G54: 30000 | H54: 20000 | I54: ○ | J54: ○ | K54: ○ | L54: ○ | M54: ○
A55: IT | B55: 태블릿 (아이패드) | C55: right spec | D55: right spec | E55: 일반형 wifi 모델 | F55: 8667 | G55: 41667 | H55: 20000 | I55: ○ | J55: ○ | K55: ○ | L55: ○ | M55: ○
A56: IT | B56: 고성능 PC·Mac | C56: 집중 투자 후 재활용 | D56: right spec | E56: Mac Studio CPU/RAM에만 집중투자 / 구형은 재활용 | F56: 30000 | G56: 0 | H56: 10000 | I56: ○ | J56: ○ | K56: ○ | L56: ○ | M56: △
A57: IT | B57: 구형 기기 재활용 | C57: relocation | D57: relocation | E57: 아이맥→인터넷전용 / 아이폰→리모컨 / 맥북→크램쉘 | F57: 0 | G57: 110000 | H57: 55000 | I57: ○ | J57: ○ | K57: ○ | L57: ○ | M57: ○
A58: IT | B58: 스트리밍 서비스 | C58: 1개 구독·제대로 볼 것 | D58: 구독 최적화 | E58: 1개만 구독 후 완전히 활용 / 광고형 요금제 또는 가족 계정 공유 | F58: 5000 | G58: 30000 | H58: 10000 | I58: ○ | J58: ○ | K58: ○ | L58: ○ | M58: ○
A59: 생활 | B59: 다용도 제품 (WD-40·바세린·니베아) | C59: 1타 N피 | D59: 1타 N피 | E59: 한 제품을 여러 용도로 활용 | F59: 1500 | G59: 15000 | H59: 15000 | I59: ○ | J59: ○ | K59: ○ | L59: ○ | M59: ○
... A72: 여행 | B72: 해외 여행 | C72: 비수기+마일리지 | D72: positioning | E72: 비수기 선택 / 마일리지 카드 적립 후 비즈니스석 | F72: 50000 | G72: 200000 | H72: 80000 | I72: ○ | J72: ○ | K72: ○ | L72: △ | M72: ○
A73: 육아 | B73: 장난감 | C73: 중고+세척 | D73: 중고품 당근 | E73: 당근 중고 구입 / 빨래망 세척으로 위생 해결 | L73: ○
A74: 육아 | B74: 아이 의류 | C74: 지인 네트워크 우선 | D74: sharing | E74: 지인 네트워크로 받기 우선 / 당근으로 보완 | L74: ○
A75: 육아 | B75: 육아 용품 (유모차·바운서 등) | C75: 중고 | D75: 중고품 당근 | E75: 중고 구입 / 필요 기간만 사용 (특히 유모차) | L75: ○
A76: 관리 | B76: 신용카드 | C76: 1개 운영 | D76: 카드사 할인 | E76: 할인카드 1개만 / 조건 맞추려는 불필요 소비 차단 | F76: 0 | G76: 300000 | H76: 150000 | I76: ○ | J76: ○ | K76: ○ | L76: ○ | M76: ○
A77: 관리 | B77: 구독 서비스 전체 | C77: 주기적 점검 | D77: 구독 최적화 | E77: 매일 쓰는 것만 유지 / 연 1회 전체 검토 | F77: 0 | G77: 50000 | H77: 20000 | I77: ○ | J77: ○ | K77: ○ | L77: ○ | M77: ○
A78: 관리 | B78: 유효기간 관리 | C78: 미리알림 앱 | D78: 유효기간 | E78: 필터·식재료·보험·면허 유효기간 앱 등록 | F78: 0 | G78: 150000 | H78: 50000 | I78: ○ | J78: ○ | K78: ○ | L78: ○ | M78: ○
A79: 관리 | B79: 보험 | C79: 실손 1개+재테크 | D79: right spec | E79: 실손 보험 외 전액 재테크 / 중복 보험 제거 | F79: 30000 | G79: 100000 | H79: 60000 | I79: ○ | J79: ○ | K79: ○ | L79: ○ | M79: ○
A80: 관리 | B80: 절세 투자 (ISA·IRP) | C80: ISA 우선 | D80: positioning | E80: ISA 비과세 한도 우선 / IRP는 장기 관점으로 유동성과 절세 균형 | F80: 0 | G80: 50000 | H80: 10000 | I80: ○ | J80: ○ | K80: ○ | L80: ○ | M80: ○
A81: 관리 | B81: 자동이체 점검 | C81: 주기적 감사 | D81: 구독 최적화 | E81: 불필요 자동이체 연 2회 전체 확인 | F81: 0 | G81: 30000 | H81: 5000 | I81: ○ | J81: ○ | K81: ○ | L81: ○ | M81: ○
A82: 관리 | B82: 육아 관련 정부 지원 | C82: 포지셔닝 | D82: positioning | E82: 아동수당·육아휴직·공공 보육시설 최대 활용 | L82: ○
A83: 관리 | B83: 공공 복지 서비스 | C83: 포지셔닝 | D83: positioning | E83: 구청 수영장·문화센터·시니어 돌봄 서비스 등 납세 서비스 최대 활용 | F83: 5000 | G83: 30000 | H83: 10000 | I83: ○ | J83: ○ | K83: ○ | L83: ○ | M83: ○

Sheet 매핑v2
A1: 대분류 | B1: 소분류 | C1: approach | D1: 실행방법 | E1: 설계자_월 | F1: 일반인_월 | G1: 노동자_월 | H1: 싱글남 | I1: 싱글여 | J1: 커플 | K1: 가족(육아) | L1: 시니어
A2: 주거 | B2: 냉난방 | C2: effectiveness | D2: 온수매트로 방 전체 난방 대신 국소 난방 | E2: 30000 | F2: 150000 | G2: 150000 | H2: ○ | I2: ○ | J2: ○ | K2: ○ | L2: ○
A3: 주거 | B3: 가구/인테리어 | C3: alternative | D3: 전열교환기 프레임에 스틸자 / 이케아+중고 조합 | E3: 5000 | F3: 60000 | G3: 30000 | H3: ○ | I3: ○ | J3: ○ | K3: ○ | L3: ○
A4: 주거 | B4: 가구/인테리어 | C4: right spec | D4: 이케아 mulig 행거: 저가·최소 공간·건조대 겸용 | E4: 165 | F4: 10417 | G4: 6667 | H4: ○ | I4: ○ | J4: ○ | K4: ○ | L4: ○
A5: 주거 | B5: 공기청정기 | C5: right spec | D5: 샤오미 + 3rd party 필터 직접 교체 | E5: 2167 | F5: 40000 | G5: 10000 | H5: ○ | I5: ○ | J5: ○ | K5: ○ | L5: ○
A6: 주거 | B6: 정수기 | C6: 부품 교환 | D6: 필터 직구 후 자가 교환 (렌탈 불필요) | E6: 11625 | F6: 45000 | G6: 20000 | H6: ○ | I6: ○ | J6: ○ | K6: ○ | L6: ○
A7: 주거 | B7: 가습기 | C7: right spec | D7: 샤오미 저가형으로 충분 | E7: 625 | F7: 20000 | G7: 10000 | H7: ○ | I7: ○ | J7: ○ | K7: ○ | L7: ○
A8: 주거 | B8: 조명 | C8: DIY | D8: LED 전구 + 한지로 직접 제작 | E8: 200 | F8: 1000 | G8: 0 | H8: ○ | I8: ○ | J8: ○ | K8: ○ | L8: ○
A9: 주거 | B9: 유지보수 (조명·힌지·문고리) | C9: 유지보수 | D9: 공구 구비 후 셀프 교체 | E9: 3000 | F9: 15000 | G9: 3000 | H9: ○ | I9: ○ | J9: ○ | K9: ○ | L9: ○
A10: 주거 | B10: 비데 필터 | C10: 부품 교환 | D10: 필터 직구 후 직접 교체 | E10: 3000 | F10: 20000 | G10: 3000 | H10: ○ | I10: ○ | J10: ○ | K10: ○ | L10: ○
A11: 주거 | B11: 가스레인지 | C11: 유지보수 | D11: 기름망 직접 세척 (청소업체 불필요) | E11: 1000 | F11: 8333 | G11: 1000 | H11: ○ | I11: ○ | J11: ○ | K11: ○ | L11: ○
A12: 주거 | B12: 통신비 | C12: right spec | D12: 공기계 구입 후 알뜰폰 조합 / 아이폰 계약 만료 후 장기 사용 | E12: 15000 | F12: 80000 | G12: 40000 | H12: ○ | I12: ○ | J12: ○ | K12: ○ | L12: ○
A13: 주거 | B13: 청소·세탁용품 | C13: condensate | D13: 농축 세제 소분 / 다회용 행주로 키친타올 대체 | E13: 5000 | F13: 30000 | G13: 15000 | H13: ○ | I13: ○ | J13: ○ | K13: ○ | L13: ○
... A29: 의 | B29: 면도기·면도날 (남성) | C29: right spec | D29: 고품질 질레트 대량 구입 + 고무판으로 날 수명 연장 + 클렌징폼을 면도크림 대용 | E29: 3000 | F29: 15000 | G29: 8000 | H29: ○ | I29: X | J29: ○ | K29: ○ | L29: ○
A30: 의 | B30: 화장품 기초 (스킨·로션·세럼) | C30: right spec | D30: 닥터지·코스알엑스·바이오더마·세타필 등 (백화점 프리미엄 불필요) | I30: ○ | J30: ○ | K30: ○
A31: 의 | B31: 화장품 색조 | C31: simplify | D31: daily 1세트로 통일 / 단종 임박 할인 구입 | I31: ○ | J31: ○ | K31: ○
A32: 의 | B32: 헤어케어 (염색·펌) | C32: not over change | D32: 미용실 주기 늘리기 + 홈 트리트먼트로 보완 | I32: ○ | J32: ○ | K32: ○
A33: 건강 | B33: 치과 예방 | C33: effectiveness | D33: 이쑤시개·치실·물분사기로 일상 물리적 관리 → 치과 방문 빈도 최소화 | E33: 5000 | F33: 30000 | G33: 10000 | H33: ○ | I33: ○ | J33: ○ | K33: ○ | L33: ○
A34: 건강 | B34: 안경·렌즈 | C34: right spec | D34: 고품질 안경 1개 장기 사용 / 렌즈는 온라인 직구 | E34: 5000 | F34: 30000 | G34: 15000 | H34: ○ | I34: ○ | J34: ○ | K34: ○ | L34: ○
A35: 기호 | B35: 커피 | C35: DIY | D35: 게샤 등 고품질 원두 직접 드립 / 드립백 자작 또는 드립 필터만 구매 | E35: 22500 | F35: 180000 | G35: 75000 | H35: ○ | I35: ○ | J35: ○ | K35: ○ | L35: ○
A36: 기호 | B36: 차·음료 | C36: condensate | D36: 티백 직접 구입해 우리기 — 기성 티백보다 품질 우수 | E36: 5000 | F36: 80000 | G36: 40000 | H36: ○ | I36: ○ | J36: ○ | K36: ○ | L36: ○
A37: 기호 | B37: 주류 | C37: right spec | D37: 독주(안동소주·VSOP 꼬냑) + 얼음 — 부피 낮고 안주 과식 방지 | E37: 30000 | F37: 120000 | G37: 60000 | H37: ○ | I37: △ | J37: △ | K37: X | L37: △
A38: 기호 | B38: 간식·견과류 | C38: simplify | D38: 캐슈넛·야채크래커 등 통일하여 대용량 구입 | E38: 20000 | F38: 200000 | G38: 100000 | H38: ○ | I38: ○ | J38: ○ | K38: △ | L38: ○
A39: 취미 | B39: 오디오 | C39: 중고품 당근 | D39: 90~2000년대 중고 오디오 컴포넌트 (당근·세컨웨이브) | E39: 58333 | F39: 0 | G39: 20000 | H39: ○ | I39: △ | J39: △ | K39: X | L39: △
A40: 취미 | B40: 사진·카메라 | C40: 중고품 당근 | D40: 중형 카메라·렌즈 중고 구입 | E40: 29167 | F40: 0 | G40: 10000 | H40: ○ | I40: ○ | J40: △ | K40: X | L40: △
A41: 취미 | B41: 스포츠 용품 | C41: 중고품 당근 | D41: 등산·낚시·골프채 중고 구입 | E41: 15000 | F41: 100000 | G41: 40000 | H41: ○ | I41: ○ | J41: ○ | K41: △ | L41: ○
A42: 취미 | B42: 비일상 가방 | C42: 중고품 당근 | D42: 보스턴백 등 비일상 가방 중고 구입 | E42: 833 | F42: 6944 | G42: 4000 | H42: ○ | I42: ○ | J42: ○ | K42: △ | L42: ○
A43: 취미 | B43: 피트니스 | C43: positioning | D43: 아파트 헬스장 / 구청 헬스장 이용 | E43: 45000 | F43: 100000 | G43: 60000 | H43: ○ | I43: ○ | J43: ○ | K43: △ | L43: ○
A44: 취미 | B44: 피트니스 | C44: 중고품 당근 | D44: 연간 회원권 중고 구입 (체험 후 지속 여부 결정 선행) | H44: ○ | I44: ○ | J44: ○ | K44: △ | L44: ○
A45: 취미 | B45: 반려식물 | C45: DIY | D45: 소형 포트 화분 직접 육성 | E45: 3000 | F45: 30000 | G45: 15000 | H45: ○ | I45: ○ | J45: ○ | K45: ○ | L45: ○
A46: 취미 | B46: 여성 취미 (공예·요가·필라테스) | C46: right spec | D46: 원데이 클래스로 먼저 체험 → 정기 등록 결정 | I46: ○ | J46: ○ | K46: ○
A47: 취미 | B47: 반려동물 사료 | C47: right spec | D47: 성분표 기반 선택 / 대용량 직구 | E47: 30000 | F47: 60000 | G47: 40000 | H47: △ | I47: △ | J47: △ | K47: △ | L47: △
A48: 취미 | B48: 반려동물 병원 | C48: effectiveness | D48: 예방접종·정기검진 준수로 치료비 예방 | E48: 10000 | F48: 30000 | G48: 15000 | H48: △ | I48: △ | J48: △ | K48: △ | L48: △
A49: 취미 | B49: 반려동물 미용 | C49: DIY | D49: 셀프 목욕·빗질 (반려동물과의 놀이 시간으로 인식) | E49: 5000 | F49: 30000 | G49: 10000 | H49: △ | I49: △ | J49: △ | K49: △ | L49: △
A50: IT | B50: PC 업그레이드 | C50: 부품 교환 | D50: RAM/SSD 추가로 본체 교체 없이 수명 연장 | E50: 8333 | F50: 62500 | G50: 30000 | H50: ○ | I50: ○ | J50: ○ | K50: ○ | L50: △
A51: IT | B51: Self-hosting | C51: DIY | D51: Nextcloud 등으로 클라우드 구독료 제로화 | E51: 5000 | F51: 50000 | G51: 20000 | H51: ○ | I51: △ | J51: △ | K51: X | L51: △
A52: IT | B52: 마우스·키보드 | C52: right spec | D52: 로지텍 기본·독거미 키보드 | E52: 1250 | F52: 15000 | G52: 8000 | H52: ○ | I52: ○ | J52: ○ | K52: ○ | L52: △
A53: IT | B53: 모니터 | C53: right spec | D53: 120hz 4K 한번 구입 후 장기 사용 | E53: 10000 | F53: 30000 | G53: 20000 | H53: ○ | I53: ○ | J53: ○ | K53: ○ | L53: ○
A54: IT | B54: 태블릿 (아이패드) | C54: right spec | D54: 일반형 wifi 모델 | E54: 8667 | F54: 41667 | G54: 20000 | H54: ○ | I54: ○ | J54: ○ | K54: ○ | L54: ○
A55: IT | B55: 고성능 PC·Mac | C55: right spec | D55: Mac Studio CPU/RAM에만 집중투자 / 구형은 재활용 | E55: 30000 | F55: 0 | G55: 10000 | H55: ○ | I55: ○ | J55: ○ | K55: ○ | L55: △
A56: IT | B56: 구형 기기 재활용 | C56: relocation | D56: 아이맥→인터넷전용 / 아이폰→리모컨 / 맥북→크램쉘 | E56: 0 | F56: 110000 | G56: 55000 | H56: ○ | I56: ○ | J56: ○ | K56: ○ | L56: ○
A57: IT | B57: 스트리밍 서비스 | C57: 구독 최적화 | D57: 1개만 구독 후 완전히 활용 / 광고형 요금제 또는 가족 계정 공유 | E57: 5000 | F57: 30000 | G57: 10000 | H57: ○ | I57: ○ | J57: ○ | K57: ○ | L57: ○
A58: 생활 | B58: 다용도 제품 (WD-40·바세린·니베아) | C58: 1타 N피 | D58: 한 제품을 여러 용도로 활용 | E58: 1500 | F58: 15000 | G58: 15000 | H58: ○ | I58: ○ | J58: ○ | K58: ○ | L58: ○
... A71: 여행 | B71: 해외 여행 | C71: positioning | D71: 비수기 선택 / 마일리지 카드 적립 후 비즈니스석 | E71: 50000 | F71: 200000 | G71: 80000 | H71: ○ | I71: ○ | J71: ○ | K71: △ | L71: ○
A72: 육아 | B72: 장난감 | C72: 중고품 당근 | D72: 당근 중고 구입 / 빨래망 세척으로 위생 해결 | K72: ○
A73: 육아 | B73: 아이 의류 | C73: sharing | D73: 지인 네트워크로 받기 우선 / 당근으로 보완 | K73: ○
A74: 육아 | B74: 육아 용품 (유모차·바운서 등) | C74: 중고품 당근 | D74: 중고 구입 / 필요 기간만 사용 (특히 유모차) | K74: ○
A75: 관리 | B75: 신용카드 | C75: 카드사 할인 | D75: 할인카드 1개만 — 조건 맞추려는 불필요 소비 차단 | E75: 0 | F75: 300000 | G75: 150000 | H75: ○ | I75: ○ | J75: ○ | K75: ○ | L75: ○
A76: 관리 | B76: 구독 서비스 전체 | C76: 구독 최적화 | D76: 매일 쓰는 것만 유지 / 연 1회 전체 검토 | E76: 0 | F76: 50000 | G76: 20000 | H76: ○ | I76: ○ | J76: ○ | K76: ○ | L76: ○
A77: 관리 | B77: 유효기간 관리 | C77: 유효기간 | D77: 필터·식재료·보험·면허 유효기간 앱 등록 | E77: 0 | F77: 150000 | G77: 50000 | H77: ○ | I77: ○ | J77: ○ | K77: ○ | L77: ○
A78: 관리 | B78: 보험 | C78: right spec | D78: 실손 보험 외 전액 재테크 / 중복 보험 제거 | E78: 30000 | F78: 100000 | G78: 60000 | H78: ○ | I78: ○ | J78: ○ | K78: ○ | L78: ○
A79: 관리 | B79: 절세 투자 (ISA·IRP) | C79: positioning | D79: ISA 비과세 한도 우선 / IRP는 장기 관점으로 유동성과 절세 균형 | E79: 0 | F79: 50000 | G79: 10000 | H79: ○ | I79: ○ | J79: ○ | K79: ○ | L79: ○
A80: 관리 | B80: 자동이체 점검 | C80: 구독 최적화 | D80: 불필요 자동이체 연 2회 전체 확인 | E80: 0 | F80: 30000 | G80: 5000 | H80: ○ | I80: ○ | J80: ○ | K80: ○ | L80: ○
A81: 관리 | B81: 육아 관련 정부 지원 | C81: positioning | D81: 아동수당·육아휴직·공공 보육시설 최대 활용 | K81: ○
A82: 관리 | B82: 공공 복지 서비스 | C82: positioning | D82: 구청 수영장·문화센터·시니어 돌봄 서비스 등 납세 서비스 최대 활용 | E82: 5000 | F82: 30000 | G82: 10000 | H82: ○ | I82: ○ | J82: ○ | K82: ○ | L82: ○

Sheet 비용분석
B1: 대분류 | C1: 소분류 | D1: approach | E1: 실행방법_설계자 | F1: 실행방법_일반인 | G1: 실행방법_노동자 | H1: 유형 | I1: 설계자_가격 | J1: 설계자_내용연수 | K1: 설계자_사용시간/빈도 | L1: 설계자_사용량 | M1: 설계자_단가 | N1: 설계자_소모품가격 | O1: 설계자_소모품내용연수 | P1: 설계자_월 | Q1: 유형_일반인 | R1: 일반인_가격 | S1: 일반인_내용연수 | T1: 일반인_사용시간 | U1: 일반인_사용량 | V1: 일반인_단가 | W1: 일반인_소모품가격 | X1: 일반인_소모품내용연수 | Y1: 일반인_월 | Z1: 유형_노동자 | AA1: 노동자_가격 | AB1: 노동자_내용연수 | AC1: 노동자_사용시간 | AD1: 노동자_사용량 | AE1: 노동자_단가 | AF1: 노동자_소모품가격 | AG1: 노동자_소모품내용연수 | AH1: 노동자_월 | AI1: 싱글남_설계자 | AJ1: 싱글남_설계자_확인 | AK1: 싱글남_일반인 | AL1: 싱글남_일반인_확인 | AM1: 싱글남_노동자 | AN1: 싱글남_노동자_확인 | AO1: 싱글여_설계자 | AP1: 싱글여_설계자_확인 | AQ1: 싱글여_일반인 | AR1: 싱글여_일반인_확인 | AS1: 싱글여_노동자 | AT1: 싱글여_노동자_확인 | AU1: 커플_설계자 | AV1: 커플_설계자_확인 | AW1: 커플_일반인 | AX1: 커플_일반인_확인 | AY1: 커플_노동자 | AZ1: 커플_노동자_확인 | BA1: 가족(육아)_설계자 | BB1: 가족(육아)_설계자_확인 | BC1: 가족(육아)_일반인 | BD1: 가족(육아)_일반인_확인 | BE1: 가족(육아)_노동자 | BF1: 가족(육아)_노동자_확인 | BG1: 시니어_설계자 | BH1: 시니어_설계자_확인 | BI1: 시니어_일반인 | BJ1: 원가절감_설계자 | BK1: 원가절감_일반인 | BL1: 원가절감_노동자 | BM1: 가치제고_설계자 | BN1: 가치제고_일반인 | BO1: 가치제고_노동자
A2: 1 | B2: 주거 | C2: 냉난방 | D2: effectiveness | E2: 온수매트로 방 전체 난방 대신 국소 난방 | F2: 안 쓰는 공간까지 보일러 풀가동 | G2: 일반인과 동일하게 전체 가동 | H2: 4 | I2: 250000 | J2: 7 | K2: 210 | L2: 0.25 | M2: 120 | P2: =IF($H2=1,IF(AND(I2<>"",J2<>""),I2/J2/12,""),IF($H2=2,IF(AND(K2<>"",L2<>"",M2<>""),K2*L2*M2,""),IF($H2=3,IF(AND(N2<>"",O2<>""),N2/O2/12,""),IF($H2=4,IF(AND(I2<>"",J2<>""),I2/J2/12,0)+IF(AND(K2<>"",L2<>"",M2<>""),K2*L2*M2,0),IF($H2=5,IF(AND(I2<>"",J2<>""),I2/J2/12,0)+IF(AND(N2<>"",O2<>""),N2/O2/12,0),IF($H2=6,IF(AND(K2<>"",L2<>"",M2<>""),K2*L2*M2,0)+IF(AND(N2<>"",O2<>""),N2/O2/12,0),"")))))) -> 9276.1905 | Q2: 2 | T2: =8*30 -> 240 | U2: 2.2 | V2: 900 | Y2: =IF($Q2=1,IF(AND(R2<>"",S2<>""),R2/S2/12,""),IF($Q2=2,IF(AND(T2<>"",U2<>"",V2<>""),T2*U2*V2,""),IF($Q2=3,IF(AND(W2<>"",X2<>""),W2/X2/12,""),IF($Q2=4,IF(AND(R2<>"",S2<>""),R2/S2/12,0)+IF(AND(T2<>"",U2<>"",V2<>""),T2*U2*V2,0),IF($Q2=5,IF(AND(R2<>"",S2<>""),R2/S2/12,0)+IF(AND(W2<>"",X2<>""),W2/X2/12,0),IF($Q2=6,IF(AND(T2<>"",U2<>"",V2<>""),T2*U2*V2,0)+IF(AND(W2<>"",X2<>""),W2/X2/12,0),"")))))) -> 475200 | Z2: 2 | AC2: =8*30 -> 240 | AD2: 2.2 | AE2: 900 | AH2: =IF($Z2=1,IF(AND(AA2<>"",AB2<>""),AA2/AB2/12,""),IF($Z2=2,IF(AND(AC2<>"",AD2<>"",AE2<>""),AC2*AD2*AE2,""),IF($Z2=3,IF(AND(AF2<>"",AG2<>""),AF2/AG2/12,""),IF($Z2=4,IF(AND(AA2<>"",AB2<>""),AA2/AB2/12,0)+IF(AND(AC2<>"",AD2<>"",AE2<>""),AC2*AD2*AE2,0),IF($Z2=5,IF(AND(AA2<>"",AB2<>""),AA2/AB2/12,0)+IF(AND(AF2<>"",AG2<>""),AF2/AG2/12,0),IF($Z2=6,IF(AND(AC2<>"",AD2<>"",AE2<>""),AC2*AD2*AE2,0)+IF(AND(AF2<>"",AG2<>""),AF2/AG2/12,0),"")))))) -> 475200 | AI2: =IF(매핑v2!H2="○",P2,"") -> 9276.1905 | AJ2: =IF(매핑v2!H2="○","○","X") -> ○ | AK2: =IF(매핑v2!H2="○",Y2,"") -> 475200 | AL2: =IF(매핑v2!H2="○","○","X") -> ○ | AM2: =IF(매핑v2!H2="○",AH2,"") -> 475200 | AN2: =IF(매핑v2!H2="○","○","X") -> ○ | AO2: =IF(매핑v2!I2="○",P2,"") -> 9276.1905 | AP2: =IF(매핑v2!I2="○","○","X") -> ○ | AQ2: =IF(매핑v2!I2="○",Y2,"") -> 475200 | AR2: =IF(매핑v2!I2="○","○","X") -> ○ | AS2: =IF(매핑v2!I2="○",AH2,"") -> 475200 | AT2: =IF(매핑v2!I2="○","○","X") -> ○ | AU2: =IF(매핑v2!J2="○",P2,"") -> 9276.1905 | AV2: =IF(매핑v2!J2="○","○","X") -> ○ | AW2: =IF(매핑v2!J2="○",Y2,"") -> 475200 | AX2: =IF(매핑v2!J2="○","○","X") -> ○ | AY2: =IF(매핑v2!J2="○",AH2,"") -> 475200 | AZ2: =IF(매핑v2!J2="○","○","X") -> ○ | BA2: =IF(매핑v2!K2="○",P2,"") -> 9276.1905 | BB2: =IF(매핑v2!K2="○","○","X") -> ○ | BC2: =IF(매핑v2!K2="○",Y2,"") -> 475200 | BD2: =IF(매핑v2!K2="○","○","X") -> ○ | BE2: =IF(매핑v2!K2="○",AH2,"") -> 475200 | BF2: =IF(매핑v2!K2="○","○","X") -> ○ | BG2: =IF(매핑v2!L2="○",P2,"") -> 9276.1905 | BH2: =IF(매핑v2!L2="○","○","X") -> ○ | BI2: =IF(매핑v2!L2="○",Y2,"") -> 475200 | BJ2: ○ | BK2: X | BL2: X | BM2: ○ | BN2: X | BO2: X
A3: 2 | B3: 주거 | C3: 가구/인테리어 | D3: alternative | E3: 아파트 전열교환기 필터 구입 및 스틸자로 프레임 강화 | F3: 프레임 부식으로 전열교환기 교환 | G3: 최저가 호환 프레임 검색에 2시간 소모, 결국 교환 | H3: 5 | I3: 5000 | J3: 5 | N3: 100000 | O3: 4 | P3: =IF($H3=1,IF(AND(I3<>"",J3<>""),I3/J3/12,""),IF($H3=2,IF(AND(K3<>"",L3<>"",M3<>""),K3*L3*M3,""),IF($H3=3,IF(AND(N3<>"",O3<>""),N3/O3/12,""),IF($H3=4,IF(AND(I3<>"",J3<>""),I3/J3/12,0)+IF(AND(K3<>"",L3<>"",M3<>""),K3*L3*M3,0),IF($H3=5,IF(AND(I3<>"",J3<>""),I3/J3/12,0)+IF(AND(N3<>"",O3<>""),N3/O3/12,0),IF($H3=6,IF(AND(K3<>"",L3<>"",M3<>""),K3*L3*M3,0)+IF(AND(N3<>"",O3<>""),N3/O3/12,0),"")))))) -> 2166.6667 | Q3: 5 | R3: 3000000 | S3: 5 | Y3: =IF($Q3=1,IF(AND(R3<>"",S3<>""),R3/S3/12,""),IF($Q3=2,IF(AND(T3<>"",U3<>"",V3<>""),T3*U3*V3,""),IF($Q3=3,IF(AND(W3<>"",X3<>""),W3/X3/12,""),IF($Q3=4,IF(AND(R3<>"",S3<>""),R3/S3/12,0)+IF(AND(T3<>"",U3<>"",V3<>""),T3*U3*V3,0),IF($Q3=5,IF(AND(R3<>"",S3<>""),R3/S3/12,0)+IF(AND(W3<>"",X3<>""),W3/X3/12,0),IF($Q3=6,IF(AND(T3<>"",U3<>"",V3<>""),T3*U3*V3,0)+IF(AND(W3<>"",X3<>""),W3/X3/12,0),"")))))) -> 50000 | Z3: 5 | AA3: 3000000 | AB3: 5 | AH3: =IF($Z3=1,IF(AND(AA3<>"",AB3<>""),AA3/AB3/12,""),IF($Z3=2,IF(AND(AC3<>"",AD3<>"",AE3<>""),AC3*AD3*AE3,""),IF($Z3=3,IF(AND(AF3<>"",AG3<>""),AF3/AG3/12,""),IF($Z3=4,IF(AND(AA3<>"",AB3<>""),AA3/AB3/12,0)+IF(AND(AC3<>"",AD3<>"",AE3<>""),AC3*AD3*AE3,0),IF($Z3=5,IF(AND(AA3<>"",AB3<>""),AA3/AB3/12,0)+IF(AND(AF3<>"",AG3<>""),AF3/AG3/12,0),IF($Z3=6,IF(AND(AC3<>"",AD3<>"",AE3<>""),AC3*AD3*AE3,0)+IF(AND(AF3<>"",AG3<>""),AF3/AG3/12,0),"")))))) -> 50000 | AI3: =IF(매핑v2!H3="○",P3,"") -> 2166.6667 | AJ3: =IF(매핑v2!H3="○","○","X") -> ○ | AK3: =IF(매핑v2!H3="○",Y3,"") -> 50000 | AL3: =IF(매핑v2!H3="○","○","X") -> ○ | AM3: =IF(매핑v2!H3="○",AH3,"") -> 50000 | AN3: =IF(매핑v2!H3="○","○","X") -> ○ | AO3: =IF(매핑v2!I3="○",P3,"") -> 2166.6667 | AP3: =IF(매핑v2!I3="○","○","X") -> ○ | AQ3: =IF(매핑v2!I3="○",Y3,"") -> 50000 | AR3: =IF(매핑v2!I3="○","○","X") -> ○ | AS3: =IF(매핑v2!I3="○",AH3,"") -> 50000 | AT3: =IF(매핑v2!I3="○","○","X") -> ○ | AU3: =IF(매핑v2!J3="○",P3,"") -> 2166.6667 | AV3: =IF(매핑v2!J3="○","○","X") -> ○ | AW3: =IF(매핑v2!J3="○",Y3,"") -> 50000 | AX3: =IF(매핑v2!J3="○","○","X") -> ○ | AY3: =IF(매핑v2!J3="○",AH3,"") -> 50000 | AZ3: =IF(매핑v2!J3="○","○","X") -> ○ | BA3: =IF(매핑v2!K3="○",P3,"") -> 2166.6667 | BB3: =IF(매핑v2!K3="○","○","X") -> ○ | BC3: =IF(매핑v2!K3="○",Y3,"") -> 50000 | BD3: =IF(매핑v2!K3="○","○","X") -> ○ | BE3: =IF(매핑v2!K3="○",AH3,"") -> 50000 | BF3: =IF(매핑v2!K3="○","○","X") -> ○ | BG3: =IF(매핑v2!L3="○",P3,"") -> 2166.6667 | BH3: =IF(매핑v2!L3="○","○","X") -> ○ | BI3: =IF(매핑v2!L3="○",Y3,"") -> 50000 | BJ3: ○ | BK3: X | BL3: ○ | BM3: ○ | BN3: X | BO3: X
A4: 3 | B4: 주거 | C4: 가구/인테리어 | D4: right spec | E4: 이케아 mulig 행거: 저가·최소 공간·건조대 겸용 | F4: 모든 옷은 붙박이 장에 걸고, 건조기 구입 | G4: 플라스틱 서랍장에 모든 옷을 접어서 넣고, 저가 건조대로 공간 희생 | H4: 1 | I4: 20000 | J4: 10 | P4: =IF($H4=1,IF(AND(I4<>"",J4<>""),I4/J4/12,""),IF($H4=2,IF(AND(K4<>"",L4<>"",M4<>""),K4*L4*M4,""),IF($H4=3,IF(AND(N4<>"",O4<>""),N4/O4/12,""),IF($H4=4,IF(AND(I4<>"",J4<>""),I4/J4/12,0)+IF(AND(K4<>"",L4<>"",M4<>""),K4*L4*M4,0),IF($H4=5,IF(AND(I4<>"",J4<>""),I4/J4/12,0)+IF(AND(N4<>"",O4<>""),N4/O4/12,0),IF($H4=6,IF(AND(K4<>"",L4<>"",M4<>""),K4*L4*M4,0)+IF(AND(N4<>"",O4<>""),N4/O4/12,0),"")))))) -> 166.66667 | Q4: 1 | R4: 15000000 | S4: 8 | W4: 1200000 | X4: 2 | Y4: =IF($Q4=1,IF(AND(R4<>"",S4<>""),R4/S4/12,""),IF($Q4=2,IF(AND(T4<>"",U4<>"",V4<>""),T4*U4*V4,""),IF($Q4=3,IF(AND(W4<>"",X4<>""),W4/X4/12,""),IF($Q4=4,IF(AND(R4<>"",S4<>""),R4/S4/12,0)+IF(AND(T4<>"",U4<>"",V4<>""),T4*U4*V4,0),IF($Q4=5,IF(AND(R4<>"",S4<>""),R4/S4/12,0)+IF(AND(W4<>"",X4<>""),W4/X4/12,0),IF($Q4=6,IF(AND(T4<>"",U4<>"",V4<>""),T4*U4*V4,0)+IF(AND(W4<>"",X4<>""),W4/X4/12,0),"")))))) -> 156250 | Z4: 1 | AA4: =60000+40000 -> 100000 | AB4: 2 | AF4: 1200000 | AG4: 2 | AH4: =IF($Z4=1,IF(AND(AA4<>"",AB4<>""),AA4/AB4/12,""),IF($Z4=2,IF(AND(AC4<>"",AD4<>"",AE4<>""),AC4*AD4*AE4,""),IF($Z4=3,IF(AND(AF4<>"",AG4<>""),AF4/AG4/12,""),IF($Z4=4,IF(AND(AA4<>"",AB4<>""),AA4/AB4/12,0)+IF(AND(AC4<>"",AD4<>"",AE4<>""),AC4*AD4*AE4,0),IF($Z4=5,IF(AND(AA4<>"",AB4<>""),AA4/AB4/12,0)+IF(AND(AF4<>"",AG4<>""),AF4/AG4/12,0),IF($Z4=6,IF(AND(AC4<>"",AD4<>"",AE4<>""),AC4*AD4*AE4,0)+IF(AND(AF4<>"",AG4<>""),AF4/AG4/12,0),"")))))) -> 4166.6667 | AI4: =IF(매핑v2!H4="○",P4,"") -> 166.66667 | AJ4: =IF(매핑v2!H4="○","○","X") -> ○ | AK4: =IF(매핑v2!H4="○",Y4,"") -> 156250 | AL4: =IF(매핑v2!H4="○","○","X") -> ○ | AM4: =IF(매핑v2!H4="○",AH4,"") -> 4166.6667 | AN4: =IF(매핑v2!H4="○","○","X") -> ○ | AO4: =IF(매핑v2!I4="○",P4,"") -> 166.66667 | AP4: =IF(매핑v2!I4="○","○","X") -> ○ | AQ4: =IF(매핑v2!I4="○",Y4,"") -> 156250 | AR4: =IF(매핑v2!I4="○","○","X") -> ○ | AS4: =IF(매핑v2!I4="○",AH4,"") -> 4166.6667 | AT4: =IF(매핑v2!I4="○","○","X") -> ○ | AU4: =IF(매핑v2!J4="○",P4,"") -> 166.66667 | AV4: =IF(매핑v2!J4="○","○","X") -> ○ | AW4: =IF(매핑v2!J4="○",Y4,"") -> 156250 | AX4: =IF(매핑v2!J4="○","○","X") -> ○ | AY4: =IF(매핑v2!J4="○",AH4,"") -> 4166.6667 | AZ4: =IF(매핑v2!J4="○","○","X") -> ○ | BA4: =IF(매핑v2!K4="○",P4,"") -> 166.66667 | BB4: =IF(매핑v2!K4="○","○","X") -> ○ | BC4: =IF(매핑v2!K4="○",Y4,"") -> 156250 | BD4: =IF(매핑v2!K4="○","○","X") -> ○ | BE4: =IF(매핑v2!K4="○",AH4,"") -> 4166.6667 | BF4: =IF(매핑v2!K4="○","○","X") -> ○ | BG4: =IF(매핑v2!L4="○",P4,"") -> 166.66667 | BH4: =IF(매핑v2!L4="○","○","X") -> ○ | BI4: =IF(매핑v2!L4="○",Y4,"") -> 156250 | BJ4: ○ | BK4: X | BL4: ○ | BM4: ○ | BN4: X | BO4: X
A5: 4 | B5: 주거 | C5: 공기청정기 | D5: right spec | E5: 샤오미 + 3rd party 필터 직접 교체 | F5: 하이엔드 브랜드 렌탈/구독료 상납 | G5: 필터 물세척해서 쓰려다 공기청정기 망가뜨림 | H5: 5 | I5: 40000 | J5: 5 | N5: 10000 | O5: 1 | P5: =IF($H5=1,IF(AND(I5<>"",J5<>""),I5/J5/12,""),IF($H5=2,IF(AND(K5<>"",L5<>"",M5<>""),K5*L5*M5,""),IF($H5=3,IF(AND(N5<>"",O5<>""),N5/O5/12,""),IF($H5=4,IF(AND(I5<>"",J5<>""),I5/J5/12,0)+IF(AND(K5<>"",L5<>"",M5<>""),K5*L5*M5,0),IF($H5=5,IF(AND(I5<>"",J5<>""),I5/J5/12,0)+IF(AND(N5<>"",O5<>""),N5/O5/12,0),IF($H5=6,IF(AND(K5<>"",L5<>"",M5<>""),K5*L5*M5,0)+IF(AND(N5<>"",O5<>""),N5/O5/12,0),"")))))) -> 1500 | Q5: 5 | T5: 1 | U5: 1 | V5: 48000 | W5: 60000 | X5: 0.5 | Y5: =IF($Q5=1,IF(AND(R5<>"",S5<>""),R5/S5/12,""),IF($Q5=2,IF(AND(T5<>"",U5<>"",V5<>""),T5*U5*V5,""),IF($Q5=3,IF(AND(W5<>"",X5<>""),W5/X5/12,""),IF($Q5=4,IF(AND(R5<>"",S5<>""),R5/S5/12,0)+IF(AND(T5<>"",U5<>"",V5<>""),T5*U5*V5,0),IF($Q5=5,IF(AND(R5<>"",S5<>""),R5/S5/12,0)+IF(AND(W5<>"",X5<>""),W5/X5/12,0),IF($Q5=6,IF(AND(T5<>"",U5<>"",V5<>""),T5*U5*V5,0)+IF(AND(W5<>"",X5<>""),W5/X5/12,0),"")))))) -> 10000 | Z5: 5 | AA5: 300000 | AB5: 1 | AF5: 60000 | AG5: 1 | AH5: =IF($Z5=1,IF(AND(AA5<>"",AB5<>""),AA5/AB5/12,""),IF($Z5=2,IF(AND(AC5<>"",AD5<>"",AE5<>""),AC5*AD5*AE5,""),IF($Z5=3,IF(AND(AF5<>"",AG5<>""),AF5/AG5/12,""),IF($Z5=4,IF(AND(AA5<>"",AB5<>""),AA5/AB5/12,0)+IF(AND(AC5<>"",AD5<>"",AE5<>""),AC5*AD5*AE5,0),IF($Z5=5,IF(AND(AA5<>"",AB5<>""),AA5/AB5/12,0)+IF(AND(AF5<>"",AG5<>""),AF5/AG5/12,0),IF($Z5=6,IF(AND(AC5<>"",AD5<>"",AE5<>""),AC5*AD5*AE5,0)+IF(AND(AF5<>"",AG5<>""),AF5/AG5/12,0),"")))))) -> 30000 | AI5: =IF(매핑v2!H5="○",P5,"") -> 1500 | AJ5: =IF(매핑v2!H5="○","○","X") -> ○ | AK5: =IF(매핑v2!H5="○",Y5,"") -> 10000 | AL5: =IF(매핑v2!H5="○","○","X") -> ○ | AM5: =IF(매핑v2!H5="○",AH5,"") -> 30000 | AN5: =IF(매핑v2!H5="○","○","X") -> ○ | AO5: =IF(매핑v2!I5="○",P5,"") -> 1500 | AP5: =IF(매핑v2!I5="○","○","X") -> ○ | AQ5: =IF(매핑v2!I5="○",Y5,"") -> 10000 | AR5: =IF(매핑v2!I5="○","○","X") -> ○ | AS5: =IF(매핑v2!I5="○",AH5,"") -> 30000 | AT5: =IF(매핑v2!I5="○","○","X") -> ○ | AU5: =IF(매핑v2!J5="○",P5,"") -> 1500 | AV5: =IF(매핑v2!J5="○","○","X") -> ○ | AW5: =IF(매핑v2!J5="○",Y5,"") -> 10000 | AX5: =IF(매핑v2!J5="○","○","X") -> ○ | AY5: =IF(매핑v2!J5="○",AH5,"") -> 30000 | AZ5: =IF(매핑v2!J5="○","○","X") -> ○ | BA5: =IF(매핑v2!K5="○",P5,"") -> 1500 | BB5: =IF(매핑v2!K5="○","○","X") -> ○ | BC5: =IF(매핑v2!K5="○",Y5,"") -> 10000 | BD5: =IF(매핑v2!K5="○","○","X") -> ○ | BE5: =IF(매핑v2!K5="○",AH5,"") -> 30000 | BF5: =IF(매핑v2!K5="○","○","X") -> ○ | BG5: =IF(매핑v2!L5="○",P5,"") -> 1500 | BH5: =IF(매핑v2!L5="○","○","X") -> ○ | BI5: =IF(매핑v2!L5="○",Y5,"") -> 10000 | BJ5: ○ | BK5: X | BL5: ○ | BM5: ○ | BN5: ○ | BO5: X
A6: 5 | B6: 주거 | C6: 정수기 | D6: 부품 교환 | E6: 필터 직구 후 자가 교환 (렌탈 불필요) | F6: 얼음/케어 포함 브랜드 렌탈 상납 | G6: 생수 최저가 검색 후 매번 문앞 이동 노동 | H6: 5 | I6: 200000 | J6: 5 | N6: 50000 | O6: 1 | P6: =IF($H6=1,IF(AND(I6<>"",J6<>""),I6/J6/12,""),IF($H6=2,IF(AND(K6<>"",L6<>"",M6<>""),K6*L6*M6,""),IF($H6=3,IF(AND(N6<>"",O6<>""),N6/O6/12,""),IF($H6=4,IF(AND(I6<>"",J6<>""),I6/J6/12,0)+IF(AND(K6<>"",L6<>"",M6<>""),K6*L6*M6,0),IF($H6=5,IF(AND(I6<>"",J6<>""),I6/J6/12,0)+IF(AND(N6<>"",O6<>""),N6/O6/12,0),IF($H6=6,IF(AND(K6<>"",L6<>"",M6<>""),K6*L6*M6,0)+IF(AND(N6<>"",O6<>""),N6/O6/12,0),"")))))) -> 7500 | Q6: 5 | T6: 1 | U6: 1 | V6: 45000 | Y6: =IF($Q6=1,IF(AND(R6<>"",S6<>""),R6/S6/12,""),IF($Q6=2,IF(AND(T6<>"",U6<>"",V6<>""),T6*U6*V6,""),IF($Q6=3,IF(AND(W6<>"",X6<>""),W6/X6/12,""),IF($Q6=4,IF(AND(R6<>"",S6<>""),R6/S6/12,0)+IF(AND(T6<>"",U6<>"",V6<>""),T6*U6*V6,0),IF($Q6=5,IF(AND(R6<>"",S6<>""),R6/S6/12,0)+IF(AND(W6<>"",X6<>""),W6/X6/12,0),IF($Q6=6,IF(AND(T6<>"",U6<>"",V6<>""),T6*U6*V6,0)+IF(AND(W6<>"",X6<>""),W6/X6/12,0),"")))))) -> 0 | Z6: 2 | AC6: 4 | AD6: 1 | AE6: 12000 | AH6: =IF($Z6=1,IF(AND(AA6<>"",AB6<>""),AA6/AB6/12,""),IF($Z6=2,IF(AND(AC6<>"",AD6<>"",AE6<>""),AC6*AD6*AE6,""),IF($Z6=3,IF(AND(AF6<>"",AG6<>""),AF6/AG6/12,""),IF($Z6=4,IF(AND(AA6<>"",AB6<>""),AA6/AB6/12,0)+IF(AND(AC6<>"",AD6<>"",AE6<>""),AC6*AD6*AE6,0),IF($Z6=5,IF(AND(AA6<>"",AB6<>""),AA6/AB6/12,0)+IF(AND(AF6<>"",AG6<>""),AF6/AG6/12,0),IF($Z6=6,IF(AND(AC6<>"",AD6<>"",AE6<>""),AC6*AD6*AE6,0)+IF(AND(AF6<>"",AG6<>""),AF6/AG6/12,0),"")))))) -> 48000 | AI6: =IF(매핑v2!H6="○",P6,"") -> 7500 | AJ6: =IF(매핑v2!H6="○","○","X") -> ○ | AK6: =IF(매핑v2!H6="○",Y6,"") -> 0 | AL6: =IF(매핑v2!H6="○","○","X") -> ○ | AM6: =IF(매핑v2!H6="○",AH6,"") -> 48000 | AN6: =IF(매핑v2!H6="○","○","X") -> ○ | AO6: =IF(매핑v2!I6="○",P6,"") -> 7500 | AP6: =IF(매핑v2!I6="○","○","X") -> ○ | AQ6: =IF(매핑v2!I6="○",Y6,"") -> 0 | AR6: =IF(매핑v2!I6="○","○","X") -> ○ | AS6: =IF(매핑v2!I6="○",AH6,"") -> 48000 | AT6: =IF(매핑v2!I6="○","○","X") -> ○ | AU6: =IF(매핑v2!J6="○",P6,"") -> 7500 | AV6: =IF(매핑v2!J6="○","○","X") -> ○ | AW6: =IF(매핑v2!J6="○",Y6,"") -> 0 | AX6: =IF(매핑v2!J6="○","○","X") -> ○ | AY6: =IF(매핑v2!J6="○",AH6,"") -> 48000 | AZ6: =IF(매핑v2!J6="○","○","X") -> ○ | BA6: =IF(매핑v2!K6="○",P6,"") -> 7500 | BB6: =IF(매핑v2!K6="○","○","X") -> ○ | BC6: =IF(매핑v2!K6="○",Y6,"") -> 0 | BD6: =IF(매핑v2!K6="○","○","X") -> ○ | BE6: =IF(매핑v2!K6="○",AH6,"") -> 48000 | BF6: =IF(매핑v2!K6="○","○","X") -> ○ | BG6: =IF(매핑v2!L6="○",P6,"") -> 7500 | BH6: =IF(매핑v2!L6="○","○","X") -> ○ | BI6: =IF(매핑v2!L6="○",Y6,"") -> 0 | BJ6: ○ | BK6: X | BL6: ○ | BM6: ○ | BN6: ○ | BO6: X
A7: 6 | B7: 주거 | C7: 가습기 | D7: right spec | E7: 샤오미 저가형으로 충분 | F7: 복합식/과보조 기능 가습기 감가 상납 | G7: 수동 세척 힘든 구조 매일 닦느라 고생 | H7: 1 | I7: 37500 | J7: 5 | P7: =IF($H7=1,IF(AND(I7<>"",J7<>""),I7/J7/12,""),IF($H7=2,IF(AND(K7<>"",L7<>"",M7<>""),K7*L7*M7,""),IF($H7=3,IF(AND(N7<>"",O7<>""),N7/O7/12,""),IF($H7=4,IF(AND(I7<>"",J7<>""),I7/J7/12,0)+IF(AND(K7<>"",L7<>"",M7<>""),K7*L7*M7,0),IF($H7=5,IF(AND(I7<>"",J7<>""),I7/J7/12,0)+IF(AND(N7<>"",O7<>""),N7/O7/12,0),IF($H7=6,IF(AND(K7<>"",L7<>"",M7<>""),K7*L7*M7,0)+IF(AND(N7<>"",O7<>""),N7/O7/12,0),"")))))) -> 625 | Q7: 1 | R7: 600000 | S7: 5 | Y7: =IF($Q7=1,IF(AND(R7<>"",S7<>""),R7/S7/12,""),IF($Q7=2,IF(AND(T7<>"",U7<>"",V7<>""),T7*U7*V7,""),IF($Q7=3,IF(AND(W7<>"",X7<>""),W7/X7/12,""),IF($Q7=4,IF(AND(R7<>"",S7<>""),R7/S7/12,0)+IF(AND(T7<>"",U7<>"",V7<>""),T7*U7*V7,0),IF($Q7=5,IF(AND(R7<>"",S7<>""),R7/S7/12,0)+IF(AND(W7<>"",X7<>""),W7/X7/12,0),IF($Q7=6,IF(AND(T7<>"",U7<>"",V7<>""),T7*U7*V7,0)+IF(AND(W7<>"",X7<>""),W7/X7/12,0),"")))))) -> 10000 | Z7: 1 | AA7: 120000 | AB7: 5 | AH7: =IF($Z7=1,IF(AND(AA7<>"",AB7<>""),AA7/AB7/12,""),IF($Z7=2,IF(AND(AC7<>"",AD7<>"",AE7<>""),AC7*AD7*AE7,""),IF($Z7=3,IF(AND(AF7<>"",AG7<>""),AF7/AG7/12,""),IF($Z7=4,IF(AND(AA7<>"",AB7<>""),AA7/AB7/12,0)+IF(AND(AC7<>"",AD7<>"",AE7<>""),AC7*AD7*AE7,0),IF($Z7=5,IF(AND(AA7<>"",AB7<>""),AA7/AB7/12,0)+IF(AND(AF7<>"",AG7<>""),AF7/AG7/12,0),IF($Z7=6,IF(AND(AC7<>"",AD7<>"",AE7<>""),AC7*AD7*AE7,0)+IF(AND(AF7<>"",AG7<>""),AF7/AG7/12,0),"")))))) -> 2000 | AI7: =IF(매핑v2!H7="○",P7,"") -> 625 | AJ7: =IF(매핑v2!H7="○","○","X") -> ○ | AK7: =IF(매핑v2!H7="○",Y7,"") -> 10000 | AL7: =IF(매핑v2!H7="○","○","X") -> ○ | AM7: =IF(매핑v2!H7="○",AH7,"") -> 2000 | AN7: =IF(매핑v2!H7="○","○","X") -> ○ | AO7: =IF(매핑v2!I7="○",P7,"") -> 625 | AP7: =IF(매핑v2!I7="○","○","X") -> ○ | AQ7: =IF(매핑v2!I7="○",Y7,"") -> 10000 | AR7: =IF(매핑v2!I7="○","○","X") -> ○ | AS7: =IF(매핑v2!I7="○",AH7,"") -> 2000 | AT7: =IF(매핑v2!I7="○","○","X") -> ○ | AU7: =IF(매핑v2!J7="○",P7,"") -> 625 | AV7: =IF(매핑v2!J7="○","○","X") -> ○ | AW7: =IF(매핑v2!J7="○",Y7,"") -> 10000 | AX7: =IF(매핑v2!J7="○","○","X") -> ○ | AY7: =IF(매핑v2!J7="○",AH7,"") -> 2000 | AZ7: =IF(매핑v2!J7="○","○","X") -> ○ | BA7: =IF(매핑v2!K7="○",P7,"") -> 625 | BB7: =IF(매핑v2!K7="○","○","X") -> ○ | BC7: =IF(매핑v2!K7="○",Y7,"") -> 10000 | BD7: =IF(매핑v2!K7="○","○","X") -> ○ | BE7: =IF(매핑v2!K7="○",AH7,"") -> 2000 | BF7: =IF(매핑v2!K7="○","○","X") -> ○ | BG7: =IF(매핑v2!L7="○",P7,"") -> 625 | BH7: =IF(매핑v2!L7="○","○","X") -> ○ | BI7: =IF(매핑v2!L7="○",Y7,"") -> 10000 | BJ7: ○ | BK7: X | BL7: ○ | BM7: ○ | BN7: X | BO7: X
A8: 7 | B8: 주거 | C8: 조명 | D8: DIY | E8: LED 전구 + 한지로 직접 제작 | F8: 수입/디자이너 조명 구매 감가 | G8: 인테리어 포기 (수면 조명 없음) | H8: 1 | I8: 10000 | J8: 5 | P8: =IF($H8=1,IF(AND(I8<>"",J8<>""),I8/J8/12,""),IF($H8=2,IF(AND(K8<>"",L8<>"",M8<>""),K8*L8*M8,""),IF($H8=3,IF(AND(N8<>"",O8<>""),N8/O8/12,""),IF($H8=4,IF(AND(I8<>"",J8<>""),I8/J8/12,0)+IF(AND(K8<>"",L8<>"",M8<>""),K8*L8*M8,0),IF($H8=5,IF(AND(I8<>"",J8<>""),I8/J8/12,0)+IF(AND(N8<>"",O8<>""),N8/O8/12,0),IF($H8=6,IF(AND(K8<>"",L8<>"",M8<>""),K8*L8*M8,0)+IF(AND(N8<>"",O8<>""),N8/O8/12,0),"")))))) -> 166.66667 | Q8: 1 | R8: 250000 | S8: 5 | Y8: =IF($Q8=1,IF(AND(R8<>"",S8<>""),R8/S8/12,""),IF($Q8=2,IF(AND(T8<>"",U8<>"",V8<>""),T8*U8*V8,""),IF($Q8=3,IF(AND(W8<>"",X8<>""),W8/X8/12,""),IF($Q8=4,IF(AND(R8<>"",S8<>""),R8/S8/12,0)+IF(AND(T8<>"",U8<>"",V8<>""),T8*U8*V8,0),IF($Q8=5,IF(AND(R8<>"",S8<>""),R8/S8/12,0)+IF(AND(W8<>"",X8<>""),W8/X8/12,0),IF($Q8=6,IF(AND(T8<>"",U8<>"",V8<>""),T8*U8*V8,0)+IF(AND(W8<>"",X8<>""),W8/X8/12,0),"")))))) -> 4166.6667 | Z8: 1 | AH8: =IF($Z8=1,IF(AND(AA8<>"",AB8<>""),AA8/AB8/12,""),IF($Z8=2,IF(AND(AC8<>"",AD8<>"",AE8<>""),AC8*AD8*AE8,""),IF($Z8=3,IF(AND(AF8<>"",AG8<>""),AF8/AG8/12,""),IF($Z8=4,IF(AND(AA8<>"",AB8<>""),AA8/AB8/12,0)+IF(AND(AC8<>"",AD8<>"",AE8<>""),AC8*AD8*AE8,0),IF($Z8=5,IF(AND(AA8<>"",AB8<>""),AA8/AB8/12,0)+IF(AND(AF8<>"",AG8<>""),AF8/AG8/12,0),IF($Z8=6,IF(AND(AC8<>"",AD8<>"",AE8<>""),AC8*AD8*AE8,0)+IF(AND(AF8<>"",AG8<>""),AF8/AG8/12,0),"")))))) | AI8: =IF(매핑v2!H8="○",P8,"") -> 166.66667 | AJ8: =IF(매핑v2!H8="○","○","X") -> ○ | AK8: =IF(매핑v2!H8="○",Y8,"") -> 4166.6667 | AL8: =IF(매핑v2!H8="○","○","X") -> ○ | AM8: =IF(매핑v2!H8="○",AH8,"") | AN8: =IF(매핑v2!H8="○","○","X") -> ○ | AO8: =IF(매핑v2!I8="○",P8,"") -> 166.66667 | AP8: =IF(매핑v2!I8="○","○","X") -> ○ | AQ8: =IF(매핑v2!I8="○",Y8,"") -> 4166.6667 | AR8: =IF(매핑v2!I8="○","○","X") -> ○ | AS8: =IF(매핑v2!I8="○",AH8,"") | AT8: =IF(매핑v2!I8="○","○","X") -> ○ | AU8: =IF(매핑v2!J8="○",P8,"") -> 166.66667 | AV8: =IF(매핑v2!J8="○","○","X") -> ○ | AW8: =IF(매핑v2!J8="○",Y8,"") -> 4166.6667 | AX8: =IF(매핑v2!J8="○","○","X") -> ○ | AY8: =IF(매핑v2!J8="○",AH8,"") | AZ8: =IF(매핑v2!J8="○","○","X") -> ○ | BA8: =IF(매핑v2!K8="○",P8,"") -> 166.66667 | BB8: =IF(매핑v2!K8="○","○","X") -> ○ | BC8: =IF(매핑v2!K8="○",Y8,"") -> 4166.6667 | BD8: =IF(매핑v2!K8="○","○","X") -> ○ | BE8: =IF(매핑v2!K8="○",AH8,"") | BF8: =IF(매핑v2!K8="○","○","X") -> ○ | BG8: =IF(매핑v2!L8="○",P8,"") -> 166.66667 | BH8: =IF(매핑v2!L8="○","○","X") -> ○ | BI8: =IF(매핑v2!L8="○",Y8,"") -> 4166.6667 | BJ8: ○ | BK8: X | BL8: ○ | BM8: ○ | BN8: ○ | BO8: X
A9: 8 | B9: 주거 | C9: 유지보수 (힌지·문고리) | D9: 유지보수 | E9: 전기드릴 등 공구 구비 후 셀프 교체 | F9: 시공업체 출장비 및 마진 연환산 | G9: 손으로 교체하다 주말 하루 통째로 반납하여 시공 노동 | H9: 5 | I9: 150000 | J9: 8 | N9: 10000 | O9: 3 | P9: =IF($H9=1,IF(AND(I9<>"",J9<>""),I9/J9/12,""),IF($H9=2,IF(AND(K9<>"",L9<>"",M9<>""),K9*L9*M9,""),IF($H9=3,IF(AND(N9<>"",O9<>""),N9/O9/12,""),IF($H9=4,IF(AND(I9<>"",J9<>""),I9/J9/12,0)+IF(AND(K9<>"",L9<>"",M9<>""),K9*L9*M9,0),IF($H9=5,IF(AND(I9<>"",J9<>""),I9/J9/12,0)+IF(AND(N9<>"",O9<>""),N9/O9/12,0),IF($H9=6,IF(AND(K9<>"",L9<>"",M9<>""),K9*L9*M9,0)+IF(AND(N9<>"",O9<>""),N9/O9/12,0),"")))))) -> 1840.2778 | Q9: 1 | R9: 200000 | S9: 2 | Y9: =IF($Q9=1,IF(AND(R9<>"",S9<>""),R9/S9/12,""),IF($Q9=2,IF(AND(T9<>"",U9<>"",V9<>""),T9*U9*V9,""),IF($Q9=3,IF(AND(W9<>"",X9<>""),W9/X9/12,""),IF($Q9=4,IF(AND(R9<>"",S9<>""),R9/S9/12,0)+IF(AND(T9<>"",U9<>"",V9<>""),T9*U9*V9,0),IF($Q9=5,IF(AND(R9<>"",S9<>""),R9/S9/12,0)+IF(AND(W9<>"",X9<>""),W9/X9/12,0),IF($Q9=6,IF(AND(T9<>"",U9<>"",V9<>""),T9*U9*V9,0)+IF(AND(W9<>"",X9<>""),W9/X9/12,0),"")))))) -> 8333.3333 | Z9: 3 | AF9: 10000 | AG9: 3 | AH9: =IF($Z9=1,IF(AND(AA9<>"",AB9<>""),AA9/AB9/12,""),IF($Z9=2,IF(AND(AC9<>"",AD9<>"",AE9<>""),AC9*AD9*AE9,""),IF($Z9=3,IF(AND(AF9<>"",AG9<>""),AF9/AG9/12,""),IF($Z9=4,IF(AND(AA9<>"",AB9<>""),AA9/AB9/12,0)+IF(AND(AC9<>"",AD9<>"",AE9<>""),AC9*AD9*AE9,0),IF($Z9=5,IF(AND(AA9<>"",AB9<>""),AA9/AB9/12,0)+IF(AND(AF9<>"",AG9<>""),AF9/AG9/12,0),IF($Z9=6,IF(AND(AC9<>"",AD9<>"",AE9<>""),AC9*AD9*AE9,0)+IF(AND(AF9<>"",AG9<>""),AF9/AG9/12,0),"")))))) -> 277.77778 | AI9: =IF(매핑v2!H9="○",P9,"") -> 1840.2778 | AJ9: =IF(매핑v2!H9="○","○","X") -> ○ | AK9: =IF(매핑v2!H9="○",Y9,"") -> 8333.3333 | AL9: =IF(매핑v2!H9="○","○","X") -> ○ | AM9: =IF(매핑v2!H9="○",AH9,"") -> 277.77778 | AN9: =IF(매핑v2!H9="○","○","X") -> ○ | AO9: =IF(매핑v2!I9="○",P9,"") -> 1840.2778 | AP9: =IF(매핑v2!I9="○","○","X") -> ○ | AQ9: =IF(매핑v2!I9="○",Y9,"") -> 8333.3333 | AR9: =IF(매핑v2!I9="○","○","X") -> ○ | AS9: =IF(매핑v2!I9="○",AH9,"") -> 277.77778 | AT9: =IF(매핑v2!I9="○","○","X") -> ○ | AU9: =IF(매핑v2!J9="○",P9,"") -> 1840.2778 | AV9: =IF(매핑v2!J9="○","○","X") -> ○ | AW9: =IF(매핑v2!J9="○",Y9,"") -> 8333.3333 | AX9: =IF(매핑v2!J9="○","○","X") -> ○ | AY9: =IF(매핑v2!J9="○",AH9,"") -> 277.77778 | AZ9: =IF(매핑v2!J9="○","○","X") -> ○ | BA9: =IF(매핑v2!K9="○",P9,"") -> 1840.2778 | BB9: =IF(매핑v2!K9="○","○","X") -> ○ | BC9: =IF(매핑v2!K9="○",Y9,"") -> 8333.3333 | BD9: =IF(매핑v2!K9="○","○","X") -> ○ | BE9: =IF(매핑v2!K9="○",AH9,"") -> 277.77778 | BF9: =IF(매핑v2!K9="○","○","X") -> ○ | BG9: =IF(매핑v2!L9="○",P9,"") -> 1840.2778 | BH9: =IF(매핑v2!L9="○","○","X") -> ○ | BI9: =IF(매핑v2!L9="○",Y9,"") -> 8333.3333 | BJ9: ○ | BK9: X | BL9: ○ | BM9: ○ | BN9: ○ | BO9: X
A10: 9 | B10: 주거 | C10: 비데 필터 | D10: 부품 교환 | E10: 필터 직구 후 직접 교체 | F10: 브랜드 렌탈 케어 서비스 상납 | G10: 호환 필터 구입하고, 고전하며 포기, 비데 수명 단축 | H10: 5 | I10: 160000 | J10: 5 | N10: 6000 | O10: 0.5 | P10: =IF($H10=1,IF(AND(I10<>"",J10<>""),I10/J10/12,""),IF($H10=2,IF(AND(K10<>"",L10<>"",M10<>""),K10*L10*M10,""),IF($H10=3,IF(AND(N10<>"",O10<>""),N10/O10/12,""),IF($H10=4,IF(AND(I10<>"",J10<>""),I10/J10/12,0)+IF(AND(K10<>"",L10<>"",M10<>""),K10*L10*M10,0),IF($H10=5,IF(AND(I10<>"",J10<>""),I10/J10/12,0)+IF(AND(N10<>"",O10<>""),N10/O10/12,0),IF($H10=6,IF(AND(K10<>"",L10<>"",M10<>""),K10*L10*M10,0)+IF(AND(N10<>"",O10<>""),N10/O10/12,0),"")))))) -> 3666.6667 | Q10: 5 | T10: 1 | U10: 1 | V10: 30000 | Y10: =IF($Q10=1,IF(AND(R10<>"",S10<>""),R10/S10/12,""),IF($Q10=2,IF(AND(T10<>"",U10<>"",V10<>""),T10*U10*V10,""),IF($Q10=3,IF(AND(W10<>"",X10<>""),W10/X10/12,""),IF($Q10=4,IF(AND(R10<>"",S10<>""),R10/S10/12,0)+IF(AND(T10<>"",U10<>"",V10<>""),T10*U10*V10,0),IF($Q10=5,IF(AND(R10<>"",S10<>""),R10/S10/12,0)+IF(AND(W10<>"",X10<>""),W10/X10/12,0),IF($Q10=6,IF(AND(T10<>"",U10<>"",V10<>""),T10*U10*V10,0)+IF(AND(W10<>"",X10<>""),W10/X10/12,0),"")))))) -> 0 | Z10: 5 | AA10: 160000 | AB10: 2 | AF10: 6000 | AG10: 0.25 | AH10: =IF($Z10=1,IF(AND(AA10<>"",AB10<>""),AA10/AB10/12,""),IF($Z10=2,IF(AND(AC10<>"",AD10<>"",AE10<>""),AC10*AD10*AE10,""),IF($Z10=3,IF(AND(AF10<>"",AG10<>""),AF10/AG10/12,""),IF($Z10=4,IF(AND(AA10<>"",AB10<>""),AA10/AB10/12,0)+IF(AND(AC10<>"",AD10<>"",AE10<>""),AC10*AD10*AE10,0),IF($Z10=5,IF(AND(AA10<>"",AB10<>""),AA10/AB10/12,0)+IF(AND(AF10<>"",AG10<>""),AF10/AG10/12,0),IF($Z10=6,IF(AND(AC10<>"",AD10<>"",AE10<>""),AC10*AD10*AE10,0)+IF(AND(AF10<>"",AG10<>""),AF10/AG10/12,0),"")))))) -> 8666.6667 | AI10: =IF(매핑v2!H10="○",P10,"") -> 3666.6667 | AJ10: =IF(매핑v2!H10="○","○","X") -> ○ | AK10: =IF(매핑v2!H10="○",Y10,"") -> 0 | AL10: =IF(매핑v2!H10="○","○","X") -> ○ | AM10: =IF(매핑v2!H10="○",AH10,"") -> 8666.6667 | AN10: =IF(매핑v2!H10="○","○","X") -> ○ | AO10: =IF(매핑v2!I10="○",P10,"") -> 3666.6667 | AP10: =IF(매핑v2!I10="○","○","X") -> ○ | AQ10: =IF(매핑v2!I10="○",Y10,"") -> 0 | AR10: =IF(매핑v2!I10="○","○","X") -> ○ | AS10: =IF(매핑v2!I10="○",AH10,"") -> 8666.6667 | AT10: =IF(매핑v2!I10="○","○","X") -> ○ | AU10: =IF(매핑v2!J10="○",P10,"") -> 3666.6667 | AV10: =IF(매핑v2!J10="○","○","X") -> ○ | AW10: =IF(매핑v2!J10="○",Y10,"") -> 0 | AX10: =IF(매핑v2!J10="○","○","X") -> ○ | AY10: =IF(매핑v2!J10="○",AH10,"") -> 8666.6667 | AZ10: =IF(매핑v2!J10="○","○","X") -> ○ | BA10: =IF(매핑v2!K10="○",P10,"") -> 3666.6667 | BB10: =IF(매핑v2!K10="○","○","X") -> ○ | BC10: =IF(매핑v2!K10="○",Y10,"") -> 0 | BD10: =IF(매핑v2!K10="○","○","X") -> ○ | BE10: =IF(매핑v2!K10="○",AH10,"") -> 8666.6667 | BF10: =IF(매핑v2!K10="○","○","X") -> ○ | BG10: =IF(매핑v2!L10="○",P10,"") -> 3666.6667 | BH10: =IF(매핑v2!L10="○","○","X") -> ○ | BI10: =IF(매핑v2!L10="○",Y10,"") -> 0 | BJ10: ○ | BK10: X | BL10: ○ | BM10: ○ | BN10: ○ | BO10: X
A11: 10 | B11: 주거 | C11: 가스레인지 | D11: 유지보수 | E11: 기름망 직접 세척 (청소업체 불필요) | F11: 청소 업체 호출 서비스 | G11: 철수세미로 손목 나갈 때까지 박박 문지름 | H11: 3 | N11: 12000 | O11: 3 | P11: =IF($H11=1,IF(AND(I11<>"",J11<>""),I11/J11/12,""),IF($H11=2,IF(AND(K11<>"",L11<>"",M11<>""),K11*L11*M11,""),IF($H11=3,IF(AND(N11<>"",O11<>""),N11/O11/12,""),IF($H11=4,IF(AND(I11<>"",J11<>""),I11/J11/12,0)+IF(AND(K11<>"",L11<>"",M11<>""),K11*L11*M11,0),IF($H11=5,IF(AND(I11<>"",J11<>""),I11/J11/12,0)+IF(AND(N11<>"",O11<>""),N11/O11/12,0),IF($H11=6,IF(AND(K11<>"",L11<>"",M11<>""),K11*L11*M11,0)+IF(AND(N11<>"",O11<>""),N11/O11/12,0),"")))))) -> 333.33333 | Q11: 3 | R11: 60000 | S11: 1 | Y11: =IF($Q11=1,IF(AND(R11<>"",S11<>""),R11/S11/12,""),IF($Q11=2,IF(AND(T11<>"",U11<>"",V11<>""),T11*U11*V11,""),IF($Q11=3,IF(AND(W11<>"",X11<>""),W11/X11/12,""),IF($Q11=4,IF(AND(R11<>"",S11<>""),R11/S11/12,0)+IF(AND(T11<>"",U11<>"",V11<>""),T11*U11*V11,0),IF($Q11=5,IF(AND(R11<>"",S11<>""),R11/S11/12,0)+IF(AND(W11<>"",X11<>""),W11/X11/12,0),IF($Q11=6,IF(AND(T11<>"",U11<>"",V11<>""),T11*U11*V11,0)+IF(AND(W11<>"",X11<>""),W11/X11/12,0),"")))))) | Z11: 1 | AH11: =IF($Z11=1,IF(AND(AA11<>"",AB11<>""),AA11/AB11/12,""),IF($Z11=2,IF(AND(AC11<>"",AD11<>"",AE11<>""),AC11*AD11*AE11,""),IF($Z11=3,IF(AND(AF11<>"",AG11<>""),AF11/AG11/12,""),IF($Z11=4,IF(AND(AA11<>"",AB11<>""),AA11/AB11/12,0)+IF(AND(AC11<>"",AD11<>"",AE11<>""),AC11*AD11*AE11,0),IF($Z11=5,IF(AND(AA11<>"",AB11<>""),AA11/AB11/12,0)+IF(AND(AF11<>"",AG11<>""),AF11/AG11/12,0),IF($Z11=6,IF(AND(AC11<>"",AD11<>"",AE11<>""),AC11*AD11*AE11,0)+IF(AND(AF11<>"",AG11<>""),AF11/AG11/12,0),"")))))) | AI11: =IF(매핑v2!H11="○",P11,"") -> 333.33333 | AJ11: =IF(매핑v2!H11="○","○","X") -> ○ | AK11: =IF(매핑v2!H11="○",Y11,"") | AL11: =IF(매핑v2!H11="○","○","X") -> ○ | AM11: =IF(매핑v2!H11="○",AH11,"") | AN11: =IF(매핑v2!H11="○","○","X") -> ○ | AO11: =IF(매핑v2!I11="○",P11,"") -> 333.33333 | AP11: =IF(매핑v2!I11="○","○","X") -> ○ | AQ11: =IF(매핑v2!I11="○",Y11,"") | AR11: =IF(매핑v2!I11="○","○","X") -> ○ | AS11: =IF(매핑v2!I11="○",AH11,"") | AT11: =IF(매핑v2!I11="○","○","X") -> ○ | AU11: =IF(매핑v2!J11="○",P11,"") -> 333.33333 | AV11: =IF(매핑v2!J11="○","○","X") -> ○ | AW11: =IF(매핑v2!J11="○",Y11,"") | AX11: =IF(매핑v2!J11="○","○","X") -> ○ | AY11: =IF(매핑v2!J11="○",AH11,"") | AZ11: =IF(매핑v2!J11="○","○","X") -> ○ | BA11: =IF(매핑v2!K11="○",P11,"") -> 333.33333 | BB11: =IF(매핑v2!K11="○","○","X") -> ○ | BC11: =IF(매핑v2!K11="○",Y11,"") | BD11: =IF(매핑v2!K11="○","○","X") -> ○ | BE11: =IF(매핑v2!K11="○",AH11,"") | BF11: =IF(매핑v2!K11="○","○","X") -> ○ | BG11: =IF(매핑v2!L11="○",P11,"") -> 333.33333 | BH11: =IF(매핑v2!L11="○","○","X") -> ○ | BI11: =IF(매핑v2!L11="○",Y11,"") | BJ11: ○ | BK11: X | BL11: ○ | BM11: ○ | BN11: ○ | BO11: X
A12: 11 | B12: 주거 | C12: 통신비 | D12: right spec | E12: 공기계 구입 후 알뜰폰 조합 / 아이폰 계약 만료 후 장기 사용 | F12: 최신 폰 출시마다 24개월 할부 + 고가 무제한 요금제 결합 (호구 잡힘) | G12: 뽐뿌 등 성지 카페 매일 잠복하며 불법 보조금 찾느라 수십 시간 낭비 | H12: 4 | I12: 1500000 | J12: 5 | K12: 1 | L12: 1 | M12: 30000 | P12: =IF($H12=1,IF(AND(I12<>"",J12<>""),I12/J12/12,""),IF($H12=2,IF(AND(K12<>"",L12<>"",M12<>""),K12*L12*M12,""),IF($H12=3,IF(AND(N12<>"",O12<>""),N12/O12/12,""),IF($H12=4,IF(AND(I12<>"",J12<>""),I12/J12/12,0)+IF(AND(K12<>"",L12<>"",M12<>""),K12*L12*M12,0),IF($H12=5,IF(AND(I12<>"",J12<>""),I12/J12/12,0)+IF(AND(N12<>"",O12<>""),N12/O12/12,0),IF($H12=6,IF(AND(K12<>"",L12<>"",M12<>""),K12*L12*M12,0)+IF(AND(N12<>"",O12<>""),N12/O12/12,0),"")))))) -> 55000 | Q12: 2 | T12: 1 | U12: 1 | V12: 95000 | Y12: =IF($Q12=1,IF(AND(R12<>"",S12<>""),R12/S12/12,""),IF($Q12=2,IF(AND(T12<>"",U12<>"",V12<>""),T12*U12*V12,""),IF($Q12=3,IF(AND(W12<>"",X12<>""),W12/X12/12,""),IF($Q12=4,IF(AND(R12<>"",S12<>""),R12/S12/12,0)+IF(AND(T12<>"",U12<>"",V12<>""),T12*U12*V12,0),IF($Q12=5,IF(AND(R12<>"",S12<>""),R12/S12/12,0)+IF(AND(W12<>"",X12<>""),W12/X12/12,0),IF($Q12=6,IF(AND(T12<>"",U12<>"",V12<>""),T12*U12*V12,0)+IF(AND(W12<>"",X12<>""),W12/X12/12,0),"")))))) -> 95000 | Z12: 2 | AA12: 800000 | AB12: 2 | AC12: 1 | AD12: 1 | AE12: 30000 | AH12: =IF($Z12=1,IF(AND(AA12<>"",AB12<>""),AA12/AB12/12,""),IF($Z12=2,IF(AND(AC12<>"",AD12<>"",AE12<>""),AC12*AD12*AE12,""),IF($Z12=3,IF(AND(AF12<>"",AG12<>""),AF12/AG12/12,""),IF($Z12=4,IF(AND(AA12<>"",AB12<>""),AA12/AB12/12,0)+IF(AND(AC12<>"",AD12<>"",AE12<>""),AC12*AD12*AE12,0),IF($Z12=5,IF(AND(AA12<>"",AB12<>""),AA12/AB12/12,0)+IF(AND(AF12<>"",AG12<>""),AF12/AG12/12,0),IF($Z12=6,IF(AND(AC12<>"",AD12<>"",AE12<>""),AC12*AD12*AE12,0)+IF(AND(AF12<>"",AG12<>""),AF12/AG12/12,0),"")))))) -> 30000 | AI12: =IF(매핑v2!H12="○",P12,"") -> 55000 | AJ12: =IF(매핑v2!H12="○","○","X") -> ○ | AK12: =IF(매핑v2!H12="○",Y12,"") -> 95000 | AL12: =IF(매핑v2!H12="○","○","X") -> ○ | AM12: =IF(매핑v2!H12="○",AH12,"") -> 30000 | AN12: =IF(매핑v2!H12="○","○","X") -> ○ | AO12: =IF(매핑v2!I12="○",P12,"") -> 55000 | AP12: =IF(매핑v2!I12="○","○","X") -> ○ | AQ12: =IF(매핑v2!I12="○",Y12,"") -> 95000 | AR12: =IF(매핑v2!I12="○","○","X") -> ○ | AS12: =IF(매핑v2!I12="○",AH12,"") -> 30000 | AT12: =IF(매핑v2!I12="○","○","X") -> ○ | AU12: =IF(매핑v2!J12="○",P12,"") -> 55000 | AV12: =IF(매핑v2!J12="○","○","X") -> ○ | AW12: =IF(매핑v2!J12="○",Y12,"") -> 95000 | AX12: =IF(매핑v2!J12="○","○","X") -> ○ | AY12: =IF(매핑v2!J12="○",AH12,"") -> 30000 | AZ12: =IF(매핑v2!J12="○","○","X") -> ○ | BA12: =IF(매핑v2!K12="○",P12,"") -> 55000 | BB12: =IF(매핑v2!K12="○","○","X") -> ○ | BC12: =IF(매핑v2!K12="○",Y12,"") -> 95000 | BD12: =IF(매핑v2!K12="○","○","X") -> ○ | BE12: =IF(매핑v2!K12="○",AH12,"") -> 30000 | BF12: =IF(매핑v2!K12="○","○","X") -> ○ | BG12: =IF(매핑v2!L12="○",P12,"") -> 55000 | BH12: =IF(매핑v2!L12="○","○","X") -> ○ | BI12: =IF(매핑v2!L12="○",Y12,"") -> 95000 | BJ12: ○ | BK12: X | BL12: ○ | BM12: ○ | BN12: ○ | BO12: X
A13: 12 | B13: 주거 | C13: 청소·세탁용품 | D13: condensate | E13: 농축 세제 소분 / 다회용 행주로 키친타올 대체 | F13: 마트 1+1 행사 대용량 무지성 구매 / 1회용 물티슈·키친타올 남용 | G13: 최저가 PB 샀다 세정력 떨어져 두 번 세탁 / 천연 세제 직접 제조하다 지침 | H13: 2 | K13: 1 | L13: 1 | M13: 5000 | P13: =IF($H13=1,IF(AND(I13<>"",J13<>""),I13/J13/12,""),IF($H13=2,IF(AND(K13<>"",L13<>"",M13<>""),K13*L13*M13,""),IF($H13=3,IF(AND(N13<>"",O13<>""),N13/O13/12,""),IF($H13=4,IF(AND(I13<>"",J13<>""),I13/J13/12,0)+IF(AND(K13<>"",L13<>"",M13<>""),K13*L13*M13,0),IF($H13=5,IF(AND(I13<>"",J13<>""),I13/J13/12,0)+IF(AND(N13<>"",O13<>""),N13/O13/12,0),IF($H13=6,IF(AND(K13<>"",L13<>"",M13<>""),K13*L13*M13,0)+IF(AND(N13<>"",O13<>""),N13/O13/12,0),"")))))) -> 5000 | Q13: 2 | T13: 1 | U13: 1 | V13: 30000 | Y13: =IF($Q13=1,IF(AND(R13<>"",S13<>""),R13/S13/12,""),IF($Q13=2,IF(AND(T13<>"",U13<>"",V13<>""),T13*U13*V13,""),IF($Q13=3,IF(AND(W13<>"",X13<>""),W13/X13/12,""),IF($Q13=4,IF(AND(R13<>"",S13<>""),R13/S13/12,0)+IF(AND(T13<>"",U13<>"",V13<>""),T13*U13*V13,0),IF($Q13=5,IF(AND(R13<>"",S13<>""),R13/S13/12,0)+IF(AND(W13<>"",X13<>""),W13/X13/12,0),IF($Q13=6,IF(AND(T13<>"",U13<>"",V13<>""),T13*U13*V13,0)+IF(AND(W13<>"",X13<>""),W13/X13/12,0),"")))))) -> 30000 | Z13: 2 | AC13: 1 | AD13: 1 | AE13: 10000 | AH13: =IF($Z13=1,IF(AND(AA13<>"",AB13<>""),AA13/AB13/12,""),IF($Z13=2,IF(AND(AC13<>"",AD13<>"",AE13<>""),AC13*AD13*AE13,""),IF($Z13=3,IF(AND(AF13<>"",AG13<>""),AF13/AG13/12,""),IF($Z13=4,IF(AND(AA13<>"",AB13<>""),AA13/AB13/12,0)+IF(AND(AC13<>"",AD13<>"",AE13<>""),AC13*AD13*AE13,0),IF($Z13=5,IF(AND(AA13<>"",AB13<>""),AA13/AB13/12,0)+IF(AND(AF13<>"",AG13<>""),AF13/AG13/12,0),IF($Z13=6,IF(AND(AC13<>"",AD13<>"",AE13<>""),AC13*AD13*AE13,0)+IF(AND(AF13<>"",AG13<>""),AF13/AG13/12,0),"")))))) -> 10000 | AI13: =IF(매핑v2!H13="○",P13,"") -> 5000 | AJ13: =IF(매핑v2!H13="○","○","X") -> ○ | AK13: =IF(매핑v2!H13="○",Y13,"") -> 30000 | AL13: =IF(매핑v2!H13="○","○","X") -> ○ | AM13: =IF(매핑v2!H13="○",AH13,"") -> 10000 | AN13: =IF(매핑v2!H13="○","○","X") -> ○ | AO13: =IF(매핑v2!I13="○",P13,"") -> 5000 | AP13: =IF(매핑v2!I13="○","○","X") -> ○ | AQ13: =IF(매핑v2!I13="○",Y13,"") -> 30000 | AR13: =IF(매핑v2!I13="○","○","X") -> ○ | AS13: =IF(매핑v2!I13="○",AH13,"") -> 10000 | AT13: =IF(매핑v2!I13="○","○","X") -> ○ | AU13: =IF(매핑v2!J13="○",P13,"") -> 5000 | AV13: =IF(매핑v2!J13="○","○","X") -> ○ | AW13: =IF(매핑v2!J13="○",Y13,"") -> 30000 | AX13: =IF(매핑v2!J13="○","○","X") -> ○ | AY13: =IF(매핑v2!J13="○",AH13,"") -> 10000 | AZ13: =IF(매핑v2!J13="○","○","X") -> ○ | BA13: =IF(매핑v2!K13="○",P13,"") -> 5000 | BB13: =IF(매핑v2!K13="○","○","X") -> ○ | BC13: =IF(매핑v2!K13="○",Y13,"") -> 30000 | BD13: =IF(매핑v2!K13="○","○","X") -> ○ | BE13: =IF(매핑v2!K13="○",AH13,"") -> 10000 | BF13: =IF(매핑v2!K13="○","○","X") -> ○ | BG13: =IF(매핑v2!L13="○",P13,"") -> 5000 | BH13: =IF(매핑v2!L13="○","○","X") -> ○ | BI13: =IF(매핑v2!L13="○",Y13,"") -> 30000 | BJ13: ○ | BK13: X | BL13: ○ | BM13: ○ | BN13: X | BO13: X
A14: 13 | B14: 주거 | C14: 청소기 | D14: right spec | E14: 신일 등 저가 무선 청소기 (다이슨 대비 동일 효과) | F14: 150만 원대 최신 다이슨/비스포크 풀옵션 충동 구매 후 인테리어로 방치 | G14: 3만 원짜리 묻지마 중국산 샀다 6개월 만에 고장나서 또 최저가 검색 무한루프 | H14: 1 | I14: 100000 | J14: 5 | P14: =IF($H14=1,IF(AND(I14<>"",J14<>""),I14/J14/12,""),IF($H14=2,IF(AND(K14<>"",L14<>"",M14<>""),K14*L14*M14,""),IF($H14=3,IF(AND(N14<>"",O14<>""),N14/O14/12,""),IF($H14=4,IF(AND(I14<>"",J14<>""),I14/J14/12,0)+IF(AND(K14<>"",L14<>"",M14<>""),K14*L14*M14,0),IF($H14=5,IF(AND(I14<>"",J14<>""),I14/J14/12,0)+IF(AND(N14<>"",O14<>""),N14/O14/12,0),IF($H14=6,IF(AND(K14<>"",L14<>"",M14<>""),K14*L14*M14,0)+IF(AND(N14<>"",O14<>""),N14/O14/12,0),"")))))) -> 1666.6667 | Q14: 1 | R14: 1000000 | S14: 5 | Y14: =IF($Q14=1,IF(AND(R14<>"",S14<>""),R14/S14/12,""),IF($Q14=2,IF(AND(T14<>"",U14<>"",V14<>""),T14*U14*V14,""),IF($Q14=3,IF(AND(W14<>"",X14<>""),W14/X14/12,""),IF($Q14=4,IF(AND(R14<>"",S14<>""),R14/S14/12,0)+IF(AND(T14<>"",U14<>"",V14<>""),T14*U14*V14,0),IF($Q14=5,IF(AND(R14<>"",S14<>""),R14/S14/12,0)+IF(AND(W14<>"",X14<>""),W14/X14/12,0),IF($Q14=6,IF(AND(T14<>"",U14<>"",V14<>""),T14*U14*V14,0)+IF(AND(W14<>"",X14<>""),W14/X14/12,0),"")))))) -> 16666.667 | Z14: 1 | AA14: 30000 | AB14: 0.5 | AH14: =IF($Z14=1,IF(AND(AA14<>"",AB14<>""),AA14/AB14/12,""),IF($Z14=2,IF(AND(AC14<>"",AD14<>"",AE14<>""),AC14*AD14*AE14,""),IF($Z14=3,IF(AND(AF14<>"",AG14<>""),AF14/AG14/12,""),IF($Z14=4,IF(AND(AA14<>"",AB14<>""),AA14/AB14/12,0)+IF(AND(AC14<>"",AD14<>"",AE14<>""),AC14*AD14*AE14,0),IF($Z14=5,IF(AND(AA14<>"",AB14<>""),AA14/AB14/12,0)+IF(AND(AF14<>"",AG14<>""),AF14/AG14/12,0),IF($Z14=6,IF(AND(AC14<>"",AD14<>"",AE14<>""),AC14*AD14*AE14,0)+IF(AND(AF14<>"",AG14<>""),AF14/AG14/12,0),"")))))) -> 5000 | AI14: =IF(매핑v2!H14="○",P14,"") -> 1666.6667 | AJ14: =IF(매핑v2!H14="○","○","X") -> ○ | AK14: =IF(매핑v2!H14="○",Y14,"") -> 16666.667 | AL14: =IF(매핑v2!H14="○","○","X") -> ○ | AM14: =IF(매핑v2!H14="○",AH14,"") -> 5000 | AN14: =IF(매핑v2!H14="○","○","X") -> ○ | AO14: =IF(매핑v2!I14="○",P14,"") -> 1666.6667 | AP14: =IF(매핑v2!I14="○","○","X") -> ○ | AQ14: =IF(매핑v2!I14="○",Y14,"") -> 16666.667 | AR14: =IF(매핑v2!I14="○","○","X") -> ○ | AS14: =IF(매핑v2!I14="○",AH14,"") -> 5000 | AT14: =IF(매핑v2!I14="○","○","X") -> ○ | AU14: =IF(매핑v2!J14="○",P14,"") -> 1666.6667 | AV14: =IF(매핑v2!J14="○","○","X") -> ○ | AW14: =IF(매핑v2!J14="○",Y14,"") -> 16666.667 | AX14: =IF(매핑v2!J14="○","○","X") -> ○ | AY14: =IF(매핑v2!J14="○",AH14,"") -> 5000 | AZ14: =IF(매핑v2!J14="○","○","X") -> ○ | BA14: =IF(매핑v2!K14="○",P14,"") -> 1666.6667 | BB14: =IF(매핑v2!K14="○","○","X") -> ○ | BC14: =IF(매핑v2!K14="○",Y14,"") -> 16666.667 | BD14: =IF(매핑v2!K14="○","○","X") -> ○ | BE14: =IF(매핑v2!K14="○",AH14,"") -> 5000 | BF14: =IF(매핑v2!K14="○","○","X") -> ○ | BG14: =IF(매핑v2!L14="○",P14,"") -> 1666.6667 | BH14: =IF(매핑v2!L14="○","○","X") -> ○ | BI14: =IF(매핑v2!L14="○",Y14,"") -> 16666.667 | BJ14: ○ | BK14: X | BL14: ○ | BM14: ○ | BN14: ○ | BO14: X
A15: 14 | B15: 주거 | C15: 침구 | D15: right spec | E15: 솜이불 사용 (no goose down) — 내용연한 유사, 촉감 좋고 털 날림 없음 | F15: 백화점 수백만 원짜리 구스다운 풀세트 할부 결제로 과시 (세탁 감당 못함) | G15: 시장 매대에서 가장 싼 솜이불 샀다가 세탁 한 번에 숨 죽어버림 | H15: 1 | I15: 100000 | J15: 5 | P15: =IF($H15=1,IF(AND(I15<>"",J15<>""),I15/J15/12,""),IF($H15=2,IF(AND(K15<>"",L15<>"",M15<>""),K15*L15*M15,""),IF($H15=3,IF(AND(N15<>"",O15<>""),N15/O15/12,""),IF($H15=4,IF(AND(I15<>"",J15<>""),I15/J15/12,0)+IF(AND(K15<>"",L15<>"",M15<>""),K15*L15*M15,0),IF($H15=5,IF(AND(I15<>"",J15<>""),I15/J15/12,0)+IF(AND(N15<>"",O15<>""),N15/O15/12,0),IF($H15=6,IF(AND(K15<>"",L15<>"",M15<>""),K15*L15*M15,0)+IF(AND(N15<>"",O15<>""),N15/O15/12,0),"")))))) -> 1666.6667 | Q15: 5 | R15: 1200000 | S15: 5 | W15: 30000 | X15: 1 | Y15: =IF($Q15=1,IF(AND(R15<>"",S15<>""),R15/S15/12,""),IF($Q15=2,IF(AND(T15<>"",U15<>"",V15<>""),T15*U15*V15,""),IF($Q15=3,IF(AND(W15<>"",X15<>""),W15/X15/12,""),IF($Q15=4,IF(AND(R15<>"",S15<>""),R15/S15/12,0)+IF(AND(T15<>"",U15<>"",V15<>""),T15*U15*V15,0),IF($Q15=5,IF(AND(R15<>"",S15<>""),R15/S15/12,0)+IF(AND(W15<>"",X15<>""),W15/X15/12,0),IF($Q15=6,IF(AND(T15<>"",U15<>"",V15<>""),T15*U15*V15,0)+IF(AND(W15<>"",X15<>""),W15/X15/12,0),"")))))) -> 22500 | Z15: 1 | AA15: 40000 | AB15: 0.5 | AG15: 1 | AH15: =IF($Z15=1,IF(AND(AA15<>"",AB15<>""),AA15/AB15/12,""),IF($Z15=2,IF(AND(AC15<>"",AD15<>"",AE15<>""),AC15*AD15*AE15,""),IF($Z15=3,IF(AND(AF15<>"",AG15<>""),AF15/AG15/12,""),IF($Z15=4,IF(AND(AA15<>"",AB15<>""),AA15/AB15/12,0)+IF(AND(AC15<>"",AD15<>"",AE15<>""),AC15*AD15*AE15,0),IF($Z15=5,IF(AND(AA15<>"",AB15<>""),AA15/AB15/12,0)+IF(AND(AF15<>"",AG15<>""),AF15/AG15/12,0),IF($Z15=6,IF(AND(AC15<>"",AD15<>"",AE15<>""),AC15*AD15*AE15,0)+IF(AND(AF15<>"",AG15<>""),AF15/AG15/12,0),"")))))) -> 6666.6667 | AI15: =IF(매핑v2!H15="○",P15,"") -> 1666.6667 | AJ15: =IF(매핑v2!H15="○","○","X") -> ○ | AK15: =IF(매핑v2!H15="○",Y15,"") -> 22500 | AL15: =IF(매핑v2!H15="○","○","X") -> ○ | AM15: =IF(매핑v2!H15="○",AH15,"") -> 6666.6667 | AN15: =IF(매핑v2!H15="○","○","X") -> ○ | AO15: =IF(매핑v2!I15="○",P15,"") -> 1666.6667 | AP15: =IF(매핑v2!I15="○","○","X") -> ○ | AQ15: =IF(매핑v2!I15="○",Y15,"") -> 22500 | AR15: =IF(매핑v2!I15="○","○","X") -> ○ | AS15: =IF(매핑v2!I15="○",AH15,"") -> 6666.6667 | AT15: =IF(매핑v2!I15="○","○","X") -> ○ | AU15: =IF(매핑v2!J15="○",P15,"") -> 1666.6667 | AV15: =IF(매핑v2!J15="○","○","X") -> ○ | AW15: =IF(매핑v2!J15="○",Y15,"") -> 22500 | AX15: =IF(매핑v2!J15="○","○","X") -> ○ | AY15: =IF(매핑v2!J15="○",AH15,"") -> 6666.6667 | AZ15: =IF(매핑v2!J15="○","○","X") -> ○ | BA15: =IF(매핑v2!K15="○",P15,"") -> 1666.6667 | BB15: =IF(매핑v2!K15="○","○","X") -> ○ | BC15: =IF(매핑v2!K15="○",Y15,"") -> 22500 | BD15: =IF(매핑v2!K15="○","○","X") -> ○ | BE15: =IF(매핑v2!K15="○",AH15,"") -> 6666.6667 | BF15: =IF(매핑v2!K15="○","○","X") -> ○ | BG15: =IF(매핑v2!L15="○",P15,"") -> 1666.6667 | BH15: =IF(매핑v2!L15="○","○","X") -> ○ | BI15: =IF(매핑v2!L15="○",Y15,"") -> 22500 | BJ15: ○ | BK15: X | BL15: ○ | BM15: ○ | BN15: ○ | BO15: X
A16: 15 | B16: 교통 | C16: 자동차 보험 | D16: right spec | E16: 다이렉트 보험 + 마일리지·운전점수·블랙박스 할인 적용 | F16: 아는 지인(설계사)에게 묻지도 따지지도 않고 풀옵션 가입 (수수료 상납) | G16: 다이렉트 가입 후 귀찮아서 마일리지 환급 등 특약 사후 관리 완벽히 누락 | H16: 1 | I16: 450000 | J16: 1 | P16: =IF($H16=1,IF(AND(I16<>"",J16<>""),I16/J16/12,""),IF($H16=2,IF(AND(K16<>"",L16<>"",M16<>""),K16*L16*M16,""),IF($H16=3,IF(AND(N16<>"",O16<>""),N16/O16/12,""),IF($H16=4,IF(AND(I16<>"",J16<>""),I16/J16/12,0)+IF(AND(K16<>"",L16<>"",M16<>""),K16*L16*M16,0),IF($H16=5,IF(AND(I16<>"",J16<>""),I16/J16/12,0)+IF(AND(N16<>"",O16<>""),N16/O16/12,0),IF($H16=6,IF(AND(K16<>"",L16<>"",M16<>""),K16*L16*M16,0)+IF(AND(N16<>"",O16<>""),N16/O16/12,0),"")))))) -> 37500 | Q16: 1 | R16: 800000 | S16: 1 | Y16: =IF($Q16=1,IF(AND(R16<>"",S16<>""),R16/S16/12,""),IF($Q16=2,IF(AND(T16<>"",U16<>"",V16<>""),T16*U16*V16,""),IF($Q16=3,IF(AND(W16<>"",X16<>""),W16/X16/12,""),IF($Q16=4,IF(AND(R16<>"",S16<>""),R16/S16/12,0)+IF(AND(T16<>"",U16<>"",V16<>""),T16*U16*V16,0),IF($Q16=5,IF(AND(R16<>"",S16<>""),R16/S16/12,0)+IF(AND(W16<>"",X16<>""),W16/X16/12,0),IF($Q16=6,IF(AND(T16<>"",U16<>"",V16<>""),T16*U16*V16,0)+IF(AND(W16<>"",X16<>""),W16/X16/12,0),"")))))) -> 66666.667 | Z16: 1 | AA16: 800000 | AB16: 1 | AH16: =IF($Z16=1,IF(AND(AA16<>"",AB16<>""),AA16/AB16/12,""),IF($Z16=2,IF(AND(AC16<>"",AD16<>"",AE16<>""),AC16*AD16*AE16,""),IF($Z16=3,IF(AND(AF16<>"",AG16<>""),AF16/AG16/12,""),IF($Z16=4,IF(AND(AA16<>"",AB16<>""),AA16/AB16/12,0)+IF(AND(AC16<>"",AD16<>"",AE16<>""),AC16*AD16*AE16,0),IF($Z16=5,IF(AND(AA16<>"",AB16<>""),AA16/AB16/12,0)+IF(AND(AF16<>"",AG16<>""),AF16/AG16/12,0),IF($Z16=6,IF(AND(AC16<>"",AD16<>"",AE16<>""),AC16*AD16*AE16,0)+IF(AND(AF16<>"",AG16<>""),AF16/AG16/12,0),"")))))) -> 66666.667 | AI16: =IF(매핑v2!H16="○",P16,"") -> 37500 | AJ16: =IF(매핑v2!H16="○","○","X") -> ○ | AK16: =IF(매핑v2!H16="○",Y16,"") -> 66666.667 | AL16: =IF(매핑v2!H16="○","○","X") -> ○ | AM16: =IF(매핑v2!H16="○",AH16,"") -> 66666.667 | AN16: =IF(매핑v2!H16="○","○","X") -> ○ | AO16: =IF(매핑v2!I16="○",P16,"") -> 37500 | AP16: =IF(매핑v2!I16="○","○","X") -> ○ | AQ16: =IF(매핑v2!I16="○",Y16,"") -> 66666.667 | AR16: =IF(매핑v2!I16="○","○","X") -> ○ | AS16: =IF(매핑v2!I16="○",AH16,"") -> 66666.667 | AT16: =IF(매핑v2!I16="○","○","X") -> ○ | AU16: =IF(매핑v2!J16="○",P16,"") -> 37500 | AV16: =IF(매핑v2!J16="○","○","X") -> ○ | AW16: =IF(매핑v2!J16="○",Y16,"") -> 66666.667 | AX16: =IF(매핑v2!J16="○","○","X") -> ○ | AY16: =IF(매핑v2!J16="○",AH16,"") -> 66666.667 | AZ16: =IF(매핑v2!J16="○","○","X") -> ○ | BA16: =IF(매핑v2!K16="○",P16,"") -> 37500 | BB16: =IF(매핑v2!K16="○","○","X") -> ○ | BC16: =IF(매핑v2!K16="○",Y16,"") -> 66666.667 | BD16: =IF(매핑v2!K16="○","○","X") -> ○ | BE16: =IF(매핑v2!K16="○",AH16,"") -> 66666.667 | BF16: =IF(매핑v2!K16="○","○","X") -> ○ | BG16: =IF(매핑v2!L16="○",P16,"") | BH16: =IF(매핑v2!L16="○","○","X") -> X | BI16: =IF(매핑v2!L16="○",Y16,"") | BJ16: ○ | BK16: X | BL16: ○ | BM16: ○ | BN16: X | BO16: X
A17: 16 | B17: 교통 | C17: 세차 | D17: effectiveness | E17: 자동세차로 3분내 마무리, 미세한 스크래치는 받아들임 | F17: 손세차+디테일링으로 세차할때 10만원 지불, 디테일링 제품은 항상 차에 넣어둠 | G17: 셀프세차에서 1시간 세차하고, 4시간 버핑하여 주말 사라짐 | H17: 2 | K17: 1 | L17: 0.5 | M17: 10000 | P17: =IF($H17=1,IF(AND(I17<>"",J17<>""),I17/J17/12,""),IF($H17=2,IF(AND(K17<>"",L17<>"",M17<>""),K17*L17*M17,""),IF($H17=3,IF(AND(N17<>"",O17<>""),N17/O17/12,""),IF($H17=4,IF(AND(I17<>"",J17<>""),I17/J17/12,0)+IF(AND(K17<>"",L17<>"",M17<>""),K17*L17*M17,0),IF($H17=5,IF(AND(I17<>"",J17<>""),I17/J17/12,0)+IF(AND(N17<>"",O17<>""),N17/O17/12,0),IF($H17=6,IF(AND(K17<>"",L17<>"",M17<>""),K17*L17*M17,0)+IF(AND(N17<>"",O17<>""),N17/O17/12,0),"")))))) -> 5000 | Q17: 2 | T17: 1 | U17: 1 | V17: 100000 | Y17: =IF($Q17=1,IF(AND(R17<>"",S17<>""),R17/S17/12,""),IF($Q17=2,IF(AND(T17<>"",U17<>"",V17<>""),T17*U17*V17,""),IF($Q17=3,IF(AND(W17<>"",X17<>""),W17/X17/12,""),IF($Q17=4,IF(AND(R17<>"",S17<>""),R17/S17/12,0)+IF(AND(T17<>"",U17<>"",V17<>""),T17*U17*V17,0),IF($Q17=5,IF(AND(R17<>"",S17<>""),R17/S17/12,0)+IF(AND(W17<>"",X17<>""),W17/X17/12,0),IF($Q17=6,IF(AND(T17<>"",U17<>"",V17<>""),T17*U17*V17,0)+IF(AND(W17<>"",X17<>""),W17/X17/12,0),"")))))) -> 100000 | Z17: 6 | AC17: 2 | AD17: 1 | AE17: 10000 | AF17: 20000 | AG17: 8 | AH17: =IF($Z17=1,IF(AND(AA17<>"",AB17<>""),AA17/AB17/12,""),IF($Z17=2,IF(AND(AC17<>"",AD17<>"",AE17<>""),AC17*AD17*AE17,""),IF($Z17=3,IF(AND(AF17<>"",AG17<>""),AF17/AG17/12,""),IF($Z17=4,IF(AND(AA17<>"",AB17<>""),AA17/AB17/12,0)+IF(AND(AC17<>"",AD17<>"",AE17<>""),AC17*AD17*AE17,0),IF($Z17=5,IF(AND(AA17<>"",AB17<>""),AA17/AB17/12,0)+IF(AND(AF17<>"",AG17<>""),AF17/AG17/12,0),IF($Z17=6,IF(AND(AC17<>"",AD17<>"",AE17<>""),AC17*AD17*AE17,0)+IF(AND(AF17<>"",AG17<>""),AF17/AG17/12,0),"")))))) -> 20208.333 | AI17: =IF(매핑v2!H17="○",P17,"") -> 5000 | AJ17: =IF(매핑v2!H17="○","○","X") -> ○ | AK17: =IF(매핑v2!H17="○",Y17,"") -> 100000 | AL17: =IF(매핑v2!H17="○","○","X") -> ○ | AM17: =IF(매핑v2!H17="○",AH17,"") -> 20208.333 | AN17: =IF(매핑v2!H17="○","○","X") -> ○ | AO17: =IF(매핑v2!I17="○",P17,"") -> 5000 | AP17: X | AQ17: =IF(매핑v2!I17="○",Y17,"") -> 100000 | AR17: X | AS17: =IF(매핑v2!I17="○",AH17,"") -> 20208.333 | AT17: X | AU17: =IF(매핑v2!J17="○",P17,"") -> 5000 | AV17: =IF(매핑v2!J17="○","○","X") -> ○ | AW17: =IF(매핑v2!J17="○",Y17,"") -> 100000 | AX17: =IF(매핑v2!J17="○","○","X") -> ○ | AY17: =IF(매핑v2!J17="○",AH17,"") -> 20208.333 | AZ17: =IF(매핑v2!J17="○","○","X") -> ○ | BA17: =IF(매핑v2!K17="○",P17,"") -> 5000 | BB17: =IF(매핑v2!K17="○","○","X") -> ○ | BC17: =IF(매핑v2!K17="○",Y17,"") -> 100000 | BD17: =IF(매핑v2!K17="○","○","X") -> ○ | BE17: =IF(매핑v2!K17="○",AH17,"") -> 20208.333 | BF17: =IF(매핑v2!K17="○","○","X") -> ○ | BG17: =IF(매핑v2!L17="○",P17,"") -> 5000 | BH17: =IF(매핑v2!L17="○","○","X") -> ○ | BI17: =IF(매핑v2!L17="○",Y17,"") -> 100000 | BJ17: ○ | BK17: X | BL17: ○ | BM17: X | BN17: ○ | BO17: ○
A18: 17 | B18: 교통 | C18: 엔진오일 | D18: right spec | E18: 데이터 기반 보충·적기 교환 | F18: 매년 1회 프리미엄 엔진오일 교환(1년 or 15천km 준수) | G18: 공임나라 최저가 찾으려 원정 정비 노동 | H18: 5 | I18: 200000 | J18: 2 | N18: 20000 | O18: 1 | P18: =IF($H18=1,IF(AND(I18<>"",J18<>""),I18/J18/12,""),IF($H18=2,IF(AND(K18<>"",L18<>"",M18<>""),K18*L18*M18,""),IF($H18=3,IF(AND(N18<>"",O18<>""),N18/O18/12,""),IF($H18=4,IF(AND(I18<>"",J18<>""),I18/J18/12,0)+IF(AND(K18<>"",L18<>"",M18<>""),K18*L18*M18,0),IF($H18=5,IF(AND(I18<>"",J18<>""),I18/J18/12,0)+IF(AND(N18<>"",O18<>""),N18/O18/12,0),IF($H18=6,IF(AND(K18<>"",L18<>"",M18<>""),K18*L18*M18,0)+IF(AND(N18<>"",O18<>""),N18/O18/12,0),"")))))) -> 10000 | Q18: 1 | R18: 200000 | S18: 1 | Y18: =IF($Q18=1,IF(AND(R18<>"",S18<>""),R18/S18/12,""),IF($Q18=2,IF(AND(T18<>"",U18<>"",V18<>""),T18*U18*V18,""),IF($Q18=3,IF(AND(W18<>"",X18<>""),W18/X18/12,""),IF($Q18=4,IF(AND(R18<>"",S18<>""),R18/S18/12,0)+IF(AND(T18<>"",U18<>"",V18<>""),T18*U18*V18,0),IF($Q18=5,IF(AND(R18<>"",S18<>""),R18/S18/12,0)+IF(AND(W18<>"",X18<>""),W18/X18/12,0),IF($Q18=6,IF(AND(T18<>"",U18<>"",V18<>""),T18*U18*V18,0)+IF(AND(W18<>"",X18<>""),W18/X18/12,0),"")))))) -> 16666.667 | Z18: 1 | AA18: 180000 | AB18: 1 | AH18: =IF($Z18=1,IF(AND(AA18<>"",AB18<>""),AA18/AB18/12,""),IF($Z18=2,IF(AND(AC18<>"",AD18<>"",AE18<>""),AC18*AD18*AE18,""),IF($Z18=3,IF(AND(AF18<>"",AG18<>""),AF18/AG18/12,""),IF($Z18=4,IF(AND(AA18<>"",AB18<>""),AA18/AB18/12,0)+IF(AND(AC18<>"",AD18<>"",AE18<>""),AC18*AD18*AE18,0),IF($Z18=5,IF(AND(AA18<>"",AB18<>""),AA18/AB18/12,0)+IF(AND(AF18<>"",AG18<>""),AF18/AG18/12,0),IF($Z18=6,IF(AND(AC18<>"",AD18<>"",AE18<>""),AC18*AD18*AE18,0)+IF(AND(AF18<>"",AG18<>""),AF18/AG18/12,0),"")))))) -> 15000 | AI18: =IF(매핑v2!H63="○",P18,"") -> 10000 | AJ18: =IF(매핑v2!H63="○","○","X") -> ○ | AK18: =IF(매핑v2!H63="○",Y18,"") -> 16666.667 | AL18: =IF(매핑v2!H63="○","○","X") -> ○ | AM18: =IF(매핑v2!H63="○",AH18,"") -> 15000 | AN18: =IF(매핑v2!H63="○","○","X") -> ○ | AO18: =IF(매핑v2!I63="○",P18,"") -> 10000 | AP18: =IF(매핑v2!I63="○","○","X") -> ○ | AQ18: =IF(매핑v2!I63="○",Y18,"") -> 16666.667 | AR18: =IF(매핑v2!I63="○","○","X") -> ○ | AS18: =IF(매핑v2!I63="○",AH18,"") -> 15000 | AT18: =IF(매핑v2!I63="○","○","X") -> ○ | AU18: =IF(매핑v2!J63="○",P18,"") -> 10000 | AV18: =IF(매핑v2!J63="○","○","X") -> ○ | AW18: =IF(매핑v2!J63="○",Y18,"") -> 16666.667 | AX18: =IF(매핑v2!J63="○","○","X") -> ○ | AY18: =IF(매핑v2!J63="○",AH18,"") -> 15000 | AZ18: =IF(매핑v2!J63="○","○","X") -> ○ | BA18: =IF(매핑v2!K63="○",P18,"") -> 10000 | BB18: =IF(매핑v2!K63="○","○","X") -> ○ | BC18: =IF(매핑v2!K63="○",Y18,"") -> 16666.667 | BD18: =IF(매핑v2!K63="○","○","X") -> ○ | BE18: =IF(매핑v2!K63="○",AH18,"") -> 15000 | BF18: =IF(매핑v2!K63="○","○","X") -> ○ | BG18: =IF(매핑v2!L63="○",P18,"") | BH18: =IF(매핑v2!L63="○","○","X") -> X | BI18: =IF(매핑v2!L63="○",Y18,"") | BJ18: ○ | BK18: X | BL18: ○ | BM18: ○ | BN18: X | BO18: X
A19: 18 | B19: 교통 | C19: 앞유리 세정제(워셔액) | D19: condensate | E19: 농축 알약 세정제·대용량 구입 | F19: 대형 페트병 워셔액 매번 구매/이동 | G19: 폐차장이나 정비소 잉여 워셔액 구걸하다가 결국 주유소에서 구입하나 지속적인 워셔액 부족에 시달림 | H19: 3 | N19: 5000 | O19: 3 | P19: =IF($H19=1,IF(AND(I19<>"",J19<>""),I19/J19/12,""),IF($H19=2,IF(AND(K19<>"",L19<>"",M19<>""),K19*L19*M19,""),IF($H19=3,IF(AND(N19<>"",O19<>""),N19/O19/12,""),IF($H19=4,IF(AND(I19<>"",J19<>""),I19/J19/12,0)+IF(AND(K19<>"",L19<>"",M19<>""),K19*L19*M19,0),IF($H19=5,IF(AND(I19<>"",J19<>""),I19/J19/12,0)+IF(AND(N19<>"",O19<>""),N19/O19/12,0),IF($H19=6,IF(AND(K19<>"",L19<>"",M19<>""),K19*L19*M19,0)+IF(AND(N19<>"",O19<>""),N19/O19/12,0),"")))))) -> 138.88889 | Q19: 2 | T19: 1 | U19: 1 | V19: 10000 | Y19: =IF($Q19=1,IF(AND(R19<>"",S19<>""),R19/S19/12,""),IF($Q19=2,IF(AND(T19<>"",U19<>"",V19<>""),T19*U19*V19,""),IF($Q19=3,IF(AND(W19<>"",X19<>""),W19/X19/12,""),IF($Q19=4,IF(AND(R19<>"",S19<>""),R19/S19/12,0)+IF(AND(T19<>"",U19<>"",V19<>""),T19*U19*V19,0),IF($Q19=5,IF(AND(R19<>"",S19<>""),R19/S19/12,0)+IF(AND(W19<>"",X19<>""),W19/X19/12,0),IF($Q19=6,IF(AND(T19<>"",U19<>"",V19<>""),T19*U19*V19,0)+IF(AND(W19<>"",X19<>""),W19/X19/12,0),"")))))) -> 10000 | Z19: 3 | AG19: 10000 | AH19: 0.25 | AI19: =IF(매핑v2!H59="○",P19,"") -> 138.88889 | AJ19: =IF(매핑v2!H59="○","○","X") -> ○ | AK19: =IF(매핑v2!H59="○",Y19,"") -> 10000 | AL19: =IF(매핑v2!H59="○","○","X") -> ○ | AM19: =IF(매핑v2!H59="○",AH19,"") -> 0.25 | AN19: =IF(매핑v2!H59="○","○","X") -> ○ | AO19: =IF(매핑v2!I59="○",P19,"") -> 138.88889 | AP19: =IF(매핑v2!I59="○","○","X") -> ○ | AQ19: =IF(매핑v2!I59="○",Y19,"") -> 10000 | AR19: =IF(매핑v2!I59="○","○","X") -> ○ | AS19: =IF(매핑v2!I59="○",AH19,"") -> 0.25 | AT19: =IF(매핑v2!I59="○","○","X") -> ○ | AU19: =IF(매핑v2!J59="○",P19,"") -> 138.88889 | AV19: =IF(매핑v2!J59="○","○","X") -> ○ | AW19: =IF(매핑v2!J59="○",Y19,"") -> 10000 | AX19: =IF(매핑v2!J59="○","○","X") -> ○ | AY19: =IF(매핑v2!J59="○",AH19,"") -> 0.25 | AZ19: =IF(매핑v2!J59="○","○","X") -> ○ | BA19: =IF(매핑v2!K59="○",P19,"") -> 138.88889 | BB19: =IF(매핑v2!K59="○","○","X") -> ○ | BC19: =IF(매핑v2!K59="○",Y19,"") -> 10000 | BD19: =IF(매핑v2!K59="○","○","X") -> ○ | BE19: =IF(매핑v2!K59="○",AH19,"") -> 0.25 | BF19: =IF(매핑v2!K59="○","○","X") -> ○ | BG19: =IF(매핑v2!L59="○",P19,"") -> 138.88889 | BH19: =IF(매핑v2!L59="○","○","X") -> ○ | BI19: =IF(매핑v2!L59="○",Y19,"") -> 10000 | BJ19: ○ | BK19: X | BL19: ○ | BM19: ○ | BN19: X | BO19: X
A20: 19 | B20: 교통 | C20: 차량 액세서리 | D20: effectiveness | E20: 유막제거 및 발수코팅만 년 1회 수행 | F20: 럭셔리 방향제, 알칸타라 핸들 커버, 시트 커버, 공기청정기 등 악세서리 집합소 | G20: 스마트폰 거치대, 메시 쿠션, 문콕 가드 등 싸구려 유사품으로 도배 | H20: 2 | K20: =1/12 -> 0.083333333 | L20: 1 | M20: 30000 | P20: =IF($H20=1,IF(AND(I20<>"",J20<>""),I20/J20/12,""),IF($H20=2,IF(AND(K20<>"",L20<>"",M20<>""),K20*L20*M20,""),IF($H20=3,IF(AND(N20<>"",O20<>""),N20/O20/12,""),IF($H20=4,IF(AND(I20<>"",J20<>""),I20/J20/12,0)+IF(AND(K20<>"",L20<>"",M20<>""),K20*L20*M20,0),IF($H20=5,IF(AND(I20<>"",J20<>""),I20/J20/12,0)+IF(AND(N20<>"",O20<>""),N20/O20/12,0),IF($H20=6,IF(AND(K20<>"",L20<>"",M20<>""),K20*L20*M20,0)+IF(AND(N20<>"",O20<>""),N20/O20/12,0),"")))))) -> 2500 | Q20: 3 | W20: 100000 | X20: 0.5 | Y20: =IF($Q20=1,IF(AND(R20<>"",S20<>""),R20/S20/12,""),IF($Q20=2,IF(AND(T20<>"",U20<>"",V20<>""),T20*U20*V20,""),IF($Q20=3,IF(AND(W20<>"",X20<>""),W20/X20/12,""),IF($Q20=4,IF(AND(R20<>"",S20<>""),R20/S20/12,0)+IF(AND(T20<>"",U20<>"",V20<>""),T20*U20*V20,0),IF($Q20=5,IF(AND(R20<>"",S20<>""),R20/S20/12,0)+IF(AND(W20<>"",X20<>""),W20/X20/12,0),IF($Q20=6,IF(AND(T20<>"",U20<>"",V20<>""),T20*U20*V20,0)+IF(AND(W20<>"",X20<>""),W20/X20/12,0),"")))))) -> 16666.667 | Z20: 3 | AF20: 20000 | AG20: 1 | AH20: =IF($Z20=1,IF(AND(AA20<>"",AB20<>""),AA20/AB20/12,""),IF($Z20=2,IF(AND(AC20<>"",AD20<>"",AE20<>""),AC20*AD20*AE20,""),IF($Z20=3,IF(AND(AF20<>"",AG20<>""),AF20/AG20/12,""),IF($Z20=4,IF(AND(AA20<>"",AB20<>""),AA20/AB20/12,0)+IF(AND(AC20<>"",AD20<>"",AE20<>""),AC20*AD20*AE20,0),IF($Z20=5,IF(AND(AA20<>"",AB20<>""),AA20/AB20/12,0)+IF(AND(AF20<>"",AG20<>""),AF20/AG20/12,0),IF($Z20=6,IF(AND(AC20<>"",AD20<>"",AE20<>""),AC20*AD20*AE20,0)+IF(AND(AF20<>"",AG20<>""),AF20/AG20/12,0),"")))))) -> 1666.6667
A21: 20 | B21: 식 | C21: 식재료 | D21: alternative | E21: 토마토로 과일 대체 / 제철 식재료 위주 | F21: 고가 제철/프리미엄 과일 구매 | G21: 마트 마감 세일 과자/과일 수령 노동 | H21: 2 | K21: 1 | L21: 1 | M21: 20000 | P21: =IF($H21=1,IF(AND(I21<>"",J21<>""),I21/J21/12,""),IF($H21=2,IF(AND(K21<>"",L21<>"",M21<>""),K21*L21*M21,""),IF($H21=3,IF(AND(N21<>"",O21<>""),N21/O21/12,""),IF($H21=4,IF(AND(I21<>"",J21<>""),I21/J21/12,0)+IF(AND(K21<>"",L21<>"",M21<>""),K21*L21*M21,0),IF($H21=5,IF(AND(I21<>"",J21<>""),I21/J21/12,0)+IF(AND(N21<>"",O21<>""),N21/O21/12,0),IF($H21=6,IF(AND(K21<>"",L21<>"",M21<>""),K21*L21*M21,0)+IF(AND(N21<>"",O21<>""),N21/O21/12,0),"")))))) -> 20000 | Q21: 2 | T21: 1 | U21: 1 | V21: 100000 | Y21: =IF($Q21=1,IF(AND(R21<>"",S21<>""),R21/S21/12,""),IF($Q21=2,IF(AND(T21<>"",U21<>"",V21<>""),T21*U21*V21,""),IF($Q21=3,IF(AND(W21<>"",X21<>""),W21/X21/12,""),IF($Q21=4,IF(AND(R21<>"",S21<>""),R21/S21/12,0)+IF(AND(T21<>"",U21<>"",V21<>""),T21*U21*V21,0),IF($Q21=5,IF(AND(R21<>"",S21<>""),R21/S21/12,0)+IF(AND(W21<>"",X21<>""),W21/X21/12,0),IF($Q21=6,IF(AND(T21<>"",U21<>"",V21<>""),T21*U21*V21,0)+IF(AND(W21<>"",X21<>""),W21/X21/12,0),"")))))) -> 100000 | Z21: 2 | AC21: 1 | AD21: 1 | AE21: 60000 | AH21: =IF($Z21=1,IF(AND(AA21<>"",AB21<>""),AA21/AB21/12,""),IF($Z21=2,IF(AND(AC21<>"",AD21<>"",AE21<>""),AC21*AD21*AE21,""),IF($Z21=3,IF(AND(AF21<>"",AG21<>""),AF21/AG21/12,""),IF($Z21=4,IF(AND(AA21<>"",AB21<>""),AA21/AB21/12,0)+IF(AND(AC21<>"",AD21<>"",AE21<>""),AC21*AD21*AE21,0),IF($Z21=5,IF(AND(AA21<>"",AB21<>""),AA21/AB21/12,0)+IF(AND(AF21<>"",AG21<>""),AF21/AG21/12,0),IF($Z21=6,IF(AND(AC21<>"",AD21<>"",AE21<>""),AC21*AD21*AE21,0)+IF(AND(AF21<>"",AG21<>""),AF21/AG21/12,0),"")))))) -> 60000 | AI21: =IF(매핑v2!H17="○",P21,"") -> 20000 | AJ21: =IF(매핑v2!H17="○","○","X") -> ○ | AK21: =IF(매핑v2!H17="○",Y21,"") -> 100000 | AL21: =IF(매핑v2!H17="○","○","X") -> ○ | AM21: =IF(매핑v2!H17="○",AH21,"") -> 60000 | AN21: =IF(매핑v2!H17="○","○","X") -> ○ | AO21: =IF(매핑v2!I17="○",P21,"") -> 20000 | AP21: =IF(매핑v2!I17="○","○","X") -> ○ | AQ21: =IF(매핑v2!I17="○",Y21,"") -> 100000 | AR21: =IF(매핑v2!I17="○","○","X") -> ○ | AS21: =IF(매핑v2!I17="○",AH21,"") -> 60000 | AT21: =IF(매핑v2!I17="○","○","X") -> ○ | AU21: =IF(매핑v2!J17="○",P21,"") -> 20000 | AV21: =IF(매핑v2!J17="○","○","X") -> ○ | AW21: =IF(매핑v2!J17="○",Y21,"") -> 100000 | AX21: =IF(매핑v2!J17="○","○","X") -> ○ | AY21: =IF(매핑v2!J17="○",AH21,"") -> 60000 | AZ21: =IF(매핑v2!J17="○","○","X") -> ○ | BA21: =IF(매핑v2!K17="○",P21,"") -> 20000 | BB21: =IF(매핑v2!K17="○","○","X") -> ○ | BC21: =IF(매핑v2!K17="○",Y21,"") -> 100000 | BD21: =IF(매핑v2!K17="○","○","X") -> ○ | BE21: =IF(매핑v2!K17="○",AH21,"") -> 60000 | BF21: =IF(매핑v2!K17="○","○","X") -> ○ | BG21: =IF(매핑v2!L17="○",P21,"") -> 20000 | BH21: =IF(매핑v2!L17="○","○","X") -> ○ | BI21: =IF(매핑v2!L17="○",Y21,"") -> 100000 | BJ21: ○ | BK21: X | BL21: ○ | BM21: ○ | BN21: ○ | BO21: X
A22: 21 | B22: 식 | C22: 식기·조리도구 | D22: right spec | E22: 놋쇠 수저·세라믹 식기 한번 구입 후 장기 사용 | F22: 유행 타는 식기 세트 잦은 기변 | G22: 다이소 플라스틱 식기 유해물질 노출 위험 | H22: 1 | I22: 100000 | J22: 5 | P22: =IF($H22=1,IF(AND(I22<>"",J22<>""),I22/J22/12,""),IF($H22=2,IF(AND(K22<>"",L22<>"",M22<>""),K22*L22*M22,""),IF($H22=3,IF(AND(N22<>"",O22<>""),N22/O22/12,""),IF($H22=4,IF(AND(I22<>"",J22<>""),I22/J22/12,0)+IF(AND(K22<>"",L22<>"",M22<>""),K22*L22*M22,0),IF($H22=5,IF(AND(I22<>"",J22<>""),I22/J22/12,0)+IF(AND(N22<>"",O22<>""),N22/O22/12,0),IF($H22=6,IF(AND(K22<>"",L22<>"",M22<>""),K22*L22*M22,0)+IF(AND(N22<>"",O22<>""),N22/O22/12,0),"")))))) -> 1666.6667 | Q22: 1 | R22: 160000 | S22: 2 | Y22: =IF($Q22=1,IF(AND(R22<>"",S22<>""),R22/S22/12,""),IF($Q22=2,IF(AND(T22<>"",U22<>"",V22<>""),T22*U22*V22,""),IF($Q22=3,IF(AND(W22<>"",X22<>""),W22/X22/12,""),IF($Q22=4,IF(AND(R22<>"",S22<>""),R22/S22/12,0)+IF(AND(T22<>"",U22<>"",V22<>""),T22*U22*V22,0),IF($Q22=5,IF(AND(R22<>"",S22<>""),R22/S22/12,0)+IF(AND(W22<>"",X22<>""),W22/X22/12,0),IF($Q22=6,IF(AND(T22<>"",U22<>"",V22<>""),T22*U22*V22,0)+IF(AND(W22<>"",X22<>""),W22/X22/12,0),"")))))) -> 6666.6667 | Z22: 1 | AA22: 20000 | AB22: 0.25 | AH22: =IF($Z22=1,IF(AND(AA22<>"",AB22<>""),AA22/AB22/12,""),IF($Z22=2,IF(AND(AC22<>"",AD22<>"",AE22<>""),AC22*AD22*AE22,""),IF($Z22=3,IF(AND(AF22<>"",AG22<>""),AF22/AG22/12,""),IF($Z22=4,IF(AND(AA22<>"",AB22<>""),AA22/AB22/12,0)+IF(AND(AC22<>"",AD22<>"",AE22<>""),AC22*AD22*AE22,0),IF($Z22=5,IF(AND(AA22<>"",AB22<>""),AA22/AB22/12,0)+IF(AND(AF22<>"",AG22<>""),AF22/AG22/12,0),IF($Z22=6,IF(AND(AC22<>"",AD22<>"",AE22<>""),AC22*AD22*AE22,0)+IF(AND(AF22<>"",AG22<>""),AF22/AG22/12,0),"")))))) -> 6666.6667 | AI22: =IF(매핑v2!H18="○",P22,"") -> 1666.6667 | AJ22: =IF(매핑v2!H18="○","○","X") -> ○ | AK22: =IF(매핑v2!H18="○",Y22,"") -> 6666.6667 | AL22: =IF(매핑v2!H18="○","○","X") -> ○ | AM22: =IF(매핑v2!H18="○",AH22,"") -> 6666.6667 | AN22: =IF(매핑v2!H18="○","○","X") -> ○ | AO22: =IF(매핑v2!I18="○",P22,"") -> 1666.6667 | AP22: =IF(매핑v2!I18="○","○","X") -> ○ | AQ22: =IF(매핑v2!I18="○",Y22,"") -> 6666.6667 | AR22: =IF(매핑v2!I18="○","○","X") -> ○ | AS22: =IF(매핑v2!I18="○",AH22,"") -> 6666.6667 | AT22: =IF(매핑v2!I18="○","○","X") -> ○ | AU22: =IF(매핑v2!J18="○",P22,"") -> 1666.6667 | AV22: =IF(매핑v2!J18="○","○","X") -> ○ | AW22: =IF(매핑v2!J18="○",Y22,"") -> 6666.6667 | AX22: =IF(매핑v2!J18="○","○","X") -> ○ | AY22: =IF(매핑v2!J18="○",AH22,"") -> 6666.6667 | AZ22: =IF(매핑v2!J18="○","○","X") -> ○ | BA22: =IF(매핑v2!K18="○",P22,"") -> 1666.6667 | BB22: =IF(매핑v2!K18="○","○","X") -> ○ | BC22: =IF(매핑v2!K18="○",Y22,"") -> 6666.6667 | BD22: =IF(매핑v2!K18="○","○","X") -> ○ | BE22: =IF(매핑v2!K18="○",AH22,"") -> 6666.6667 | BF22: =IF(매핑v2!K18="○","○","X") -> ○ | BG22: =IF(매핑v2!L18="○",P22,"") -> 1666.6667 | BH22: =IF(매핑v2!L18="○","○","X") -> ○ | BI22: =IF(매핑v2!L18="○",Y22,"") -> 6666.6667 | BJ22: ○ | BK22: X | BL22: ○ | BM22: ○ | BN22: ○ | BO22: X
A23: 22 | B23: 식 | C23: 칼·주방도구 유지보수 | D23: 유지보수 | E23: 이케아 칼갈이로 자가 연마 | F23: 무뎌지면 버리고 새 세트 구매 | G23: 숫돌에 물 부어가며 주말 내내 칼 가는 노동 | H23: 1 | I23: 10000 | J23: 8 | P23: =IF($H23=1,IF(AND(I23<>"",J23<>""),I23/J23/12,""),IF($H23=2,IF(AND(K23<>"",L23<>"",M23<>""),K23*L23*M23,""),IF($H23=3,IF(AND(N23<>"",O23<>""),N23/O23/12,""),IF($H23=4,IF(AND(I23<>"",J23<>""),I23/J23/12,0)+IF(AND(K23<>"",L23<>"",M23<>""),K23*L23*M23,0),IF($H23=5,IF(AND(I23<>"",J23<>""),I23/J23/12,0)+IF(AND(N23<>"",O23<>""),N23/O23/12,0),IF($H23=6,IF(AND(K23<>"",L23<>"",M23<>""),K23*L23*M23,0)+IF(AND(N23<>"",O23<>""),N23/O23/12,0),"")))))) -> 104.16667 | Q23: 1 | R23: 80000 | S23: 2 | Y23: =IF($Q23=1,IF(AND(R23<>"",S23<>""),R23/S23/12,""),IF($Q23=2,IF(AND(T23<>"",U23<>"",V23<>""),T23*U23*V23,""),IF($Q23=3,IF(AND(W23<>"",X23<>""),W23/X23/12,""),IF($Q23=4,IF(AND(R23<>"",S23<>""),R23/S23/12,0)+IF(AND(T23<>"",U23<>"",V23<>""),T23*U23*V23,0),IF($Q23=5,IF(AND(R23<>"",S23<>""),R23/S23/12,0)+IF(AND(W23<>"",X23<>""),W23/X23/12,0),IF($Q23=6,IF(AND(T23<>"",U23<>"",V23<>""),T23*U23*V23,0)+IF(AND(W23<>"",X23<>""),W23/X23/12,0),"")))))) -> 3333.3333 | Z23: 1 | AA23: 10000 | AB23: 10 | AH23: =IF($Z23=1,IF(AND(AA23<>"",AB23<>""),AA23/AB23/12,""),IF($Z23=2,IF(AND(AC23<>"",AD23<>"",AE23<>""),AC23*AD23*AE23,""),IF($Z23=3,IF(AND(AF23<>"",AG23<>""),AF23/AG23/12,""),IF($Z23=4,IF(AND(AA23<>"",AB23<>""),AA23/AB23/12,0)+IF(AND(AC23<>"",AD23<>"",AE23<>""),AC23*AD23*AE23,0),IF($Z23=5,IF(AND(AA23<>"",AB23<>""),AA23/AB23/12,0)+IF(AND(AF23<>"",AG23<>""),AF23/AG23/12,0),IF($Z23=6,IF(AND(AC23<>"",AD23<>"",AE23<>""),AC23*AD23*AE23,0)+IF(AND(AF23<>"",AG23<>""),AF23/AG23/12,0),"")))))) -> 83.333333 | AI23: =IF(매핑v2!H19="○",P23,"") -> 104.16667 | AJ23: =IF(매핑v2!H19="○","○","X") -> ○ | AK23: =IF(매핑v2!H19="○",Y23,"") -> 3333.3333 | AL23: =IF(매핑v2!H19="○","○","X") -> ○ | AM23: =IF(매핑v2!H19="○",AH23,"") -> 83.333333 | AN23: =IF(매핑v2!H19="○","○","X") -> ○ | AO23: =IF(매핑v2!I19="○",P23,"") -> 104.16667 | AP23: =IF(매핑v2!I19="○","○","X") -> ○ | AQ23: =IF(매핑v2!I19="○",Y23,"") -> 3333.3333 | AR23: =IF(매핑v2!I19="○","○","X") -> ○ | AS23: =IF(매핑v2!I19="○",AH23,"") -> 83.333333 | AT23: =IF(매핑v2!I19="○","○","X") -> ○ | AU23: =IF(매핑v2!J19="○",P23,"") -> 104.16667 | AV23: =IF(매핑v2!J19="○","○","X") -> ○ | AW23: =IF(매핑v2!J19="○",Y23,"") -> 3333.3333 | AX23: =IF(매핑v2!J19="○","○","X") -> ○ | AY23: =IF(매핑v2!J19="○",AH23,"") -> 83.333333 | AZ23: =IF(매핑v2!J19="○","○","X") -> ○ | BA23: =IF(매핑v2!K19="○",P23,"") -> 104.16667 | BB23: =IF(매핑v2!K19="○","○","X") -> ○ | BC23: =IF(매핑v2!K19="○",Y23,"") -> 3333.3333 | BD23: =IF(매핑v2!K19="○","○","X") -> ○ | BE23: =IF(매핑v2!K19="○",AH23,"") -> 83.333333 | BF23: =IF(매핑v2!K19="○","○","X") -> ○ | BG23: =IF(매핑v2!L19="○",P23,"") -> 104.16667 | BH23: =IF(매핑v2!L19="○","○","X") -> ○ | BI23: =IF(매핑v2!L19="○",Y23,"") -> 3333.3333 | BJ23: ○ | BK23: X | BL23: ○ | BM23: ○ | BN23: X | BO23: X
A24: 23 | B24: 식 | C24: 양념·소모품 | D24: sharing | E24: 후추·소금 대용량 구입 후 지인 소분 | F24: 악성 재고로 유통기한 경과 후 폐기 | G24: 굳어버린 양념 억지로 쓰다 음식 망침 | H24: 1 | I24: 20000 | J24: 2 | P24: =IF($H24=1,IF(AND(I24<>"",J24<>""),I24/J24/12,""),IF($H24=2,IF(AND(K24<>"",L24<>"",M24<>""),K24*L24*M24,""),IF($H24=3,IF(AND(N24<>"",O24<>""),N24/O24/12,""),IF($H24=4,IF(AND(I24<>"",J24<>""),I24/J24/12,0)+IF(AND(K24<>"",L24<>"",M24<>""),K24*L24*M24,0),IF($H24=5,IF(AND(I24<>"",J24<>""),I24/J24/12,0)+IF(AND(N24<>"",O24<>""),N24/O24/12,0),IF($H24=6,IF(AND(K24<>"",L24<>"",M24<>""),K24*L24*M24,0)+IF(AND(N24<>"",O24<>""),N24/O24/12,0),"")))))) -> 833.33333 | Q24: 3 | W24: 50000 | X24: 1 | Y24: =IF($Q24=1,IF(AND(R24<>"",S24<>""),R24/S24/12,""),IF($Q24=2,IF(AND(T24<>"",U24<>"",V24<>""),T24*U24*V24,""),IF($Q24=3,IF(AND(W24<>"",X24<>""),W24/X24/12,""),IF($Q24=4,IF(AND(R24<>"",S24<>""),R24/S24/12,0)+IF(AND(T24<>"",U24<>"",V24<>""),T24*U24*V24,0),IF($Q24=5,IF(AND(R24<>"",S24<>""),R24/S24/12,0)+IF(AND(W24<>"",X24<>""),W24/X24/12,0),IF($Q24=6,IF(AND(T24<>"",U24<>"",V24<>""),T24*U24*V24,0)+IF(AND(W24<>"",X24<>""),W24/X24/12,0),"")))))) -> 4166.6667 | Z24: 3 | AF24: 20000 | AG24: 2 | AH24: =IF($Z24=1,IF(AND(AA24<>"",AB24<>""),AA24/AB24/12,""),IF($Z24=2,IF(AND(AC24<>"",AD24<>"",AE24<>""),AC24*AD24*AE24,""),IF($Z24=3,IF(AND(AF24<>"",AG24<>""),AF24/AG24/12,""),IF($Z24=4,IF(AND(AA24<>"",AB24<>""),AA24/AB24/12,0)+IF(AND(AC24<>"",AD24<>"",AE24<>""),AC24*AD24*AE24,0),IF($Z24=5,IF(AND(AA24<>"",AB24<>""),AA24/AB24/12,0)+IF(AND(AF24<>"",AG24<>""),AF24/AG24/12,0),IF($Z24=6,IF(AND(AC24<>"",AD24<>"",AE24<>""),AC24*AD24*AE24,0)+IF(AND(AF24<>"",AG24<>""),AF24/AG24/12,0),"")))))) -> 833.33333 | AI24: =IF(매핑v2!H20="○",P24,"") -> 833.33333 | AJ24: =IF(매핑v2!H20="○","○","X") -> ○ | AK24: =IF(매핑v2!H20="○",Y24,"") -> 4166.6667 | AL24: =IF(매핑v2!H20="○","○","X") -> ○ | AM24: =IF(매핑v2!H20="○",AH24,"") -> 833.33333 | AN24: =IF(매핑v2!H20="○","○","X") -> ○ | AO24: =IF(매핑v2!I20="○",P24,"") -> 833.33333 | AP24: =IF(매핑v2!I20="○","○","X") -> ○ | AQ24: =IF(매핑v2!I20="○",Y24,"") -> 4166.6667 | AR24: =IF(매핑v2!I20="○","○","X") -> ○ | AS24: =IF(매핑v2!I20="○",AH24,"") -> 833.33333 | AT24: =IF(매핑v2!I20="○","○","X") -> ○ | AU24: =IF(매핑v2!J20="○",P24,"") -> 833.33333 | AV24: =IF(매핑v2!J20="○","○","X") -> ○ | AW24: =IF(매핑v2!J20="○",Y24,"") -> 4166.6667 | AX24: =IF(매핑v2!J20="○","○","X") -> ○ | AY24: =IF(매핑v2!J20="○",AH24,"") -> 833.33333 | AZ24: =IF(매핑v2!J20="○","○","X") -> ○ | BA24: =IF(매핑v2!K20="○",P24,"") -> 833.33333 | BB24: =IF(매핑v2!K20="○","○","X") -> ○ | BC24: =IF(매핑v2!K20="○",Y24,"") -> 4166.6667 | BD24: =IF(매핑v2!K20="○","○","X") -> ○ | BE24: =IF(매핑v2!K20="○",AH24,"") -> 833.33333 | BF24: =IF(매핑v2!K20="○","○","X") -> ○ | BG24: =IF(매핑v2!L20="○",P24,"") -> 833.33333 | BH24: =IF(매핑v2!L20="○","○","X") -> ○ | BI24: =IF(매핑v2!L20="○",Y24,"") -> 4166.6667 | BJ24: ○ | BK24: X | BL24: X | BM24: ○ | BN24: X | BO24: X
A25: 24 | B25: 식 | C25: 외식 | D25: effectiveness | E25: 네트워킹할 때만 외식 / 집밥이 더 간편하고 효율적 | F25: 인스타 핫플 2시간 웨이팅 / 기분 전환 명목 주 3~4회 오마카세 지출 | G25: 가성비 무한리필, 저가 국밥집만 전전하며 건강(나트륨·당)과 체력 잃음 | H25: 2 | K25: 2 | L25: 1 | M25: 100000 | P25: =IF($H25=1,IF(AND(I25<>"",J25<>""),I25/J25/12,""),IF($H25=2,IF(AND(K25<>"",L25<>"",M25<>""),K25*L25*M25,""),IF($H25=3,IF(AND(N25<>"",O25<>""),N25/O25/12,""),IF($H25=4,IF(AND(I25<>"",J25<>""),I25/J25/12,0)+IF(AND(K25<>"",L25<>"",M25<>""),K25*L25*M25,0),IF($H25=5,IF(AND(I25<>"",J25<>""),I25/J25/12,0)+IF(AND(N25<>"",O25<>""),N25/O25/12,0),IF($H25=6,IF(AND(K25<>"",L25<>"",M25<>""),K25*L25*M25,0)+IF(AND(N25<>"",O25<>""),N25/O25/12,0),"")))))) -> 200000 | Q25: 2 | T25: 4 | U25: 1 | V25: 100000 | Y25: =IF($Q25=1,IF(AND(R25<>"",S25<>""),R25/S25/12,""),IF($Q25=2,IF(AND(T25<>"",U25<>"",V25<>""),T25*U25*V25,""),IF($Q25=3,IF(AND(W25<>"",X25<>""),W25/X25/12,""),IF($Q25=4,IF(AND(R25<>"",S25<>""),R25/S25/12,0)+IF(AND(T25<>"",U25<>"",V25<>""),T25*U25*V25,0),IF($Q25=5,IF(AND(R25<>"",S25<>""),R25/S25/12,0)+IF(AND(W25<>"",X25<>""),W25/X25/12,0),IF($Q25=6,IF(AND(T25<>"",U25<>"",V25<>""),T25*U25*V25,0)+IF(AND(W25<>"",X25<>""),W25/X25/12,0),"")))))) -> 400000 | Z25: 2 | AC25: 4 | AD25: 1 | AE25: 20000 | AH25: =IF($Z25=1,IF(AND(AA25<>"",AB25<>""),AA25/AB25/12,""),IF($Z25=2,IF(AND(AC25<>"",AD25<>"",AE25<>""),AC25*AD25*AE25,""),IF($Z25=3,IF(AND(AF25<>"",AG25<>""),AF25/AG25/12,""),IF($Z25=4,IF(AND(AA25<>"",AB25<>""),AA25/AB25/12,0)+IF(AND(AC25<>"",AD25<>"",AE25<>""),AC25*AD25*AE25,0),IF($Z25=5,IF(AND(AA25<>"",AB25<>""),AA25/AB25/12,0)+IF(AND(AF25<>"",AG25<>""),AF25/AG25/12,0),IF($Z25=6,IF(AND(AC25<>"",AD25<>"",AE25<>""),AC25*AD25*AE25,0)+IF(AND(AF25<>"",AG25<>""),AF25/AG25/12,0),"")))))) -> 80000 | AI25: =IF(매핑v2!H21="○",P25,"") -> 200000 | AJ25: =IF(매핑v2!H21="○","○","X") -> ○ | AK25: =IF(매핑v2!H21="○",Y25,"") -> 400000 | AL25: =IF(매핑v2!H21="○","○","X") -> ○ | AM25: =IF(매핑v2!H21="○",AH25,"") -> 80000 | AN25: =IF(매핑v2!H21="○","○","X") -> ○ | AO25: =IF(매핑v2!I21="○",P25,"") -> 200000 | AP25: =IF(매핑v2!I21="○","○","X") -> ○ | AQ25: =IF(매핑v2!I21="○",Y25,"") -> 400000 | AR25: =IF(매핑v2!I21="○","○","X") -> ○ | AS25: =IF(매핑v2!I21="○",AH25,"") -> 80000 | AT25: =IF(매핑v2!I21="○","○","X") -> ○ | AU25: =IF(매핑v2!J21="○",P25,"") -> 200000 | AV25: =IF(매핑v2!J21="○","○","X") -> ○ | AW25: =IF(매핑v2!J21="○",Y25,"") -> 400000 | AX25: =IF(매핑v2!J21="○","○","X") -> ○ | AY25: =IF(매핑v2!J21="○",AH25,"") -> 80000 | AZ25: =IF(매핑v2!J21="○","○","X") -> ○ | BA25: =IF(매핑v2!K21="○",P25,"") -> 200000 | BB25: =IF(매핑v2!K21="○","○","X") -> ○ | BC25: =IF(매핑v2!K21="○",Y25,"") -> 400000 | BD25: =IF(매핑v2!K21="○","○","X") -> ○ | BE25: =IF(매핑v2!K21="○",AH25,"") -> 80000 | BF25: =IF(매핑v2!K21="○","○","X") -> ○ | BG25: =IF(매핑v2!L21="○",P25,"") -> 200000 | BH25: =IF(매핑v2!L21="○","○","X") -> ○ | BI25: =IF(매핑v2!L21="○",Y25,"") -> 400000 | BJ25: ○ | BK25: X | BL25: ○ | BM25: ○ | BN25: X | BO25: X
A26: 25 | B26: 식 | C26: 배달 | D26: effectiveness | E26: 비추 — 대기+뒷처리 비효율 / 기름·당분 과다 → 집밥 또는 치킨 픽업 | F26: 퇴근길 피로 핑계로 배민 VIP 유지 / 월 수십만 원 배달비로 고정비 누수 | G26: 배달비 3천 원 아끼겠다고 포장 주문 후 왕복 40분 걸어 다녀오느라 진 뺌 | H26: 2 | K26: 1 | L26: 1 | M26: 20000 | P26: =IF($H26=1,IF(AND(I26<>"",J26<>""),I26/J26/12,""),IF($H26=2,IF(AND(K26<>"",L26<>"",M26<>""),K26*L26*M26,""),IF($H26=3,IF(AND(N26<>"",O26<>""),N26/O26/12,""),IF($H26=4,IF(AND(I26<>"",J26<>""),I26/J26/12,0)+IF(AND(K26<>"",L26<>"",M26<>""),K26*L26*M26,0),IF($H26=5,IF(AND(I26<>"",J26<>""),I26/J26/12,0)+IF(AND(N26<>"",O26<>""),N26/O26/12,0),IF($H26=6,IF(AND(K26<>"",L26<>"",M26<>""),K26*L26*M26,0)+IF(AND(N26<>"",O26<>""),N26/O26/12,0),"")))))) -> 20000 | Q26: 2 | T26: 8 | U26: 1 | V26: 25000 | Y26: =IF($Q26=1,IF(AND(R26<>"",S26<>""),R26/S26/12,""),IF($Q26=2,IF(AND(T26<>"",U26<>"",V26<>""),T26*U26*V26,""),IF($Q26=3,IF(AND(W26<>"",X26<>""),W26/X26/12,""),IF($Q26=4,IF(AND(R26<>"",S26<>""),R26/S26/12,0)+IF(AND(T26<>"",U26<>"",V26<>""),T26*U26*V26,0),IF($Q26=5,IF(AND(R26<>"",S26<>""),R26/S26/12,0)+IF(AND(W26<>"",X26<>""),W26/X26/12,0),IF($Q26=6,IF(AND(T26<>"",U26<>"",V26<>""),T26*U26*V26,0)+IF(AND(W26<>"",X26<>""),W26/X26/12,0),"")))))) -> 200000 | Z26: 2 | AC26: 8 | AD26: 1 | AE26: 20000 | AH26: =IF($Z26=1,IF(AND(AA26<>"",AB26<>""),AA26/AB26/12,""),IF($Z26=2,IF(AND(AC26<>"",AD26<>"",AE26<>""),AC26*AD26*AE26,""),IF($Z26=3,IF(AND(AF26<>"",AG26<>""),AF26/AG26/12,""),IF($Z26=4,IF(AND(AA26<>"",AB26<>""),AA26/AB26/12,0)+IF(AND(AC26<>"",AD26<>"",AE26<>""),AC26*AD26*AE26,0),IF($Z26=5,IF(AND(AA26<>"",AB26<>""),AA26/AB26/12,0)+IF(AND(AF26<>"",AG26<>""),AF26/AG26/12,0),IF($Z26=6,IF(AND(AC26<>"",AD26<>"",AE26<>""),AC26*AD26*AE26,0)+IF(AND(AF26<>"",AG26<>""),AF26/AG26/12,0),"")))))) -> 160000 | AI26: =IF(매핑v2!H22="○",P26,"") -> 20000 | AJ26: =IF(매핑v2!H22="○","○","X") -> ○ | AK26: =IF(매핑v2!H22="○",Y26,"") -> 200000 | AL26: =IF(매핑v2!H22="○","○","X") -> ○ | AM26: =IF(매핑v2!H22="○",AH26,"") -> 160000 | AN26: =IF(매핑v2!H22="○","○","X") -> ○ | AO26: =IF(매핑v2!I22="○",P26,"") -> 20000 | AP26: =IF(매핑v2!I22="○","○","X") -> ○ | AQ26: =IF(매핑v2!I22="○",Y26,"") -> 200000 | AR26: =IF(매핑v2!I22="○","○","X") -> ○ | AS26: =IF(매핑v2!I22="○",AH26,"") -> 160000 | AT26: =IF(매핑v2!I22="○","○","X") -> ○ | AU26: =IF(매핑v2!J22="○",P26,"") -> 20000 | AV26: =IF(매핑v2!J22="○","○","X") -> ○ | AW26: =IF(매핑v2!J22="○",Y26,"") -> 200000 | AX26: =IF(매핑v2!J22="○","○","X") -> ○ | AY26: =IF(매핑v2!J22="○",AH26,"") -> 160000 | AZ26: =IF(매핑v2!J22="○","○","X") -> ○ | BA26: =IF(매핑v2!K22="○",P26,"") | BB26: =IF(매핑v2!K22="○","○","X") -> X | BC26: =IF(매핑v2!K22="○",Y26,"") | BD26: =IF(매핑v2!K22="○","○","X") -> X | BE26: =IF(매핑v2!K22="○",AH26,"") | BF26: =IF(매핑v2!K22="○","○","X") -> X | BG26: =IF(매핑v2!L22="○",P26,"") -> 20000 | BH26: =IF(매핑v2!L22="○","○","X") -> ○ | BI26: =IF(매핑v2!L22="○",Y26,"") -> 200000 | BJ26: ○ | BK26: X | BL26: ○ | BM26: ○ | BN26: X | BO26: X
A27: 26 | B27: 식 | C27: 건강보조제·비타민 | D27: right spec | E27: 성분표 기반 선택 / 흡수율 감안해 직관 대비 1/2만 섭취 | F27: 홈쇼핑/인플루언서 공구 패키지 대량 결제 후 유통기한 지나서 폐기 | G27: 직구 사이트에서 성분 확인 없이 무조건 알약 수 제일 많은 최저가 구매 | H27: 2 | K27: 1 | L27: 1 | M27: 15000 | P27: =IF($H27=1,IF(AND(I27<>"",J27<>""),I27/J27/12,""),IF($H27=2,IF(AND(K27<>"",L27<>"",M27<>""),K27*L27*M27,""),IF($H27=3,IF(AND(N27<>"",O27<>""),N27/O27/12,""),IF($H27=4,IF(AND(I27<>"",J27<>""),I27/J27/12,0)+IF(AND(K27<>"",L27<>"",M27<>""),K27*L27*M27,0),IF($H27=5,IF(AND(I27<>"",J27<>""),I27/J27/12,0)+IF(AND(N27<>"",O27<>""),N27/O27/12,0),IF($H27=6,IF(AND(K27<>"",L27<>"",M27<>""),K27*L27*M27,0)+IF(AND(N27<>"",O27<>""),N27/O27/12,0),"")))))) -> 15000 | Q27: 2 | T27: 1 | U27: 1 | V27: 30000 | Y27: =IF($Q27=1,IF(AND(R27<>"",S27<>""),R27/S27/12,""),IF($Q27=2,IF(AND(T27<>"",U27<>"",V27<>""),T27*U27*V27,""),IF($Q27=3,IF(AND(W27<>"",X27<>""),W27/X27/12,""),IF($Q27=4,IF(AND(R27<>"",S27<>""),R27/S27/12,0)+IF(AND(T27<>"",U27<>"",V27<>""),T27*U27*V27,0),IF($Q27=5,IF(AND(R27<>"",S27<>""),R27/S27/12,0)+IF(AND(W27<>"",X27<>""),W27/X27/12,0),IF($Q27=6,IF(AND(T27<>"",U27<>"",V27<>""),T27*U27*V27,0)+IF(AND(W27<>"",X27<>""),W27/X27/12,0),"")))))) -> 30000 | Z27: 2 | AC27: 1 | AD27: 1 | AE27: 10000 | AH27: =IF($Z27=1,IF(AND(AA27<>"",AB27<>""),AA27/AB27/12,""),IF($Z27=2,IF(AND(AC27<>"",AD27<>"",AE27<>""),AC27*AD27*AE27,""),IF($Z27=3,IF(AND(AF27<>"",AG27<>""),AF27/AG27/12,""),IF($Z27=4,IF(AND(AA27<>"",AB27<>""),AA27/AB27/12,0)+IF(AND(AC27<>"",AD27<>"",AE27<>""),AC27*AD27*AE27,0),IF($Z27=5,IF(AND(AA27<>"",AB27<>""),AA27/AB27/12,0)+IF(AND(AF27<>"",AG27<>""),AF27/AG27/12,0),IF($Z27=6,IF(AND(AC27<>"",AD27<>"",AE27<>""),AC27*AD27*AE27,0)+IF(AND(AF27<>"",AG27<>""),AF27/AG27/12,0),"")))))) -> 10000 | AI27: =IF(매핑v2!H23="○",P27,"") -> 15000 | AJ27: =IF(매핑v2!H23="○","○","X") -> ○ | AK27: =IF(매핑v2!H23="○",Y27,"") -> 30000 | AL27: =IF(매핑v2!H23="○","○","X") -> ○ | AM27: =IF(매핑v2!H23="○",AH27,"") -> 10000 | AN27: =IF(매핑v2!H23="○","○","X") -> ○ | AO27: =IF(매핑v2!I23="○",P27,"") -> 15000 | AP27: =IF(매핑v2!I23="○","○","X") -> ○ | AQ27: =IF(매핑v2!I23="○",Y27,"") -> 30000 | AR27: =IF(매핑v2!I23="○","○","X") -> ○ | AS27: =IF(매핑v2!I23="○",AH27,"") -> 10000 | AT27: =IF(매핑v2!I23="○","○","X") -> ○ | AU27: =IF(매핑v2!J23="○",P27,"") -> 15000 | AV27: =IF(매핑v2!J23="○","○","X") -> ○ | AW27: =IF(매핑v2!J23="○",Y27,"") -> 30000 | AX27: =IF(매핑v2!J23="○","○","X") -> ○ | AY27: =IF(매핑v2!J23="○",AH27,"") -> 10000 | AZ27: =IF(매핑v2!J23="○","○","X") -> ○ | BA27: =IF(매핑v2!K23="○",P27,"") | BB27: =IF(매핑v2!K23="○","○","X") -> X | BC27: =IF(매핑v2!K23="○",Y27,"") | BD27: =IF(매핑v2!K23="○","○","X") -> X | BE27: =IF(매핑v2!K23="○",AH27,"") | BF27: =IF(매핑v2!K23="○","○","X") -> X | BG27: =IF(매핑v2!L23="○",P27,"") -> 15000 | BH27: =IF(매핑v2!L23="○","○","X") -> ○ | BI27: =IF(매핑v2!L23="○",Y27,"") -> 30000 | BJ27: ○ | BK27: X | BL27: ○ | BM27: ○ | BN27: X | BO27: X
A28: 27 | B28: 의 | C28: 속옷·내의 (남성) | D28: simplify | E28: 국산 국민내의 대량 구입 (좋은사람들·BYC 등) | F28: 브랜드/백화점 내의 낱개 구매 누수 | G28: 다이소 초저가 내의 사서 금방 늘어남 | H28: 1 | I28: 6000 | J28: 0.5 | P28: =IF($H28=1,IF(AND(I28<>"",J28<>""),I28/J28/12,""),IF($H28=2,IF(AND(K28<>"",L28<>"",M28<>""),K28*L28*M28,""),IF($H28=3,IF(AND(N28<>"",O28<>""),N28/O28/12,""),IF($H28=4,IF(AND(I28<>"",J28<>""),I28/J28/12,0)+IF(AND(K28<>"",L28<>"",M28<>""),K28*L28*M28,0),IF($H28=5,IF(AND(I28<>"",J28<>""),I28/J28/12,0)+IF(AND(N28<>"",O28<>""),N28/O28/12,0),IF($H28=6,IF(AND(K28<>"",L28<>"",M28<>""),K28*L28*M28,0)+IF(AND(N28<>"",O28<>""),N28/O28/12,0),"")))))) -> 1000 | Q28: 1 | T28: 1 | U28: 1 | V28: 20000 | Y28: =IF($Q28=1,IF(AND(R28<>"",S28<>""),R28/S28/12,""),IF($Q28=2,IF(AND(T28<>"",U28<>"",V28<>""),T28*U28*V28,""),IF($Q28=3,IF(AND(W28<>"",X28<>""),W28/X28/12,""),IF($Q28=4,IF(AND(R28<>"",S28<>""),R28/S28/12,0)+IF(AND(T28<>"",U28<>"",V28<>""),T28*U28*V28,0),IF($Q28=5,IF(AND(R28<>"",S28<>""),R28/S28/12,0)+IF(AND(W28<>"",X28<>""),W28/X28/12,0),IF($Q28=6,IF(AND(T28<>"",U28<>"",V28<>""),T28*U28*V28,0)+IF(AND(W28<>"",X28<>""),W28/X28/12,0),"")))))) | Z28: 3 | AF28: 2000 | AG28: 0.25 | AH28: =IF($Z28=1,IF(AND(AA28<>"",AB28<>""),AA28/AB28/12,""),IF($Z28=2,IF(AND(AC28<>"",AD28<>"",AE28<>""),AC28*AD28*AE28,""),IF($Z28=3,IF(AND(AF28<>"",AG28<>""),AF28/AG28/12,""),IF($Z28=4,IF(AND(AA28<>"",AB28<>""),AA28/AB28/12,0)+IF(AND(AC28<>"",AD28<>"",AE28<>""),AC28*AD28*AE28,0),IF($Z28=5,IF(AND(AA28<>"",AB28<>""),AA28/AB28/12,0)+IF(AND(AF28<>"",AG28<>""),AF28/AG28/12,0),IF($Z28=6,IF(AND(AC28<>"",AD28<>"",AE28<>""),AC28*AD28*AE28,0)+IF(AND(AF28<>"",AG28<>""),AF28/AG28/12,0),"")))))) -> 666.66667 | AI28: =IF(매핑v2!H24="○",P28,"") -> 1000 | AJ28: =IF(매핑v2!H24="○","○","X") -> ○ | AK28: =IF(매핑v2!H24="○",Y28,"") | AL28: =IF(매핑v2!H24="○","○","X") -> ○ | AM28: =IF(매핑v2!H24="○",AH28,"") -> 666.66667 | AN28: =IF(매핑v2!H24="○","○","X") -> ○ | AO28: =IF(매핑v2!I24="○",P28,"") | AP28: =IF(매핑v2!I24="○","○","X") -> X | AQ28: =IF(매핑v2!I24="○",Y28,"") | AR28: =IF(매핑v2!I24="○","○","X") -> X | AS28: =IF(매핑v2!I24="○",AH28,"") | AT28: =IF(매핑v2!I24="○","○","X") -> X | AU28: =IF(매핑v2!J24="○",P28,"") -> 1000 | AV28: =IF(매핑v2!J24="○","○","X") -> ○ | AW28: =IF(매핑v2!J24="○",Y28,"") | AX28: =IF(매핑v2!J24="○","○","X") -> ○ | AY28: =IF(매핑v2!J24="○",AH28,"") -> 666.66667 | AZ28: =IF(매핑v2!J24="○","○","X") -> ○ | BA28: =IF(매핑v2!K24="○",P28,"") -> 1000 | BB28: =IF(매핑v2!K24="○","○","X") -> ○ | BC28: =IF(매핑v2!K24="○",Y28,"") | BD28: =IF(매핑v2!K24="○","○","X") -> ○ | BE28: =IF(매핑v2!K24="○",AH28,"") -> 666.66667 | BF28: =IF(매핑v2!K24="○","○","X") -> ○ | BG28: =IF(매핑v2!L24="○",P28,"") -> 1000 | BH28: =IF(매핑v2!L24="○","○","X") -> ○ | BI28: =IF(매핑v2!L24="○",Y28,"") | BJ28: ○ | BK28: X | BL28: ○ | BM28: ○ | BN28: ○ | BO28: X
A29: 28 | B29: 의 | C29: 아우터·이너 | D29: right spec | E29: 기능성 이너 아울렛 구입 개당 5만원으로 연간 4개 구입 | F29: 신상/브랜드 이너웨어 구매 : 개당 20만원 | G29: 구제 시장 뒤져가며 옷 고르는 시간 낭비 | H29: 1 | I29: =4*50000 -> 200000 | J29: 4 | P29: =IF($H29=1,IF(AND(I29<>"",J29<>""),I29/J29/12,""),IF($H29=2,IF(AND(K29<>"",L29<>"",M29<>""),K29*L29*M29,""),IF($H29=3,IF(AND(N29<>"",O29<>""),N29/O29/12,""),IF($H29=4,IF(AND(I29<>"",J29<>""),I29/J29/12,0)+IF(AND(K29<>"",L29<>"",M29<>""),K29*L29*M29,0),IF($H29=5,IF(AND(I29<>"",J29<>""),I29/J29/12,0)+IF(AND(N29<>"",O29<>""),N29/O29/12,0),IF($H29=6,IF(AND(K29<>"",L29<>"",M29<>""),K29*L29*M29,0)+IF(AND(N29<>"",O29<>""),N29/O29/12,0),"")))))) -> 4166.6667 | Q29: 1 | T29: 1 | U29: 0.5 | V29: 200000 | Y29: =IF($Q29=1,IF(AND(R29<>"",S29<>""),R29/S29/12,""),IF($Q29=2,IF(AND(T29<>"",U29<>"",V29<>""),T29*U29*V29,""),IF($Q29=3,IF(AND(W29<>"",X29<>""),W29/X29/12,""),IF($Q29=4,IF(AND(R29<>"",S29<>""),R29/S29/12,0)+IF(AND(T29<>"",U29<>"",V29<>""),T29*U29*V29,0),IF($Q29=5,IF(AND(R29<>"",S29<>""),R29/S29/12,0)+IF(AND(W29<>"",X29<>""),W29/X29/12,0),IF($Q29=6,IF(AND(T29<>"",U29<>"",V29<>""),T29*U29*V29,0)+IF(AND(W29<>"",X29<>""),W29/X29/12,0),"")))))) | Z29: 1 | AA29: 20000 | AB29: 0.5 | AH29: =IF($Z29=1,IF(AND(AA29<>"",AB29<>""),AA29/AB29/12,""),IF($Z29=2,IF(AND(AC29<>"",AD29<>"",AE29<>""),AC29*AD29*AE29,""),IF($Z29=3,IF(AND(AF29<>"",AG29<>""),AF29/AG29/12,""),IF($Z29=4,IF(AND(AA29<>"",AB29<>""),AA29/AB29/12,0)+IF(AND(AC29<>"",AD29<>"",AE29<>""),AC29*AD29*AE29,0),IF($Z29=5,IF(AND(AA29<>"",AB29<>""),AA29/AB29/12,0)+IF(AND(AF29<>"",AG29<>""),AF29/AG29/12,0),IF($Z29=6,IF(AND(AC29<>"",AD29<>"",AE29<>""),AC29*AD29*AE29,0)+IF(AND(AF29<>"",AG29<>""),AF29/AG29/12,0),"")))))) -> 3333.3333 | AI29: =IF(매핑v2!H25="○",P29,"") -> 4166.6667 | AJ29: =IF(매핑v2!H25="○","○","X") -> ○ | AK29: =IF(매핑v2!H25="○",Y29,"") | AL29: =IF(매핑v2!H25="○","○","X") -> ○ | AM29: =IF(매핑v2!H25="○",AH29,"") -> 3333.3333 | AN29: =IF(매핑v2!H25="○","○","X") -> ○ | AO29: =IF(매핑v2!I25="○",P29,"") -> 4166.6667 | AP29: =IF(매핑v2!I25="○","○","X") -> ○ | AQ29: =IF(매핑v2!I25="○",Y29,"") | AR29: =IF(매핑v2!I25="○","○","X") -> ○ | AS29: =IF(매핑v2!I25="○",AH29,"") -> 3333.3333 | AT29: =IF(매핑v2!I25="○","○","X") -> ○ | AU29: =IF(매핑v2!J25="○",P29,"") -> 4166.6667 | AV29: =IF(매핑v2!J25="○","○","X") -> ○ | AW29: =IF(매핑v2!J25="○",Y29,"") | AX29: =IF(매핑v2!J25="○","○","X") -> ○ | AY29: =IF(매핑v2!J25="○",AH29,"") -> 3333.3333 | AZ29: =IF(매핑v2!J25="○","○","X") -> ○ | BA29: =IF(매핑v2!K25="○",P29,"") -> 4166.6667 | BB29: =IF(매핑v2!K25="○","○","X") -> ○ | BC29: =IF(매핑v2!K25="○",Y29,"") | BD29: =IF(매핑v2!K25="○","○","X") -> ○ | BE29: =IF(매핑v2!K25="○",AH29,"") -> 3333.3333 | BF29: =IF(매핑v2!K25="○","○","X") -> ○ | BG29: =IF(매핑v2!L25="○",P29,"") -> 4166.6667 | BH29: =IF(매핑v2!L25="○","○","X") -> ○ | BI29: =IF(매핑v2!L25="○",Y29,"") | BJ29: ○ | BK29: X | BL29: ○ | BM29: ○ | BN29: ○ | BO29: X
A30: 29 | B30: 의 | C30: 신발 밑창 | D30: 유지보수 | E30: 비브람 밑창 교환으로 신발 수명 연장 | F30: 밑창 닳으면 신발 통째 폐기 및 재구입 | G30: 셀프작업하다 집안에 냄새 가득 노동 | H30: 5 | I30: 150000 | J30: 6 | N30: 30000 | O30: 2 | P30: =IF($H30=1,IF(AND(I30<>"",J30<>""),I30/J30/12,""),IF($H30=2,IF(AND(K30<>"",L30<>"",M30<>""),K30*L30*M30,""),IF($H30=3,IF(AND(N30<>"",O30<>""),N30/O30/12,""),IF($H30=4,IF(AND(I30<>"",J30<>""),I30/J30/12,0)+IF(AND(K30<>"",L30<>"",M30<>""),K30*L30*M30,0),IF($H30=5,IF(AND(I30<>"",J30<>""),I30/J30/12,0)+IF(AND(N30<>"",O30<>""),N30/O30/12,0),IF($H30=6,IF(AND(K30<>"",L30<>"",M30<>""),K30*L30*M30,0)+IF(AND(N30<>"",O30<>""),N30/O30/12,0),"")))))) -> 3333.3333 | Q30: 3 | R30: 200000 | S30: 1 | Y30: =IF($Q30=1,IF(AND(R30<>"",S30<>""),R30/S30/12,""),IF($Q30=2,IF(AND(T30<>"",U30<>"",V30<>""),T30*U30*V30,""),IF($Q30=3,IF(AND(W30<>"",X30<>""),W30/X30/12,""),IF($Q30=4,IF(AND(R30<>"",S30<>""),R30/S30/12,0)+IF(AND(T30<>"",U30<>"",V30<>""),T30*U30*V30,0),IF($Q30=5,IF(AND(R30<>"",S30<>""),R30/S30/12,0)+IF(AND(W30<>"",X30<>""),W30/X30/12,0),IF($Q30=6,IF(AND(T30<>"",U30<>"",V30<>""),T30*U30*V30,0)+IF(AND(W30<>"",X30<>""),W30/X30/12,0),"")))))) | Z30: 5 | AA30: 150000 | AB30: 3 | AF30: 25000 | AG30: 1 | AH30: =IF($Z30=1,IF(AND(AA30<>"",AB30<>""),AA30/AB30/12,""),IF($Z30=2,IF(AND(AC30<>"",AD30<>"",AE30<>""),AC30*AD30*AE30,""),IF($Z30=3,IF(AND(AF30<>"",AG30<>""),AF30/AG30/12,""),IF($Z30=4,IF(AND(AA30<>"",AB30<>""),AA30/AB30/12,0)+IF(AND(AC30<>"",AD30<>"",AE30<>""),AC30*AD30*AE30,0),IF($Z30=5,IF(AND(AA30<>"",AB30<>""),AA30/AB30/12,0)+IF(AND(AF30<>"",AG30<>""),AF30/AG30/12,0),IF($Z30=6,IF(AND(AC30<>"",AD30<>"",AE30<>""),AC30*AD30*AE30,0)+IF(AND(AF30<>"",AG30<>""),AF30/AG30/12,0),"")))))) -> 6250 | AI30: =IF(매핑v2!H26="○",P30,"") -> 3333.3333 | AJ30: =IF(매핑v2!H26="○","○","X") -> ○ | AK30: =IF(매핑v2!H26="○",Y30,"") | AL30: =IF(매핑v2!H26="○","○","X") -> ○ | AM30: =IF(매핑v2!H26="○",AH30,"") -> 6250 | AN30: =IF(매핑v2!H26="○","○","X") -> ○ | AO30: =IF(매핑v2!I26="○",P30,"") -> 3333.3333 | AP30: =IF(매핑v2!I26="○","○","X") -> ○ | AQ30: =IF(매핑v2!I26="○",Y30,"") | AR30: =IF(매핑v2!I26="○","○","X") -> ○ | AS30: =IF(매핑v2!I26="○",AH30,"") -> 6250 | AT30: =IF(매핑v2!I26="○","○","X") -> ○ | AU30: =IF(매핑v2!J26="○",P30,"") -> 3333.3333 | AV30: =IF(매핑v2!J26="○","○","X") -> ○ | AW30: =IF(매핑v2!J26="○",Y30,"") | AX30: =IF(매핑v2!J26="○","○","X") -> ○ | AY30: =IF(매핑v2!J26="○",AH30,"") -> 6250 | AZ30: =IF(매핑v2!J26="○","○","X") -> ○ | BA30: =IF(매핑v2!K26="○",P30,"") -> 3333.3333 | BB30: =IF(매핑v2!K26="○","○","X") -> ○ | BC30: =IF(매핑v2!K26="○",Y30,"") | BD30: =IF(매핑v2!K26="○","○","X") -> ○ | BE30: =IF(매핑v2!K26="○",AH30,"") -> 6250 | BF30: =IF(매핑v2!K26="○","○","X") -> ○ | BG30: =IF(매핑v2!L26="○",P30,"") -> 3333.3333 | BH30: =IF(매핑v2!L26="○","○","X") -> ○ | BI30: =IF(매핑v2!L26="○",Y30,"") | BJ30: ○ | BK30: X | BL30: ○ | BM30: ○ | BN30: X | BO30: X
A31: 30 | B31: 의 | C31: 가죽제품: 가방 | D31: 유지보수 | E31: 가죽 정기 컨디셔닝으로 수명 연장 | F31: 갈라지고 부패하여 통폐기/재구입 | G31: 다이소 구두약으로 인조가죽 문지르다 가죽 망가뜨림 | H31: 5 | I31: 500000 | J31: 10 | N31: 20000 | O31: 5 | P31: =IF($H31=1,IF(AND(I31<>"",J31<>""),I31/J31/12,""),IF($H31=2,IF(AND(K31<>"",L31<>"",M31<>""),K31*L31*M31,""),IF($H31=3,IF(AND(N31<>"",O31<>""),N31/O31/12,""),IF($H31=4,IF(AND(I31<>"",J31<>""),I31/J31/12,0)+IF(AND(K31<>"",L31<>"",M31<>""),K31*L31*M31,0),IF($H31=5,IF(AND(I31<>"",J31<>""),I31/J31/12,0)+IF(AND(N31<>"",O31<>""),N31/O31/12,0),IF($H31=6,IF(AND(K31<>"",L31<>"",M31<>""),K31*L31*M31,0)+IF(AND(N31<>"",O31<>""),N31/O31/12,0),"")))))) -> 4500 | Q31: 5 | R31: 500000 | S31: 2 | Y31: =IF($Q31=1,IF(AND(R31<>"",S31<>""),R31/S31/12,""),IF($Q31=2,IF(AND(T31<>"",U31<>"",V31<>""),T31*U31*V31,""),IF($Q31=3,IF(AND(W31<>"",X31<>""),W31/X31/12,""),IF($Q31=4,IF(AND(R31<>"",S31<>""),R31/S31/12,0)+IF(AND(T31<>"",U31<>"",V31<>""),T31*U31*V31,0),IF($Q31=5,IF(AND(R31<>"",S31<>""),R31/S31/12,0)+IF(AND(W31<>"",X31<>""),W31/X31/12,0),IF($Q31=6,IF(AND(T31<>"",U31<>"",V31<>""),T31*U31*V31,0)+IF(AND(W31<>"",X31<>""),W31/X31/12,0),"")))))) -> 20833.333 | Z31: 1 | AA31: 100000 | AB31: 1 | AH31: =IF($Z31=1,IF(AND(AA31<>"",AB31<>""),AA31/AB31/12,""),IF($Z31=2,IF(AND(AC31<>"",AD31<>"",AE31<>""),AC31*AD31*AE31,""),IF($Z31=3,IF(AND(AF31<>"",AG31<>""),AF31/AG31/12,""),IF($Z31=4,IF(AND(AA31<>"",AB31<>""),AA31/AB31/12,0)+IF(AND(AC31<>"",AD31<>"",AE31<>""),AC31*AD31*AE31,0),IF($Z31=5,IF(AND(AA31<>"",AB31<>""),AA31/AB31/12,0)+IF(AND(AF31<>"",AG31<>""),AF31/AG31/12,0),IF($Z31=6,IF(AND(AC31<>"",AD31<>"",AE31<>""),AC31*AD31*AE31,0)+IF(AND(AF31<>"",AG31<>""),AF31/AG31/12,0),"")))))) -> 8333.3333 | AI31: =IF(매핑v2!H27="○",P31,"") -> 4500 | AJ31: =IF(매핑v2!H27="○","○","X") -> ○ | AK31: =IF(매핑v2!H27="○",Y31,"") -> 20833.333 | AL31: =IF(매핑v2!H27="○","○","X") -> ○ | AM31: =IF(매핑v2!H27="○",AH31,"") -> 8333.3333 | AN31: =IF(매핑v2!H27="○","○","X") -> ○ | AO31: =IF(매핑v2!I27="○",P31,"") -> 4500 | AP31: =IF(매핑v2!I27="○","○","X") -> ○ | AQ31: =IF(매핑v2!I27="○",Y31,"") -> 20833.333 | AR31: =IF(매핑v2!I27="○","○","X") -> ○ | AS31: =IF(매핑v2!I27="○",AH31,"") -> 8333.3333 | AT31: =IF(매핑v2!I27="○","○","X") -> ○ | AU31: =IF(매핑v2!J27="○",P31,"") -> 4500 | AV31: =IF(매핑v2!J27="○","○","X") -> ○ | AW31: =IF(매핑v2!J27="○",Y31,"") -> 20833.333 | AX31: =IF(매핑v2!J27="○","○","X") -> ○ | AY31: =IF(매핑v2!J27="○",AH31,"") -> 8333.3333 | AZ31: =IF(매핑v2!J27="○","○","X") -> ○ | BA31: =IF(매핑v2!K27="○",P31,"") -> 4500 | BB31: =IF(매핑v2!K27="○","○","X") -> ○ | BC31: =IF(매핑v2!K27="○",Y31,"") -> 20833.333 | BD31: =IF(매핑v2!K27="○","○","X") -> ○ | BE31: =IF(매핑v2!K27="○",AH31,"") -> 8333.3333 | BF31: =IF(매핑v2!K27="○","○","X") -> ○ | BG31: =IF(매핑v2!L27="○",P31,"") -> 4500 | BH31: =IF(매핑v2!L27="○","○","X") -> ○ | BI31: =IF(매핑v2!L27="○",Y31,"") -> 20833.333 | BJ31: ○ | BK31: X | BL31: ○ | BM31: ○ | BN31: X | BO31: X
A32: 31 | B32: 의 | C32: 개인용품 (샴푸·바디워시) | D32: sharing | E32: 대용량 구입 후 소분 용기 이용 | F32: 여행/운동용 트래블 키트 매번 구매 누수 | G32: 대용량 통째로 가방에 무겁게 들고 다님 | H32: 3 | N32: 100000 | O32: 3 | P32: =IF($H32=1,IF(AND(I32<>"",J32<>""),I32/J32/12,""),IF($H32=2,IF(AND(K32<>"",L32<>"",M32<>""),K32*L32*M32,""),IF($H32=3,IF(AND(N32<>"",O32<>""),N32/O32/12,""),IF($H32=4,IF(AND(I32<>"",J32<>""),I32/J32/12,0)+IF(AND(K32<>"",L32<>"",M32<>""),K32*L32*M32,0),IF($H32=5,IF(AND(I32<>"",J32<>""),I32/J32/12,0)+IF(AND(N32<>"",O32<>""),N32/O32/12,0),IF($H32=6,IF(AND(K32<>"",L32<>"",M32<>""),K32*L32*M32,0)+IF(AND(N32<>"",O32<>""),N32/O32/12,0),"")))))) -> 2777.7778 | Q32: 3 | W32: 20000 | X32: 1 | Y32: =IF($Q32=1,IF(AND(R32<>"",S32<>""),R32/S32/12,""),IF($Q32=2,IF(AND(T32<>"",U32<>"",V32<>""),T32*U32*V32,""),IF($Q32=3,IF(AND(W32<>"",X32<>""),W32/X32/12,""),IF($Q32=4,IF(AND(R32<>"",S32<>""),R32/S32/12,0)+IF(AND(T32<>"",U32<>"",V32<>""),T32*U32*V32,0),IF($Q32=5,IF(AND(R32<>"",S32<>""),R32/S32/12,0)+IF(AND(W32<>"",X32<>""),W32/X32/12,0),IF($Q32=6,IF(AND(T32<>"",U32<>"",V32<>""),T32*U32*V32,0)+IF(AND(W32<>"",X32<>""),W32/X32/12,0),"")))))) -> 1666.6667 | Z32: 3 | AF32: 20000 | AG32: 1 | AH32: =IF($Z32=1,IF(AND(AA32<>"",AB32<>""),AA32/AB32/12,""),IF($Z32=2,IF(AND(AC32<>"",AD32<>"",AE32<>""),AC32*AD32*AE32,""),IF($Z32=3,IF(AND(AF32<>"",AG32<>""),AF32/AG32/12,""),IF($Z32=4,IF(AND(AA32<>"",AB32<>""),AA32/AB32/12,0)+IF(AND(AC32<>"",AD32<>"",AE32<>""),AC32*AD32*AE32,0),IF($Z32=5,IF(AND(AA32<>"",AB32<>""),AA32/AB32/12,0)+IF(AND(AF32<>"",AG32<>""),AF32/AG32/12,0),IF($Z32=6,IF(AND(AC32<>"",AD32<>"",AE32<>""),AC32*AD32*AE32,0)+IF(AND(AF32<>"",AG32<>""),AF32/AG32/12,0),"")))))) -> 1666.6667 | AI32: =IF(매핑v2!H28="○",P32,"") -> 2777.7778 | AJ32: =IF(매핑v2!H28="○","○","X") -> ○ | AK32: =IF(매핑v2!H28="○",Y32,"") -> 1666.6667 | AL32: =IF(매핑v2!H28="○","○","X") -> ○ | AM32: =IF(매핑v2!H28="○",AH32,"") -> 1666.6667 | AN32: =IF(매핑v2!H28="○","○","X") -> ○ | AO32: =IF(매핑v2!I28="○",P32,"") -> 2777.7778 | AP32: =IF(매핑v2!I28="○","○","X") -> ○ | AQ32: =IF(매핑v2!I28="○",Y32,"") -> 1666.6667 | AR32: =IF(매핑v2!I28="○","○","X") -> ○ | AS32: =IF(매핑v2!I28="○",AH32,"") -> 1666.6667 | AT32: =IF(매핑v2!I28="○","○","X") -> ○ | AU32: =IF(매핑v2!J28="○",P32,"") -> 2777.7778 | AV32: =IF(매핑v2!J28="○","○","X") -> ○ | AW32: =IF(매핑v2!J28="○",Y32,"") -> 1666.6667 | AX32: =IF(매핑v2!J28="○","○","X") -> ○ | AY32: =IF(매핑v2!J28="○",AH32,"") -> 1666.6667 | AZ32: =IF(매핑v2!J28="○","○","X") -> ○ | BA32: =IF(매핑v2!K28="○",P32,"") -> 2777.7778 | BB32: =IF(매핑v2!K28="○","○","X") -> ○ | BC32: =IF(매핑v2!K28="○",Y32,"") -> 1666.6667 | BD32: =IF(매핑v2!K28="○","○","X") -> ○ | BE32: =IF(매핑v2!K28="○",AH32,"") -> 1666.6667 | BF32: =IF(매핑v2!K28="○","○","X") -> ○ | BG32: =IF(매핑v2!L28="○",P32,"") -> 2777.7778 | BH32: =IF(매핑v2!L28="○","○","X") -> ○ | BI32: =IF(매핑v2!L28="○",Y32,"") -> 1666.6667 | BJ32: ○ | BK32: X | BL32: ○ | BM32: ○ | BN32: X | BO32: X
A33: 32 | B33: 의 | C33: 면도기·면도날 (남성) | D33: right spec | E33: 고품질 질레트 대량 구입 + 고무판으로 날 수명 연장 + 클렌징폼을 면도크림 대용 | F33: 올리브영 비싼 진동 면도기 세트 + 전용 쉐이빙 폼 정기 구매 | G33: 모텔 일회용품이나 싸구려 다회용 쓰다 트러블 생겨 피부과 약값 더 나감 | H33: 5 | I33: 10000 | J33: 5 | N33: 100000 | O33: 5 | P33: =IF($H33=1,IF(AND(I33<>"",J33<>""),I33/J33/12,""),IF($H33=2,IF(AND(K33<>"",L33<>"",M33<>""),K33*L33*M33,""),IF($H33=3,IF(AND(N33<>"",O33<>""),N33/O33/12,""),IF($H33=4,IF(AND(I33<>"",J33<>""),I33/J33/12,0)+IF(AND(K33<>"",L33<>"",M33<>""),K33*L33*M33,0),IF($H33=5,IF(AND(I33<>"",J33<>""),I33/J33/12,0)+IF(AND(N33<>"",O33<>""),N33/O33/12,0),IF($H33=6,IF(AND(K33<>"",L33<>"",M33<>""),K33*L33*M33,0)+IF(AND(N33<>"",O33<>""),N33/O33/12,0),"")))))) -> 1833.3333 | Q33: 5 | R33: 50000 | S33: 2 | W33: 40000 | X33: 0.5 | Y33: =IF($Q33=1,IF(AND(R33<>"",S33<>""),R33/S33/12,""),IF($Q33=2,IF(AND(T33<>"",U33<>"",V33<>""),T33*U33*V33,""),IF($Q33=3,IF(AND(W33<>"",X33<>""),W33/X33/12,""),IF($Q33=4,IF(AND(R33<>"",S33<>""),R33/S33/12,0)+IF(AND(T33<>"",U33<>"",V33<>""),T33*U33*V33,0),IF($Q33=5,IF(AND(R33<>"",S33<>""),R33/S33/12,0)+IF(AND(W33<>"",X33<>""),W33/X33/12,0),IF($Q33=6,IF(AND(T33<>"",U33<>"",V33<>""),T33*U33*V33,0)+IF(AND(W33<>"",X33<>""),W33/X33/12,0),"")))))) -> 8750 | Z33: 5 | AC33: 0.25 | AD33: 1 | AE33: 60000 | AF33: 1000 | AG33: 0.25 | AH33: =IF($Z33=1,IF(AND(AA33<>"",AB33<>""),AA33/AB33/12,""),IF($Z33=2,IF(AND(AC33<>"",AD33<>"",AE33<>""),AC33*AD33*AE33,""),IF($Z33=3,IF(AND(AF33<>"",AG33<>""),AF33/AG33/12,""),IF($Z33=4,IF(AND(AA33<>"",AB33<>""),AA33/AB33/12,0)+IF(AND(AC33<>"",AD33<>"",AE33<>""),AC33*AD33*AE33,0),IF($Z33=5,IF(AND(AA33<>"",AB33<>""),AA33/AB33/12,0)+IF(AND(AF33<>"",AG33<>""),AF33/AG33/12,0),IF($Z33=6,IF(AND(AC33<>"",AD33<>"",AE33<>""),AC33*AD33*AE33,0)+IF(AND(AF33<>"",AG33<>""),AF33/AG33/12,0),"")))))) -> 333.33333 | AI33: =IF(매핑v2!H29="○",P33,"") -> 1833.3333 | AJ33: =IF(매핑v2!H29="○","○","X") -> ○ | AK33: =IF(매핑v2!H29="○",Y33,"") -> 8750 | AL33: =IF(매핑v2!H29="○","○","X") -> ○ | AM33: =IF(매핑v2!H29="○",AH33,"") -> 333.33333 | AN33: =IF(매핑v2!H29="○","○","X") -> ○ | AO33: =IF(매핑v2!I29="○",P33,"") | AP33: =IF(매핑v2!I29="○","○","X") -> X | AQ33: =IF(매핑v2!I29="○",Y33,"") | AR33: =IF(매핑v2!I29="○","○","X") -> X | AS33: =IF(매핑v2!I29="○",AH33,"") | AT33: =IF(매핑v2!I29="○","○","X") -> X | AU33: =IF(매핑v2!J29="○",P33,"") -> 1833.3333 | AV33: =IF(매핑v2!J29="○","○","X") -> ○ | AW33: =IF(매핑v2!J29="○",Y33,"") -> 8750 | AX33: =IF(매핑v2!J29="○","○","X") -> ○ | AY33: =IF(매핑v2!J29="○",AH33,"") -> 333.33333 | AZ33: =IF(매핑v2!J29="○","○","X") -> ○ | BA33: =IF(매핑v2!K29="○",P33,"") -> 1833.3333 | BB33: =IF(매핑v2!K29="○","○","X") -> ○ | BC33: =IF(매핑v2!K29="○",Y33,"") -> 8750 | BD33: =IF(매핑v2!K29="○","○","X") -> ○ | BE33: =IF(매핑v2!K29="○",AH33,"") -> 333.33333 | BF33: =IF(매핑v2!K29="○","○","X") -> ○ | BG33: =IF(매핑v2!L29="○",P33,"") -> 1833.3333 | BH33: =IF(매핑v2!L29="○","○","X") -> ○ | BI33: =IF(매핑v2!L29="○",Y33,"") -> 8750 | BJ33: ○ | BK33: X | BL33: ○ | BM33: ○ | BN33: ○ | BO33: X
A34: 33 | B34: 의 | C34: 화장품 기초 (스킨·로션·세럼) | D34: right spec | E34: 닥터지·코스알엑스·바이오더마·세타필 등 (백화점 프리미엄 불필요) | F34: 백화점 1층 명품 브랜드 스킨케어 세트 단위 구매 | G34: 로드샵 1+1 땡처리 할 때만 기다렸다 성분 안 맞아도 억지로 바름 | H34: 3 | N34: =5*10000 -> 50000 | O34: 1.5 | P34: =IF($H34=1,IF(AND(I34<>"",J34<>""),I34/J34/12,""),IF($H34=2,IF(AND(K34<>"",L34<>"",M34<>""),K34*L34*M34,""),IF($H34=3,IF(AND(N34<>"",O34<>""),N34/O34/12,""),IF($H34=4,IF(AND(I34<>"",J34<>""),I34/J34/12,0)+IF(AND(K34<>"",L34<>"",M34<>""),K34*L34*M34,0),IF($H34=5,IF(AND(I34<>"",J34<>""),I34/J34/12,0)+IF(AND(N34<>"",O34<>""),N34/O34/12,0),IF($H34=6,IF(AND(K34<>"",L34<>"",M34<>""),K34*L34*M34,0)+IF(AND(N34<>"",O34<>""),N34/O34/12,0),"")))))) -> 2777.7778 | Q34: 3 | W34: 120000 | X34: 0.5 | Y34: =IF($Q34=1,IF(AND(R34<>"",S34<>""),R34/S34/12,""),IF($Q34=2,IF(AND(T34<>"",U34<>"",V34<>""),T34*U34*V34,""),IF($Q34=3,IF(AND(W34<>"",X34<>""),W34/X34/12,""),IF($Q34=4,IF(AND(R34<>"",S34<>""),R34/S34/12,0)+IF(AND(T34<>"",U34<>"",V34<>""),T34*U34*V34,0),IF($Q34=5,IF(AND(R34<>"",S34<>""),R34/S34/12,0)+IF(AND(W34<>"",X34<>""),W34/X34/12,0),IF($Q34=6,IF(AND(T34<>"",U34<>"",V34<>""),T34*U34*V34,0)+IF(AND(W34<>"",X34<>""),W34/X34/12,0),"")))))) -> 20000 | Z34: 3 | AF34: 30000 | AG34: 0.5 | AH34: =IF($Z34=1,IF(AND(AA34<>"",AB34<>""),AA34/AB34/12,""),IF($Z34=2,IF(AND(AC34<>"",AD34<>"",AE34<>""),AC34*AD34*AE34,""),IF($Z34=3,IF(AND(AF34<>"",AG34<>""),AF34/AG34/12,""),IF($Z34=4,IF(AND(AA34<>"",AB34<>""),AA34/AB34/12,0)+IF(AND(AC34<>"",AD34<>"",AE34<>""),AC34*AD34*AE34,0),IF($Z34=5,IF(AND(AA34<>"",AB34<>""),AA34/AB34/12,0)+IF(AND(AF34<>"",AG34<>""),AF34/AG34/12,0),IF($Z34=6,IF(AND(AC34<>"",AD34<>"",AE34<>""),AC34*AD34*AE34,0)+IF(AND(AF34<>"",AG34<>""),AF34/AG34/12,0),"")))))) -> 5000 | AI34: =IF(매핑v2!H30="○",P34,"") | AJ34: =IF(매핑v2!H30="○","○","X") -> X | AK34: =IF(매핑v2!H30="○",Y34,"") | AL34: =IF(매핑v2!H30="○","○","X") -> X | AM34: =IF(매핑v2!H30="○",AH34,"") | AN34: =IF(매핑v2!H30="○","○","X") -> X | AO34: =IF(매핑v2!I30="○",P34,"") -> 2777.7778 | AP34: =IF(매핑v2!I30="○","○","X") -> ○ | AQ34: =IF(매핑v2!I30="○",Y34,"") -> 20000 | AR34: =IF(매핑v2!I30="○","○","X") -> ○ | AS34: =IF(매핑v2!I30="○",AH34,"") -> 5000 | AT34: =IF(매핑v2!I30="○","○","X") -> ○ | AU34: =IF(매핑v2!J30="○",P34,"") -> 2777.7778 | AV34: =IF(매핑v2!J30="○","○","X") -> ○ | AW34: =IF(매핑v2!J30="○",Y34,"") -> 20000 | AX34: =IF(매핑v2!J30="○","○","X") -> ○ | AY34: =IF(매핑v2!J30="○",AH34,"") -> 5000 | AZ34: =IF(매핑v2!J30="○","○","X") -> ○ | BA34: =IF(매핑v2!K30="○",P34,"") -> 2777.7778 | BB34: =IF(매핑v2!K30="○","○","X") -> ○ | BC34: =IF(매핑v2!K30="○",Y34,"") -> 20000 | BD34: =IF(매핑v2!K30="○","○","X") -> ○ | BE34: =IF(매핑v2!K30="○",AH34,"") -> 5000 | BF34: =IF(매핑v2!K30="○","○","X") -> ○ | BG34: =IF(매핑v2!L30="○",P34,"") | BH34: =IF(매핑v2!L30="○","○","X") -> X | BI34: =IF(매핑v2!L30="○",Y34,"") | BJ34: ○ | BK34: X | BL34: ○ | BM34: ○ | BN34: ○ | BO34: X
A35: 34 | B35: 의 | C35: 화장품 색조 | D35: simplify | E35: daily 1세트로 통일 / 단종 임박 할인 구입 | F35: 뷰티 유튜버 추천 매 시즌 신상 팔레트 다 모음 (화장대 블랙홀 포화) | G35: 유통기한 임박한 땡처리 화장품 무더기로 샀다 피부 발진 발생 | H35: 3 | N35: 40000 | O35: 1 | P35: =IF($H35=1,IF(AND(I35<>"",J35<>""),I35/J35/12,""),IF($H35=2,IF(AND(K35<>"",L35<>"",M35<>""),K35*L35*M35,""),IF($H35=3,IF(AND(N35<>"",O35<>""),N35/O35/12,""),IF($H35=4,IF(AND(I35<>"",J35<>""),I35/J35/12,0)+IF(AND(K35<>"",L35<>"",M35<>""),K35*L35*M35,0),IF($H35=5,IF(AND(I35<>"",J35<>""),I35/J35/12,0)+IF(AND(N35<>"",O35<>""),N35/O35/12,0),IF($H35=6,IF(AND(K35<>"",L35<>"",M35<>""),K35*L35*M35,0)+IF(AND(N35<>"",O35<>""),N35/O35/12,0),"")))))) -> 3333.3333 | Q35: 3 | W35: 40000 | X35: 0.25 | Y35: =IF($Q35=1,IF(AND(R35<>"",S35<>""),R35/S35/12,""),IF($Q35=2,IF(AND(T35<>"",U35<>"",V35<>""),T35*U35*V35,""),IF($Q35=3,IF(AND(W35<>"",X35<>""),W35/X35/12,""),IF($Q35=4,IF(AND(R35<>"",S35<>""),R35/S35/12,0)+IF(AND(T35<>"",U35<>"",V35<>""),T35*U35*V35,0),IF($Q35=5,IF(AND(R35<>"",S35<>""),R35/S35/12,0)+IF(AND(W35<>"",X35<>""),W35/X35/12,0),IF($Q35=6,IF(AND(T35<>"",U35<>"",V35<>""),T35*U35*V35,0)+IF(AND(W35<>"",X35<>""),W35/X35/12,0),"")))))) -> 13333.333 | Z35: 3 | AF35: 20000 | AG35: 0.25 | AH35: =IF($Z35=1,IF(AND(AA35<>"",AB35<>""),AA35/AB35/12,""),IF($Z35=2,IF(AND(AC35<>"",AD35<>"",AE35<>""),AC35*AD35*AE35,""),IF($Z35=3,IF(AND(AF35<>"",AG35<>""),AF35/AG35/12,""),IF($Z35=4,IF(AND(AA35<>"",AB35<>""),AA35/AB35/12,0)+IF(AND(AC35<>"",AD35<>"",AE35<>""),AC35*AD35*AE35,0),IF($Z35=5,IF(AND(AA35<>"",AB35<>""),AA35/AB35/12,0)+IF(AND(AF35<>"",AG35<>""),AF35/AG35/12,0),IF($Z35=6,IF(AND(AC35<>"",AD35<>"",AE35<>""),AC35*AD35*AE35,0)+IF(AND(AF35<>"",AG35<>""),AF35/AG35/12,0),"")))))) -> 6666.6667 | AI35: =IF(매핑v2!H31="○",P35,"") | AJ35: =IF(매핑v2!H31="○","○","X") -> X | AK35: =IF(매핑v2!H31="○",Y35,"") | AL35: =IF(매핑v2!H31="○","○","X") -> X | AM35: =IF(매핑v2!H31="○",AH35,"") | AN35: =IF(매핑v2!H31="○","○","X") -> X | AO35: =IF(매핑v2!I31="○",P35,"") -> 3333.3333 | AP35: =IF(매핑v2!I31="○","○","X") -> ○ | AQ35: =IF(매핑v2!I31="○",Y35,"") -> 13333.333 | AR35: =IF(매핑v2!I31="○","○","X") -> ○ | AS35: =IF(매핑v2!I31="○",AH35,"") -> 6666.6667 | AT35: =IF(매핑v2!I31="○","○","X") -> ○ | AU35: =IF(매핑v2!J31="○",P35,"") -> 3333.3333 | AV35: =IF(매핑v2!J31="○","○","X") -> ○ | AW35: =IF(매핑v2!J31="○",Y35,"") -> 13333.333 | AX35: =IF(매핑v2!J31="○","○","X") -> ○ | AY35: =IF(매핑v2!J31="○",AH35,"") -> 6666.6667 | AZ35: =IF(매핑v2!J31="○","○","X") -> ○ | BA35: =IF(매핑v2!K31="○",P35,"") -> 3333.3333 | BB35: =IF(매핑v2!K31="○","○","X") -> ○ | BC35: =IF(매핑v2!K31="○",Y35,"") -> 13333.333 | BD35: =IF(매핑v2!K31="○","○","X") -> ○ | BE35: =IF(매핑v2!K31="○",AH35,"") -> 6666.6667 | BF35: =IF(매핑v2!K31="○","○","X") -> ○ | BG35: =IF(매핑v2!L31="○",P35,"") | BH35: =IF(매핑v2!L31="○","○","X") -> X | BI35: =IF(매핑v2!L31="○",Y35,"") | BJ35: ○ | BK35: X | BL35: ○ | BM35: ○ | BN35: ○ | BO35: X
A36: 35 | B36: 의 | C36: 헤어케어 (염색·펌) | D36: effectiveness | E36: 미용실 두달에 한 번 + 홈 트리트먼트로 보완 | F36: 대형 미용실 실장의 100만 원 정액권 결제 스크립트에 당해 현금 묶임 | G36: 만원 블루클럽 / 동네 셀프 염색약 썼다 머릿결 상한 상태로 생활 | H36: 6 | K36: 0.5 | L36: 1 | M36: 40000 | N36: 10000 | O36: 1 | P36: =IF($H36=1,IF(AND(I36<>"",J36<>""),I36/J36/12,""),IF($H36=2,IF(AND(K36<>"",L36<>"",M36<>""),K36*L36*M36,""),IF($H36=3,IF(AND(N36<>"",O36<>""),N36/O36/12,""),IF($H36=4,IF(AND(I36<>"",J36<>""),I36/J36/12,0)+IF(AND(K36<>"",L36<>"",M36<>""),K36*L36*M36,0),IF($H36=5,IF(AND(I36<>"",J36<>""),I36/J36/12,0)+IF(AND(N36<>"",O36<>""),N36/O36/12,0),IF($H36=6,IF(AND(K36<>"",L36<>"",M36<>""),K36*L36*M36,0)+IF(AND(N36<>"",O36<>""),N36/O36/12,0),"")))))) -> 20833.333 | Q36: 6 | T36: 1 | U36: 1 | V36: 100000 | Y36: =IF($Q36=1,IF(AND(R36<>"",S36<>""),R36/S36/12,""),IF($Q36=2,IF(AND(T36<>"",U36<>"",V36<>""),T36*U36*V36,""),IF($Q36=3,IF(AND(W36<>"",X36<>""),W36/X36/12,""),IF($Q36=4,IF(AND(R36<>"",S36<>""),R36/S36/12,0)+IF(AND(T36<>"",U36<>"",V36<>""),T36*U36*V36,0),IF($Q36=5,IF(AND(R36<>"",S36<>""),R36/S36/12,0)+IF(AND(W36<>"",X36<>""),W36/X36/12,0),IF($Q36=6,IF(AND(T36<>"",U36<>"",V36<>""),T36*U36*V36,0)+IF(AND(W36<>"",X36<>""),W36/X36/12,0),"")))))) -> 100000 | Z36: 3 | AF36: 10000 | AG36: =1/12 -> 0.083333333 | AH36: =IF($Z36=1,IF(AND(AA36<>"",AB36<>""),AA36/AB36/12,""),IF($Z36=2,IF(AND(AC36<>"",AD36<>"",AE36<>""),AC36*AD36*AE36,""),IF($Z36=3,IF(AND(AF36<>"",AG36<>""),AF36/AG36/12,""),IF($Z36=4,IF(AND(AA36<>"",AB36<>""),AA36/AB36/12,0)+IF(AND(AC36<>"",AD36<>"",AE36<>""),AC36*AD36*AE36,0),IF($Z36=5,IF(AND(AA36<>"",AB36<>""),AA36/AB36/12,0)+IF(AND(AF36<>"",AG36<>""),AF36/AG36/12,0),IF($Z36=6,IF(AND(AC36<>"",AD36<>"",AE36<>""),AC36*AD36*AE36,0)+IF(AND(AF36<>"",AG36<>""),AF36/AG36/12,0),"")))))) -> 10000 | AI36: =IF(매핑v2!H32="○",P36,"") | AJ36: =IF(매핑v2!H32="○","○","X") -> X | AK36: =IF(매핑v2!H32="○",Y36,"") | AL36: =IF(매핑v2!H32="○","○","X") -> X | AM36: =IF(매핑v2!H32="○",AH36,"") | AN36: =IF(매핑v2!H32="○","○","X") -> X | AO36: =IF(매핑v2!I32="○",P36,"") -> 20833.333 | AP36: =IF(매핑v2!I32="○","○","X") -> ○ | AQ36: =IF(매핑v2!I32="○",Y36,"") -> 100000 | AR36: =IF(매핑v2!I32="○","○","X") -> ○ | AS36: =IF(매핑v2!I32="○",AH36,"") -> 10000 | AT36: =IF(매핑v2!I32="○","○","X") -> ○ | AU36: =IF(매핑v2!J32="○",P36,"") -> 20833.333 | AV36: =IF(매핑v2!J32="○","○","X") -> ○ | AW36: =IF(매핑v2!J32="○",Y36,"") -> 100000 | AX36: =IF(매핑v2!J32="○","○","X") -> ○ | AY36: =IF(매핑v2!J32="○",AH36,"") -> 10000 | AZ36: =IF(매핑v2!J32="○","○","X") -> ○ | BA36: =IF(매핑v2!K32="○",P36,"") -> 20833.333 | BB36: =IF(매핑v2!K32="○","○","X") -> ○ | BC36: =IF(매핑v2!K32="○",Y36,"") -> 100000 | BD36: =IF(매핑v2!K32="○","○","X") -> ○ | BE36: =IF(매핑v2!K32="○",AH36,"") -> 10000 | BF36: =IF(매핑v2!K32="○","○","X") -> ○ | BG36: =IF(매핑v2!L32="○",P36,"") | BH36: =IF(매핑v2!L32="○","○","X") -> X | BI36: =IF(매핑v2!L32="○",Y36,"") | BJ36: ○ | BK36: X | BL36: ○ | BM36: ○ | BN36: ○ | BO36: X
A37: 36 | B37: 건강 | C37: 치과 예방 | D37: effectiveness | E37: 이쑤시개·치실·물분사기로 일상 물리적 관리 → 치과 방문 빈도 최소화 | F37: 아플 때까지 방치하다 임플란트·신경치료로 수백만 원 한 번에 탕진 | G37: 양치만 무식하게 세게 오래 하다 치경부 마모증 생겨 레진 치료 받음 | H37: 2 | K37: 1 | L37: 1 | M37: 5000 | P37: =IF($H37=1,IF(AND(I37<>"",J37<>""),I37/J37/12,""),IF($H37=2,IF(AND(K37<>"",L37<>"",M37<>""),K37*L37*M37,""),IF($H37=3,IF(AND(N37<>"",O37<>""),N37/O37/12,""),IF($H37=4,IF(AND(I37<>"",J37<>""),I37/J37/12,0)+IF(AND(K37<>"",L37<>"",M37<>""),K37*L37*M37,0),IF($H37=5,IF(AND(I37<>"",J37<>""),I37/J37/12,0)+IF(AND(N37<>"",O37<>""),N37/O37/12,0),IF($H37=6,IF(AND(K37<>"",L37<>"",M37<>""),K37*L37*M37,0)+IF(AND(N37<>"",O37<>""),N37/O37/12,0),"")))))) -> 5000 | Q37: 3 | W37: 600000 | X37: 1 | Y37: =IF($Q37=1,IF(AND(R37<>"",S37<>""),R37/S37/12,""),IF($Q37=2,IF(AND(T37<>"",U37<>"",V37<>""),T37*U37*V37,""),IF($Q37=3,IF(AND(W37<>"",X37<>""),W37/X37/12,""),IF($Q37=4,IF(AND(R37<>"",S37<>""),R37/S37/12,0)+IF(AND(T37<>"",U37<>"",V37<>""),T37*U37*V37,0),IF($Q37=5,IF(AND(R37<>"",S37<>""),R37/S37/12,0)+IF(AND(W37<>"",X37<>""),W37/X37/12,0),IF($Q37=6,IF(AND(T37<>"",U37<>"",V37<>""),T37*U37*V37,0)+IF(AND(W37<>"",X37<>""),W37/X37/12,0),"")))))) -> 50000 | Z37: 3 | AF37: 300000 | AG37: 1 | AH37: =IF($Z37=1,IF(AND(AA37<>"",AB37<>""),AA37/AB37/12,""),IF($Z37=2,IF(AND(AC37<>"",AD37<>"",AE37<>""),AC37*AD37*AE37,""),IF($Z37=3,IF(AND(AF37<>"",AG37<>""),AF37/AG37/12,""),IF($Z37=4,IF(AND(AA37<>"",AB37<>""),AA37/AB37/12,0)+IF(AND(AC37<>"",AD37<>"",AE37<>""),AC37*AD37*AE37,0),IF($Z37=5,IF(AND(AA37<>"",AB37<>""),AA37/AB37/12,0)+IF(AND(AF37<>"",AG37<>""),AF37/AG37/12,0),IF($Z37=6,IF(AND(AC37<>"",AD37<>"",AE37<>""),AC37*AD37*AE37,0)+IF(AND(AF37<>"",AG37<>""),AF37/AG37/12,0),"")))))) -> 25000 | AI37: =IF(매핑v2!H33="○",P37,"") -> 5000 | AJ37: =IF(매핑v2!H33="○","○","X") -> ○ | AK37: =IF(매핑v2!H33="○",Y37,"") -> 50000 | AL37: =IF(매핑v2!H33="○","○","X") -> ○ | AM37: =IF(매핑v2!H33="○",AH37,"") -> 25000 | AN37: =IF(매핑v2!H33="○","○","X") -> ○ | AO37: =IF(매핑v2!I33="○",P37,"") -> 5000 | AP37: =IF(매핑v2!I33="○","○","X") -> ○ | AQ37: =IF(매핑v2!I33="○",Y37,"") -> 50000 | AR37: =IF(매핑v2!I33="○","○","X") -> ○ | AS37: =IF(매핑v2!I33="○",AH37,"") -> 25000 | AT37: =IF(매핑v2!I33="○","○","X") -> ○ | AU37: =IF(매핑v2!J33="○",P37,"") -> 5000 | AV37: =IF(매핑v2!J33="○","○","X") -> ○ | AW37: =IF(매핑v2!J33="○",Y37,"") -> 50000 | AX37: =IF(매핑v2!J33="○","○","X") -> ○ | AY37: =IF(매핑v2!J33="○",AH37,"") -> 25000 | AZ37: =IF(매핑v2!J33="○","○","X") -> ○ | BA37: =IF(매핑v2!K33="○",P37,"") -> 5000 | BB37: =IF(매핑v2!K33="○","○","X") -> ○ | BC37: =IF(매핑v2!K33="○",Y37,"") -> 50000 | BD37: =IF(매핑v2!K33="○","○","X") -> ○ | BE37: =IF(매핑v2!K33="○",AH37,"") -> 25000 | BF37: =IF(매핑v2!K33="○","○","X") -> ○ | BG37: =IF(매핑v2!L33="○",P37,"") -> 5000 | BH37: =IF(매핑v2!L33="○","○","X") -> ○ | BI37: =IF(매핑v2!L33="○",Y37,"") -> 50000 | BJ37: ○ | BK37: X | BL37: X | BM37: ○ | BN37: ○ | BO37: X
A38: 37 | B38: 건강 | C38: 안경·렌즈 | D38: right spec | E38: 고품질 안경 1개 장기 사용 | F38: 유행하는 젠틀몬스터 등 브랜드 안경테 다수 소유 / 렌즈 안경점 정가 구매 | G38: 시력에 안 맞는 길거리 싸구려 테 쓰며 눈 피로도 급증 및 시력 저하 | H38: 1 | I38: 600000 | J38: 5 | P38: =IF($H38=1,IF(AND(I38<>"",J38<>""),I38/J38/12,""),IF($H38=2,IF(AND(K38<>"",L38<>"",M38<>""),K38*L38*M38,""),IF($H38=3,IF(AND(N38<>"",O38<>""),N38/O38/12,""),IF($H38=4,IF(AND(I38<>"",J38<>""),I38/J38/12,0)+IF(AND(K38<>"",L38<>"",M38<>""),K38*L38*M38,0),IF($H38=5,IF(AND(I38<>"",J38<>""),I38/J38/12,0)+IF(AND(N38<>"",O38<>""),N38/O38/12,0),IF($H38=6,IF(AND(K38<>"",L38<>"",M38<>""),K38*L38*M38,0)+IF(AND(N38<>"",O38<>""),N38/O38/12,0),"")))))) -> 10000 | Q38: 1 | R38: 250000 | S38: 1 | Y38: =IF($Q38=1,IF(AND(R38<>"",S38<>""),R38/S38/12,""),IF($Q38=2,IF(AND(T38<>"",U38<>"",V38<>""),T38*U38*V38,""),IF($Q38=3,IF(AND(W38<>"",X38<>""),W38/X38/12,""),IF($Q38=4,IF(AND(R38<>"",S38<>""),R38/S38/12,0)+IF(AND(T38<>"",U38<>"",V38<>""),T38*U38*V38,0),IF($Q38=5,IF(AND(R38<>"",S38<>""),R38/S38/12,0)+IF(AND(W38<>"",X38<>""),W38/X38/12,0),IF($Q38=6,IF(AND(T38<>"",U38<>"",V38<>""),T38*U38*V38,0)+IF(AND(W38<>"",X38<>""),W38/X38/12,0),"")))))) -> 20833.333 | Z38: 1 | AA38: 60000 | AB38: 1 | AH38: =IF($Z38=1,IF(AND(AA38<>"",AB38<>""),AA38/AB38/12,""),IF($Z38=2,IF(AND(AC38<>"",AD38<>"",AE38<>""),AC38*AD38*AE38,""),IF($Z38=3,IF(AND(AF38<>"",AG38<>""),AF38/AG38/12,""),IF($Z38=4,IF(AND(AA38<>"",AB38<>""),AA38/AB38/12,0)+IF(AND(AC38<>"",AD38<>"",AE38<>""),AC38*AD38*AE38,0),IF($Z38=5,IF(AND(AA38<>"",AB38<>""),AA38/AB38/12,0)+IF(AND(AF38<>"",AG38<>""),AF38/AG38/12,0),IF($Z38=6,IF(AND(AC38<>"",AD38<>"",AE38<>""),AC38*AD38*AE38,0)+IF(AND(AF38<>"",AG38<>""),AF38/AG38/12,0),"")))))) -> 5000 | AI38: =IF(매핑v2!H34="○",P38,"") -> 10000 | AJ38: =IF(매핑v2!H34="○","○","X") -> ○ | AK38: =IF(매핑v2!H34="○",Y38,"") -> 20833.333 | AL38: =IF(매핑v2!H34="○","○","X") -> ○ | AM38: =IF(매핑v2!H34="○",AH38,"") -> 5000 | AN38: =IF(매핑v2!H34="○","○","X") -> ○ | AO38: =IF(매핑v2!I34="○",P38,"") -> 10000 | AP38: =IF(매핑v2!I34="○","○","X") -> ○ | AQ38: =IF(매핑v2!I34="○",Y38,"") -> 20833.333 | AR38: =IF(매핑v2!I34="○","○","X") -> ○ | AS38: =IF(매핑v2!I34="○",AH38,"") -> 5000 | AT38: =IF(매핑v2!I34="○","○","X") -> ○ | AU38: =IF(매핑v2!J34="○",P38,"") -> 10000 | AV38: =IF(매핑v2!J34="○","○","X") -> ○ | AW38: =IF(매핑v2!J34="○",Y38,"") -> 20833.333 | AX38: =IF(매핑v2!J34="○","○","X") -> ○ | AY38: =IF(매핑v2!J34="○",AH38,"") -> 5000 | AZ38: =IF(매핑v2!J34="○","○","X") -> ○ | BA38: =IF(매핑v2!K34="○",P38,"") -> 10000 | BB38: =IF(매핑v2!K34="○","○","X") -> ○ | BC38: =IF(매핑v2!K34="○",Y38,"") -> 20833.333 | BD38: =IF(매핑v2!K34="○","○","X") -> ○ | BE38: =IF(매핑v2!K34="○",AH38,"") -> 5000 | BF38: =IF(매핑v2!K34="○","○","X") -> ○ | BG38: =IF(매핑v2!L34="○",P38,"") -> 10000 | BH38: =IF(매핑v2!L34="○","○","X") -> ○ | BI38: =IF(매핑v2!L34="○",Y38,"") -> 20833.333 | BJ38: ○ | BK38: X | BL38: ○ | BM38: ○ | BN38: ○ | BO38: X
A39: 38 | B39: 기호 | C39: 커피 | D39: DIY | E39: 게샤 등 고품질 원두 직접 드립 / 드립백 자작 또는 드립 필터만 구매 | F39: 브랜드 커피 전문점 무심코 이용 | G39: 가성비 저가 커피숍 찾아 원정 통근 | H39: 6 | K39: 1 | L39: 1 | M39: 40000 | N39: 20000 | O39: 0.25 | P39: =IF($H39=1,IF(AND(I39<>"",J39<>""),I39/J39/12,""),IF($H39=2,IF(AND(K39<>"",L39<>"",M39<>""),K39*L39*M39,""),IF($H39=3,IF(AND(N39<>"",O39<>""),N39/O39/12,""),IF($H39=4,IF(AND(I39<>"",J39<>""),I39/J39/12,0)+IF(AND(K39<>"",L39<>"",M39<>""),K39*L39*M39,0),IF($H39=5,IF(AND(I39<>"",J39<>""),I39/J39/12,0)+IF(AND(N39<>"",O39<>""),N39/O39/12,0),IF($H39=6,IF(AND(K39<>"",L39<>"",M39<>""),K39*L39*M39,0)+IF(AND(N39<>"",O39<>""),N39/O39/12,0),"")))))) -> 46666.667 | Q39: 2 | T39: 20 | U39: 1 | V39: 5000 | Y39: =IF($Q39=1,IF(AND(R39<>"",S39<>""),R39/S39/12,""),IF($Q39=2,IF(AND(T39<>"",U39<>"",V39<>""),T39*U39*V39,""),IF($Q39=3,IF(AND(W39<>"",X39<>""),W39/X39/12,""),IF($Q39=4,IF(AND(R39<>"",S39<>""),R39/S39/12,0)+IF(AND(T39<>"",U39<>"",V39<>""),T39*U39*V39,0),IF($Q39=5,IF(AND(R39<>"",S39<>""),R39/S39/12,0)+IF(AND(W39<>"",X39<>""),W39/X39/12,0),IF($Q39=6,IF(AND(T39<>"",U39<>"",V39<>""),T39*U39*V39,0)+IF(AND(W39<>"",X39<>""),W39/X39/12,0),"")))))) -> 100000 | Z39: 2 | AC39: 20 | AD39: 1 | AE39: 1800 | AH39: =IF($Z39=1,IF(AND(AA39<>"",AB39<>""),AA39/AB39/12,""),IF($Z39=2,IF(AND(AC39<>"",AD39<>"",AE39<>""),AC39*AD39*AE39,""),IF($Z39=3,IF(AND(AF39<>"",AG39<>""),AF39/AG39/12,""),IF($Z39=4,IF(AND(AA39<>"",AB39<>""),AA39/AB39/12,0)+IF(AND(AC39<>"",AD39<>"",AE39<>""),AC39*AD39*AE39,0),IF($Z39=5,IF(AND(AA39<>"",AB39<>""),AA39/AB39/12,0)+IF(AND(AF39<>"",AG39<>""),AF39/AG39/12,0),IF($Z39=6,IF(AND(AC39<>"",AD39<>"",AE39<>""),AC39*AD39*AE39,0)+IF(AND(AF39<>"",AG39<>""),AF39/AG39/12,0),"")))))) -> 36000 | AI39: =IF(매핑v2!H35="○",P39,"") -> 46666.667 | AJ39: =IF(매핑v2!H35="○","○","X") -> ○ | AK39: =IF(매핑v2!H35="○",Y39,"") -> 100000 | AL39: =IF(매핑v2!H35="○","○","X") -> ○ | AM39: =IF(매핑v2!H35="○",AH39,"") -> 36000 | AN39: =IF(매핑v2!H35="○","○","X") -> ○ | AO39: =IF(매핑v2!I35="○",P39,"") -> 46666.667 | AP39: =IF(매핑v2!I35="○","○","X") -> ○ | AQ39: =IF(매핑v2!I35="○",Y39,"") -> 100000 | AR39: =IF(매핑v2!I35="○","○","X") -> ○ | AS39: =IF(매핑v2!I35="○",AH39,"") -> 36000 | AT39: =IF(매핑v2!I35="○","○","X") -> ○ | AU39: =IF(매핑v2!J35="○",P39,"") -> 46666.667 | AV39: =IF(매핑v2!J35="○","○","X") -> ○ | AW39: =IF(매핑v2!J35="○",Y39,"") -> 100000 | AX39: =IF(매핑v2!J35="○","○","X") -> ○ | AY39: =IF(매핑v2!J35="○",AH39,"") -> 36000 | AZ39: =IF(매핑v2!J35="○","○","X") -> ○ | BA39: =IF(매핑v2!K35="○",P39,"") -> 46666.667 | BB39: =IF(매핑v2!K35="○","○","X") -> ○ | BC39: =IF(매핑v2!K35="○",Y39,"") -> 100000 | BD39: =IF(매핑v2!K35="○","○","X") -> ○ | BE39: =IF(매핑v2!K35="○",AH39,"") -> 36000 | BF39: =IF(매핑v2!K35="○","○","X") -> ○ | BG39: =IF(매핑v2!L35="○",P39,"") -> 46666.667 | BH39: =IF(매핑v2!L35="○","○","X") -> ○ | BI39: =IF(매핑v2!L35="○",Y39,"") -> 100000 | BJ39: ○ | BK39: X | BL39: ○ | BM39: ○ | BN39: X | BO39: X
A40: 39 | B40: 기호 | C40: 차·음료 | D40: condensate | E40: 티백 직접 구입해 우리기 — 기성 티백보다 품질 우수 | F40: 무거운 페트병 음료 박스 단위 구매/노동 | G40: 저가 보급형 대용량 현미녹차 쟁여두기 | H40: 3 | N40: 5000 | O40: 0.5 | P40: =IF($H40=1,IF(AND(I40<>"",J40<>""),I40/J40/12,""),IF($H40=2,IF(AND(K40<>"",L40<>"",M40<>""),K40*L40*M40,""),IF($H40=3,IF(AND(N40<>"",O40<>""),N40/O40/12,""),IF($H40=4,IF(AND(I40<>"",J40<>""),I40/J40/12,0)+IF(AND(K40<>"",L40<>"",M40<>""),K40*L40*M40,0),IF($H40=5,IF(AND(I40<>"",J40<>""),I40/J40/12,0)+IF(AND(N40<>"",O40<>""),N40/O40/12,0),IF($H40=6,IF(AND(K40<>"",L40<>"",M40<>""),K40*L40*M40,0)+IF(AND(N40<>"",O40<>""),N40/O40/12,0),"")))))) -> 833.33333 | Q40: 2 | T40: 4 | U40: 1 | V40: 30000 | Y40: =IF($Q40=1,IF(AND(R40<>"",S40<>""),R40/S40/12,""),IF($Q40=2,IF(AND(T40<>"",U40<>"",V40<>""),T40*U40*V40,""),IF($Q40=3,IF(AND(W40<>"",X40<>""),W40/X40/12,""),IF($Q40=4,IF(AND(R40<>"",S40<>""),R40/S40/12,0)+IF(AND(T40<>"",U40<>"",V40<>""),T40*U40*V40,0),IF($Q40=5,IF(AND(R40<>"",S40<>""),R40/S40/12,0)+IF(AND(W40<>"",X40<>""),W40/X40/12,0),IF($Q40=6,IF(AND(T40<>"",U40<>"",V40<>""),T40*U40*V40,0)+IF(AND(W40<>"",X40<>""),W40/X40/12,0),"")))))) -> 120000 | Z40: 2 | AC40: 1 | AD40: 1 | AE40: 2500 | AH40: =IF($Z40=1,IF(AND(AA40<>"",AB40<>""),AA40/AB40/12,""),IF($Z40=2,IF(AND(AC40<>"",AD40<>"",AE40<>""),AC40*AD40*AE40,""),IF($Z40=3,IF(AND(AF40<>"",AG40<>""),AF40/AG40/12,""),IF($Z40=4,IF(AND(AA40<>"",AB40<>""),AA40/AB40/12,0)+IF(AND(AC40<>"",AD40<>"",AE40<>""),AC40*AD40*AE40,0),IF($Z40=5,IF(AND(AA40<>"",AB40<>""),AA40/AB40/12,0)+IF(AND(AF40<>"",AG40<>""),AF40/AG40/12,0),IF($Z40=6,IF(AND(AC40<>"",AD40<>"",AE40<>""),AC40*AD40*AE40,0)+IF(AND(AF40<>"",AG40<>""),AF40/AG40/12,0),"")))))) -> 2500 | AI40: =IF(매핑v2!H36="○",P40,"") -> 833.33333 | AJ40: =IF(매핑v2!H36="○","○","X") -> ○ | AK40: =IF(매핑v2!H36="○",Y40,"") -> 120000 | AL40: =IF(매핑v2!H36="○","○","X") -> ○ | AM40: =IF(매핑v2!H36="○",AH40,"") -> 2500 | AN40: =IF(매핑v2!H36="○","○","X") -> ○ | AO40: =IF(매핑v2!I36="○",P40,"") -> 833.33333 | AP40: =IF(매핑v2!I36="○","○","X") -> ○ | AQ40: =IF(매핑v2!I36="○",Y40,"") -> 120000 | AR40: =IF(매핑v2!I36="○","○","X") -> ○ | AS40: =IF(매핑v2!I36="○",AH40,"") -> 2500 | AT40: =IF(매핑v2!I36="○","○","X") -> ○ | AU40: =IF(매핑v2!J36="○",P40,"") -> 833.33333 | AV40: =IF(매핑v2!J36="○","○","X") -> ○ | AW40: =IF(매핑v2!J36="○",Y40,"") -> 120000 | AX40: =IF(매핑v2!J36="○","○","X") -> ○ | AY40: =IF(매핑v2!J36="○",AH40,"") -> 2500 | AZ40: =IF(매핑v2!J36="○","○","X") -> ○ | BA40: =IF(매핑v2!K36="○",P40,"") -> 833.33333 | BB40: =IF(매핑v2!K36="○","○","X") -> ○ | BC40: =IF(매핑v2!K36="○",Y40,"") -> 120000 | BD40: =IF(매핑v2!K36="○","○","X") -> ○ | BE40: =IF(매핑v2!K36="○",AH40,"") -> 2500 | BF40: =IF(매핑v2!K36="○","○","X") -> ○ | BG40: =IF(매핑v2!L36="○",P40,"") -> 833.33333 | BH40: =IF(매핑v2!L36="○","○","X") -> ○ | BI40: =IF(매핑v2!L36="○",Y40,"") -> 120000 | BJ40: ○ | BK40: X | BL40: ○ | BM40: ○ | BN40: X | BO40: X
A41: 40 | B41: 기호 | C41: 주류 | D41: condensate | E41: 독주(안동소주·VSOP 꼬냑) + 얼음 — 부피 낮고 안주 과식 방지 | F41: 부피 큰 맥주 구매 및 페트병 분리수거 지옥 | G41: 초저가 발포주 대량 구매하여 배부름 가중 | H41: 2 | K41: 1 | L41: 0.5 | M41: 70000 | P41: =IF($H41=1,IF(AND(I41<>"",J41<>""),I41/J41/12,""),IF($H41=2,IF(AND(K41<>"",L41<>"",M41<>""),K41*L41*M41,""),IF($H41=3,IF(AND(N41<>"",O41<>""),N41/O41/12,""),IF($H41=4,IF(AND(I41<>"",J41<>""),I41/J41/12,0)+IF(AND(K41<>"",L41<>"",M41<>""),K41*L41*M41,0),IF($H41=5,IF(AND(I41<>"",J41<>""),I41/J41/12,0)+IF(AND(N41<>"",O41<>""),N41/O41/12,0),IF($H41=6,IF(AND(K41<>"",L41<>"",M41<>""),K41*L41*M41,0)+IF(AND(N41<>"",O41<>""),N41/O41/12,0),"")))))) -> 35000 | Q41: 2 | T41: 4 | U41: 1 | V41: 12000 | Y41: =IF($Q41=1,IF(AND(R41<>"",S41<>""),R41/S41/12,""),IF($Q41=2,IF(AND(T41<>"",U41<>"",V41<>""),T41*U41*V41,""),IF($Q41=3,IF(AND(W41<>"",X41<>""),W41/X41/12,""),IF($Q41=4,IF(AND(R41<>"",S41<>""),R41/S41/12,0)+IF(AND(T41<>"",U41<>"",V41<>""),T41*U41*V41,0),IF($Q41=5,IF(AND(R41<>"",S41<>""),R41/S41/12,0)+IF(AND(W41<>"",X41<>""),W41/X41/12,0),IF($Q41=6,IF(AND(T41<>"",U41<>"",V41<>""),T41*U41*V41,0)+IF(AND(W41<>"",X41<>""),W41/X41/12,0),"")))))) -> 48000 | Z41: 2 | AC41: 8 | AD41: 1 | AE41: 8000 | AH41: =IF($Z41=1,IF(AND(AA41<>"",AB41<>""),AA41/AB41/12,""),IF($Z41=2,IF(AND(AC41<>"",AD41<>"",AE41<>""),AC41*AD41*AE41,""),IF($Z41=3,IF(AND(AF41<>"",AG41<>""),AF41/AG41/12,""),IF($Z41=4,IF(AND(AA41<>"",AB41<>""),AA41/AB41/12,0)+IF(AND(AC41<>"",AD41<>"",AE41<>""),AC41*AD41*AE41,0),IF($Z41=5,IF(AND(AA41<>"",AB41<>""),AA41/AB41/12,0)+IF(AND(AF41<>"",AG41<>""),AF41/AG41/12,0),IF($Z41=6,IF(AND(AC41<>"",AD41<>"",AE41<>""),AC41*AD41*AE41,0)+IF(AND(AF41<>"",AG41<>""),AF41/AG41/12,0),"")))))) -> 64000 | AI41: =IF(매핑v2!H37="○",P41,"") -> 35000 | AJ41: =IF(매핑v2!H37="○","○","X") -> ○ | AK41: =IF(매핑v2!H37="○",Y41,"") -> 48000 | AL41: =IF(매핑v2!H37="○","○","X") -> ○ | AM41: =IF(매핑v2!H37="○",AH41,"") -> 64000 | AN41: =IF(매핑v2!H37="○","○","X") -> ○ | AO41: =IF(매핑v2!I37="○",P41,"") | AP41: =IF(매핑v2!I37="○","○","X") -> X | AQ41: =IF(매핑v2!I37="○",Y41,"") | AR41: =IF(매핑v2!I37="○","○","X") -> X | AS41: =IF(매핑v2!I37="○",AH41,"") | AT41: =IF(매핑v2!I37="○","○","X") -> X | AU41: =IF(매핑v2!J37="○",P41,"") | AV41: =IF(매핑v2!J37="○","○","X") -> X | AW41: =IF(매핑v2!J37="○",Y41,"") | AX41: =IF(매핑v2!J37="○","○","X") -> X | AY41: =IF(매핑v2!J37="○",AH41,"") | AZ41: =IF(매핑v2!J37="○","○","X") -> X | BA41: =IF(매핑v2!K37="○",P41,"") | BB41: =IF(매핑v2!K37="○","○","X") -> X | BC41: =IF(매핑v2!K37="○",Y41,"") | BD41: =IF(매핑v2!K37="○","○","X") -> X | BE41: =IF(매핑v2!K37="○",AH41,"") | BF41: =IF(매핑v2!K37="○","○","X") -> X | BG41: =IF(매핑v2!L37="○",P41,"") | BH41: =IF(매핑v2!L37="○","○","X") -> X | BI41: =IF(매핑v2!L37="○",Y41,"") | BJ41: ○ | BK41: X | BL41: ○ | BM41: ○ | BN41: X | BO41: X
A42: 41 | B42: 기호 | C42: 간식·견과류 | D42: simplify | E42: 캐슈넛·야채크래커 등 제품 통일하여 대용량 구입 | F42: 온갖 프리미엄 간식 탐색 과소비 | G42: 최저가 못난이 견과류 검색, 안먹고 버림 | H42: 2 | K42: 1 | L42: 1 | M42: 20000 | P42: =IF($H42=1,IF(AND(I42<>"",J42<>""),I42/J42/12,""),IF($H42=2,IF(AND(K42<>"",L42<>"",M42<>""),K42*L42*M42,""),IF($H42=3,IF(AND(N42<>"",O42<>""),N42/O42/12,""),IF($H42=4,IF(AND(I42<>"",J42<>""),I42/J42/12,0)+IF(AND(K42<>"",L42<>"",M42<>""),K42*L42*M42,0),IF($H42=5,IF(AND(I42<>"",J42<>""),I42/J42/12,0)+IF(AND(N42<>"",O42<>""),N42/O42/12,0),IF($H42=6,IF(AND(K42<>"",L42<>"",M42<>""),K42*L42*M42,0)+IF(AND(N42<>"",O42<>""),N42/O42/12,0),"")))))) -> 20000 | Q42: 2 | T42: 4 | U42: 1 | V42: 30000 | Y42: =IF($Q42=1,IF(AND(R42<>"",S42<>""),R42/S42/12,""),IF($Q42=2,IF(AND(T42<>"",U42<>"",V42<>""),T42*U42*V42,""),IF($Q42=3,IF(AND(W42<>"",X42<>""),W42/X42/12,""),IF($Q42=4,IF(AND(R42<>"",S42<>""),R42/S42/12,0)+IF(AND(T42<>"",U42<>"",V42<>""),T42*U42*V42,0),IF($Q42=5,IF(AND(R42<>"",S42<>""),R42/S42/12,0)+IF(AND(W42<>"",X42<>""),W42/X42/12,0),IF($Q42=6,IF(AND(T42<>"",U42<>"",V42<>""),T42*U42*V42,0)+IF(AND(W42<>"",X42<>""),W42/X42/12,0),"")))))) -> 120000 | Z42: 2 | AC42: 2 | AD42: 1 | AE42: 7800 | AH42: =IF($Z42=1,IF(AND(AA42<>"",AB42<>""),AA42/AB42/12,""),IF($Z42=2,IF(AND(AC42<>"",AD42<>"",AE42<>""),AC42*AD42*AE42,""),IF($Z42=3,IF(AND(AF42<>"",AG42<>""),AF42/AG42/12,""),IF($Z42=4,IF(AND(AA42<>"",AB42<>""),AA42/AB42/12,0)+IF(AND(AC42<>"",AD42<>"",AE42<>""),AC42*AD42*AE42,0),IF($Z42=5,IF(AND(AA42<>"",AB42<>""),AA42/AB42/12,0)+IF(AND(AF42<>"",AG42<>""),AF42/AG42/12,0),IF($Z42=6,IF(AND(AC42<>"",AD42<>"",AE42<>""),AC42*AD42*AE42,0)+IF(AND(AF42<>"",AG42<>""),AF42/AG42/12,0),"")))))) -> 15600 | AI42: =IF(매핑v2!H38="○",P42,"") -> 20000 | AJ42: =IF(매핑v2!H38="○","○","X") -> ○ | AK42: =IF(매핑v2!H38="○",Y42,"") -> 120000 | AL42: =IF(매핑v2!H38="○","○","X") -> ○ | AM42: =IF(매핑v2!H38="○",AH42,"") -> 15600 | AN42: =IF(매핑v2!H38="○","○","X") -> ○ | AO42: =IF(매핑v2!I38="○",P42,"") -> 20000 | AP42: =IF(매핑v2!I38="○","○","X") -> ○ | AQ42: =IF(매핑v2!I38="○",Y42,"") -> 120000 | AR42: =IF(매핑v2!I38="○","○","X") -> ○ | AS42: =IF(매핑v2!I38="○",AH42,"") -> 15600 | AT42: =IF(매핑v2!I38="○","○","X") -> ○ | AU42: =IF(매핑v2!J38="○",P42,"") -> 20000 | AV42: =IF(매핑v2!J38="○","○","X") -> ○ | AW42: =IF(매핑v2!J38="○",Y42,"") -> 120000 | AX42: =IF(매핑v2!J38="○","○","X") -> ○ | AY42: =IF(매핑v2!J38="○",AH42,"") -> 15600 | AZ42: =IF(매핑v2!J38="○","○","X") -> ○ | BA42: =IF(매핑v2!K38="○",P42,"") | BB42: =IF(매핑v2!K38="○","○","X") -> X | BC42: =IF(매핑v2!K38="○",Y42,"") | BD42: =IF(매핑v2!K38="○","○","X") -> X | BE42: =IF(매핑v2!K38="○",AH42,"") | BF42: =IF(매핑v2!K38="○","○","X") -> X | BG42: =IF(매핑v2!L38="○",P42,"") -> 20000 | BH42: =IF(매핑v2!L38="○","○","X") -> ○ | BI42: =IF(매핑v2!L38="○",Y42,"") -> 120000 | BJ42: ○ | BK42: X | BL42: ○ | BM42: ○ | BN42: X | BO42: X
A43: 42 | B43: 취미 | C43: 오디오 | D43: 중고품 당근 | E43: 90~2000년대 중고 오디오 컴포넌트 단위 구입 | F43: 일반인 기준 제외 (관심 없음) | G43: 당근 키워드 알림 보며 무한 잠복 스트레스받다가 최신 국내, 중국산 오디오 구입, 오디오 카페 의견에 따라 고가 케이블/멀티탭 구입 | H43: 1 | I43: 7000000 | J43: 10 | P43: =IF($H43=1,IF(AND(I43<>"",J43<>""),I43/J43/12,""),IF($H43=2,IF(AND(K43<>"",L43<>"",M43<>""),K43*L43*M43,""),IF($H43=3,IF(AND(N43<>"",O43<>""),N43/O43/12,""),IF($H43=4,IF(AND(I43<>"",J43<>""),I43/J43/12,0)+IF(AND(K43<>"",L43<>"",M43<>""),K43*L43*M43,0),IF($H43=5,IF(AND(I43<>"",J43<>""),I43/J43/12,0)+IF(AND(N43<>"",O43<>""),N43/O43/12,0),IF($H43=6,IF(AND(K43<>"",L43<>"",M43<>""),K43*L43*M43,0)+IF(AND(N43<>"",O43<>""),N43/O43/12,0),"")))))) -> 58333.333 | Q43: 1 | Y43: =IF($Q43=1,IF(AND(R43<>"",S43<>""),R43/S43/12,""),IF($Q43=2,IF(AND(T43<>"",U43<>"",V43<>""),T43*U43*V43,""),IF($Q43=3,IF(AND(W43<>"",X43<>""),W43/X43/12,""),IF($Q43=4,IF(AND(R43<>"",S43<>""),R43/S43/12,0)+IF(AND(T43<>"",U43<>"",V43<>""),T43*U43*V43,0),IF($Q43=5,IF(AND(R43<>"",S43<>""),R43/S43/12,0)+IF(AND(W43<>"",X43<>""),W43/X43/12,0),IF($Q43=6,IF(AND(T43<>"",U43<>"",V43<>""),T43*U43*V43,0)+IF(AND(W43<>"",X43<>""),W43/X43/12,0),"")))))) | Z43: 5 | AA43: 900000 | AB43: 2 | AF43: 600000 | AG43: 2 | AH43: =IF($Z43=1,IF(AND(AA43<>"",AB43<>""),AA43/AB43/12,""),IF($Z43=2,IF(AND(AC43<>"",AD43<>"",AE43<>""),AC43*AD43*AE43,""),IF($Z43=3,IF(AND(AF43<>"",AG43<>""),AF43/AG43/12,""),IF($Z43=4,IF(AND(AA43<>"",AB43<>""),AA43/AB43/12,0)+IF(AND(AC43<>"",AD43<>"",AE43<>""),AC43*AD43*AE43,0),IF($Z43=5,IF(AND(AA43<>"",AB43<>""),AA43/AB43/12,0)+IF(AND(AF43<>"",AG43<>""),AF43/AG43/12,0),IF($Z43=6,IF(AND(AC43<>"",AD43<>"",AE43<>""),AC43*AD43*AE43,0)+IF(AND(AF43<>"",AG43<>""),AF43/AG43/12,0),"")))))) -> 62500 | AI43: =IF(매핑v2!H39="○",P43,"") -> 58333.333 | AJ43: =IF(매핑v2!H39="○","○","X") -> ○ | AK43: =IF(매핑v2!H39="○",Y43,"") | AL43: =IF(매핑v2!H39="○","○","X") -> ○ | AM43: =IF(매핑v2!H39="○",AH43,"") -> 62500 | AN43: =IF(매핑v2!H39="○","○","X") -> ○ | AO43: =IF(매핑v2!I39="○",P43,"") | AP43: =IF(매핑v2!I39="○","○","X") -> X | AQ43: =IF(매핑v2!I39="○",Y43,"") | AR43: =IF(매핑v2!I39="○","○","X") -> X | AS43: =IF(매핑v2!I39="○",AH43,"") | AT43: =IF(매핑v2!I39="○","○","X") -> X | AU43: =IF(매핑v2!J39="○",P43,"") | AV43: =IF(매핑v2!J39="○","○","X") -> X | AW43: =IF(매핑v2!J39="○",Y43,"") | AX43: =IF(매핑v2!J39="○","○","X") -> X | AY43: =IF(매핑v2!J39="○",AH43,"") | AZ43: =IF(매핑v2!J39="○","○","X") -> X | BA43: =IF(매핑v2!K39="○",P43,"") | BB43: =IF(매핑v2!K39="○","○","X") -> X | BC43: =IF(매핑v2!K39="○",Y43,"") | BD43: =IF(매핑v2!K39="○","○","X") -> X | BE43: =IF(매핑v2!K39="○",AH43,"") | BF43: =IF(매핑v2!K39="○","○","X") -> X | BG43: =IF(매핑v2!L39="○",P43,"") | BH43: =IF(매핑v2!L39="○","○","X") -> X | BI43: =IF(매핑v2!L39="○",Y43,"") | BJ43: ○ | BL43: ○ | BM43: ○ | BO43: X
A44: 43 | B44: 취미 | C44: 사진·카메라 | D44: 중고품 당근 | E44: 중형 카메라·렌즈 중고 구입 | F44: 일반인 기준 제외 (관심 없음) | G44: 밤낮으로 장터 매물 사기 검증 스트레스로 미러리스 카메라, 렌즈 구입후 호환 지옥 | H44: 1 | I44: 6000000 | J44: 7 | P44: =IF($H44=1,IF(AND(I44<>"",J44<>""),I44/J44/12,""),IF($H44=2,IF(AND(K44<>"",L44<>"",M44<>""),K44*L44*M44,""),IF($H44=3,IF(AND(N44<>"",O44<>""),N44/O44/12,""),IF($H44=4,IF(AND(I44<>"",J44<>""),I44/J44/12,0)+IF(AND(K44<>"",L44<>"",M44<>""),K44*L44*M44,0),IF($H44=5,IF(AND(I44<>"",J44<>""),I44/J44/12,0)+IF(AND(N44<>"",O44<>""),N44/O44/12,0),IF($H44=6,IF(AND(K44<>"",L44<>"",M44<>""),K44*L44*M44,0)+IF(AND(N44<>"",O44<>""),N44/O44/12,0),"")))))) -> 71428.571 | Q44: 1 | Y44: =IF($Q44=1,IF(AND(R44<>"",S44<>""),R44/S44/12,""),IF($Q44=2,IF(AND(T44<>"",U44<>"",V44<>""),T44*U44*V44,""),IF($Q44=3,IF(AND(W44<>"",X44<>""),W44/X44/12,""),IF($Q44=4,IF(AND(R44<>"",S44<>""),R44/S44/12,0)+IF(AND(T44<>"",U44<>"",V44<>""),T44*U44*V44,0),IF($Q44=5,IF(AND(R44<>"",S44<>""),R44/S44/12,0)+IF(AND(W44<>"",X44<>""),W44/X44/12,0),IF($Q44=6,IF(AND(T44<>"",U44<>"",V44<>""),T44*U44*V44,0)+IF(AND(W44<>"",X44<>""),W44/X44/12,0),"")))))) | Z44: 1 | AA44: 2000000 | AB44: 2 | AH44: =IF($Z44=1,IF(AND(AA44<>"",AB44<>""),AA44/AB44/12,""),IF($Z44=2,IF(AND(AC44<>"",AD44<>"",AE44<>""),AC44*AD44*AE44,""),IF($Z44=3,IF(AND(AF44<>"",AG44<>""),AF44/AG44/12,""),IF($Z44=4,IF(AND(AA44<>"",AB44<>""),AA44/AB44/12,0)+IF(AND(AC44<>"",AD44<>"",AE44<>""),AC44*AD44*AE44,0),IF($Z44=5,IF(AND(AA44<>"",AB44<>""),AA44/AB44/12,0)+IF(AND(AF44<>"",AG44<>""),AF44/AG44/12,0),IF($Z44=6,IF(AND(AC44<>"",AD44<>"",AE44<>""),AC44*AD44*AE44,0)+IF(AND(AF44<>"",AG44<>""),AF44/AG44/12,0),"")))))) -> 83333.333 | AI44: =IF(매핑v2!H40="○",P44,"") -> 71428.571 | AJ44: =IF(매핑v2!H40="○","○","X") -> ○ | AK44: =IF(매핑v2!H40="○",Y44,"") | AL44: =IF(매핑v2!H40="○","○","X") -> ○ | AM44: =IF(매핑v2!H40="○",AH44,"") -> 83333.333 | AN44: =IF(매핑v2!H40="○","○","X") -> ○ | AO44: =IF(매핑v2!I40="○",P44,"") -> 71428.571 | AP44: =IF(매핑v2!I40="○","○","X") -> ○ | AQ44: =IF(매핑v2!I40="○",Y44,"") | AR44: =IF(매핑v2!I40="○","○","X") -> ○ | AS44: =IF(매핑v2!I40="○",AH44,"") -> 83333.333 | AT44: =IF(매핑v2!I40="○","○","X") -> ○ | AU44: =IF(매핑v2!J40="○",P44,"") | AV44: =IF(매핑v2!J40="○","○","X") -> X | AW44: =IF(매핑v2!J40="○",Y44,"") | AX44: =IF(매핑v2!J40="○","○","X") -> X | AY44: =IF(매핑v2!J40="○",AH44,"") | AZ44: =IF(매핑v2!J40="○","○","X") -> X | BA44: =IF(매핑v2!K40="○",P44,"") | BB44: =IF(매핑v2!K40="○","○","X") -> X | BC44: =IF(매핑v2!K40="○",Y44,"") | BD44: =IF(매핑v2!K40="○","○","X") -> X | BE44: =IF(매핑v2!K40="○",AH44,"") | BF44: =IF(매핑v2!K40="○","○","X") -> X | BG44: =IF(매핑v2!L40="○",P44,"") | BH44: =IF(매핑v2!L40="○","○","X") -> X | BI44: =IF(매핑v2!L40="○",Y44,"") | BJ44: ○ | BL44: ○ | BM44: ○ | BO44: X
A45: 44 | B45: 취미 | C45: 스포츠 용품 | D45: 중고품 당근 | E45: 등산·낚시·골프채 중고 구입 | F45: 유행 따라 신상 풀세트 구매 감가 | G45: 상태 불량 매물 잘못 사서 이중 지출 고생 | H45: 1 | I45: 1500000 | J45: 5 | P45: =IF($H45=1,IF(AND(I45<>"",J45<>""),I45/J45/12,""),IF($H45=2,IF(AND(K45<>"",L45<>"",M45<>""),K45*L45*M45,""),IF($H45=3,IF(AND(N45<>"",O45<>""),N45/O45/12,""),IF($H45=4,IF(AND(I45<>"",J45<>""),I45/J45/12,0)+IF(AND(K45<>"",L45<>"",M45<>""),K45*L45*M45,0),IF($H45=5,IF(AND(I45<>"",J45<>""),I45/J45/12,0)+IF(AND(N45<>"",O45<>""),N45/O45/12,0),IF($H45=6,IF(AND(K45<>"",L45<>"",M45<>""),K45*L45*M45,0)+IF(AND(N45<>"",O45<>""),N45/O45/12,0),"")))))) -> 25000 | Q45: 1 | R45: 1500000 | S45: 5 | Y45: =IF($Q45=1,IF(AND(R45<>"",S45<>""),R45/S45/12,""),IF($Q45=2,IF(AND(T45<>"",U45<>"",V45<>""),T45*U45*V45,""),IF($Q45=3,IF(AND(W45<>"",X45<>""),W45/X45/12,""),IF($Q45=4,IF(AND(R45<>"",S45<>""),R45/S45/12,0)+IF(AND(T45<>"",U45<>"",V45<>""),T45*U45*V45,0),IF($Q45=5,IF(AND(R45<>"",S45<>""),R45/S45/12,0)+IF(AND(W45<>"",X45<>""),W45/X45/12,0),IF($Q45=6,IF(AND(T45<>"",U45<>"",V45<>""),T45*U45*V45,0)+IF(AND(W45<>"",X45<>""),W45/X45/12,0),"")))))) -> 25000 | Z45: 1 | AA45: 250000 | AB45: 1 | AH45: =IF($Z45=1,IF(AND(AA45<>"",AB45<>""),AA45/AB45/12,""),IF($Z45=2,IF(AND(AC45<>"",AD45<>"",AE45<>""),AC45*AD45*AE45,""),IF($Z45=3,IF(AND(AF45<>"",AG45<>""),AF45/AG45/12,""),IF($Z45=4,IF(AND(AA45<>"",AB45<>""),AA45/AB45/12,0)+IF(AND(AC45<>"",AD45<>"",AE45<>""),AC45*AD45*AE45,0),IF($Z45=5,IF(AND(AA45<>"",AB45<>""),AA45/AB45/12,0)+IF(AND(AF45<>"",AG45<>""),AF45/AG45/12,0),IF($Z45=6,IF(AND(AC45<>"",AD45<>"",AE45<>""),AC45*AD45*AE45,0)+IF(AND(AF45<>"",AG45<>""),AF45/AG45/12,0),"")))))) -> 20833.333 | AI45: =IF(매핑v2!H41="○",P45,"") -> 25000 | AJ45: =IF(매핑v2!H41="○","○","X") -> ○ | AK45: =IF(매핑v2!H41="○",Y45,"") -> 25000 | AL45: =IF(매핑v2!H41="○","○","X") -> ○ | AM45: =IF(매핑v2!H41="○",AH45,"") -> 20833.333 | AN45: =IF(매핑v2!H41="○","○","X") -> ○ | AO45: =IF(매핑v2!I41="○",P45,"") -> 25000 | AP45: =IF(매핑v2!I41="○","○","X") -> ○ | AQ45: =IF(매핑v2!I41="○",Y45,"") -> 25000 | AR45: =IF(매핑v2!I41="○","○","X") -> ○ | AS45: =IF(매핑v2!I41="○",AH45,"") -> 20833.333 | AT45: =IF(매핑v2!I41="○","○","X") -> ○ | AU45: =IF(매핑v2!J41="○",P45,"") -> 25000 | AV45: =IF(매핑v2!J41="○","○","X") -> ○ | AW45: =IF(매핑v2!J41="○",Y45,"") -> 25000 | AX45: =IF(매핑v2!J41="○","○","X") -> ○ | AY45: =IF(매핑v2!J41="○",AH45,"") -> 20833.333 | AZ45: =IF(매핑v2!J41="○","○","X") -> ○ | BA45: =IF(매핑v2!K41="○",P45,"") | BB45: =IF(매핑v2!K41="○","○","X") -> X | BC45: =IF(매핑v2!K41="○",Y45,"") | BD45: =IF(매핑v2!K41="○","○","X") -> X | BE45: =IF(매핑v2!K41="○",AH45,"") | BF45: =IF(매핑v2!K41="○","○","X") -> X | BG45: =IF(매핑v2!L41="○",P45,"") -> 25000 | BH45: =IF(매핑v2!L41="○","○","X") -> ○ | BI45: =IF(매핑v2!L41="○",Y45,"") -> 25000 | BJ45: ○ | BK45: X | BL45: X | BM45: ○ | BN45: X | BO45: X
A46: 45 | B46: 취미 | C46: 비일상 가방 | D46: 중고품 당근 | E46: 보스턴백 등 비일상 가방 중고 구입 | F46: 필요할 때마다 새 제품 구매 방치 | G46: 중고 직거래하러 왕복 1시간 운전 노동 | H46: 1 | I46: 50000 | J46: 5 | P46: =IF($H46=1,IF(AND(I46<>"",J46<>""),I46/J46/12,""),IF($H46=2,IF(AND(K46<>"",L46<>"",M46<>""),K46*L46*M46,""),IF($H46=3,IF(AND(N46<>"",O46<>""),N46/O46/12,""),IF($H46=4,IF(AND(I46<>"",J46<>""),I46/J46/12,0)+IF(AND(K46<>"",L46<>"",M46<>""),K46*L46*M46,0),IF($H46=5,IF(AND(I46<>"",J46<>""),I46/J46/12,0)+IF(AND(N46<>"",O46<>""),N46/O46/12,0),IF($H46=6,IF(AND(K46<>"",L46<>"",M46<>""),K46*L46*M46,0)+IF(AND(N46<>"",O46<>""),N46/O46/12,0),"")))))) -> 833.33333 | Q46: 1 | R46: 250000 | S46: 5 | Y46: =IF($Q46=1,IF(AND(R46<>"",S46<>""),R46/S46/12,""),IF($Q46=2,IF(AND(T46<>"",U46<>"",V46<>""),T46*U46*V46,""),IF($Q46=3,IF(AND(W46<>"",X46<>""),W46/X46/12,""),IF($Q46=4,IF(AND(R46<>"",S46<>""),R46/S46/12,0)+IF(AND(T46<>"",U46<>"",V46<>""),T46*U46*V46,0),IF($Q46=5,IF(AND(R46<>"",S46<>""),R46/S46/12,0)+IF(AND(W46<>"",X46<>""),W46/X46/12,0),IF($Q46=6,IF(AND(T46<>"",U46<>"",V46<>""),T46*U46*V46,0)+IF(AND(W46<>"",X46<>""),W46/X46/12,0),"")))))) -> 4166.6667 | Z46: 1 | AA46: 35000 | AB46: 2 | AH46: =IF($Z46=1,IF(AND(AA46<>"",AB46<>""),AA46/AB46/12,""),IF($Z46=2,IF(AND(AC46<>"",AD46<>"",AE46<>""),AC46*AD46*AE46,""),IF($Z46=3,IF(AND(AF46<>"",AG46<>""),AF46/AG46/12,""),IF($Z46=4,IF(AND(AA46<>"",AB46<>""),AA46/AB46/12,0)+IF(AND(AC46<>"",AD46<>"",AE46<>""),AC46*AD46*AE46,0),IF($Z46=5,IF(AND(AA46<>"",AB46<>""),AA46/AB46/12,0)+IF(AND(AF46<>"",AG46<>""),AF46/AG46/12,0),IF($Z46=6,IF(AND(AC46<>"",AD46<>"",AE46<>""),AC46*AD46*AE46,0)+IF(AND(AF46<>"",AG46<>""),AF46/AG46/12,0),"")))))) -> 1458.3333 | AI46: =IF(매핑v2!H42="○",P46,"") -> 833.33333 | AJ46: =IF(매핑v2!H42="○","○","X") -> ○ | AK46: =IF(매핑v2!H42="○",Y46,"") -> 4166.6667 | AL46: =IF(매핑v2!H42="○","○","X") -> ○ | AM46: =IF(매핑v2!H42="○",AH46,"") -> 1458.3333 | AN46: =IF(매핑v2!H42="○","○","X") -> ○ | AO46: =IF(매핑v2!I42="○",P46,"") -> 833.33333 | AP46: =IF(매핑v2!I42="○","○","X") -> ○ | AQ46: =IF(매핑v2!I42="○",Y46,"") -> 4166.6667 | AR46: =IF(매핑v2!I42="○","○","X") -> ○ | AS46: =IF(매핑v2!I42="○",AH46,"") -> 1458.3333 | AT46: =IF(매핑v2!I42="○","○","X") -> ○ | AU46: =IF(매핑v2!J42="○",P46,"") -> 833.33333 | AV46: =IF(매핑v2!J42="○","○","X") -> ○ | AW46: =IF(매핑v2!J42="○",Y46,"") -> 4166.6667 | AX46: =IF(매핑v2!J42="○","○","X") -> ○ | AY46: =IF(매핑v2!J42="○",AH46,"") -> 1458.3333 | AZ46: =IF(매핑v2!J42="○","○","X") -> ○ | BA46: =IF(매핑v2!K42="○",P46,"") | BB46: =IF(매핑v2!K42="○","○","X") -> X | BC46: =IF(매핑v2!K42="○",Y46,"") | BD46: =IF(매핑v2!K42="○","○","X") -> X | BE46: =IF(매핑v2!K42="○",AH46,"") | BF46: =IF(매핑v2!K42="○","○","X") -> X | BG46: =IF(매핑v2!L42="○",P46,"") -> 833.33333 | BH46: =IF(매핑v2!L42="○","○","X") -> ○ | BI46: =IF(매핑v2!L42="○",Y46,"") -> 4166.6667 | BJ46: ○ | BK46: X | BL46: ○ | BM46: ○ | BN46: X | BO46: X
A47: 46 | B47: 취미 | C47: 피트니스 | D47: 중고품 당근 | E47: 연간 회원권 중고 구입 (체험 후 지속 여부 결정 선행) | F47: 정가 연간권 결제 후 유령 회원 | G47: 헬스장 거리 멀어도 무조건 싼 곳 결제 | H47: 1 | I47: 450000 | J47: =8/12 -> 0.66666667 | P47: =IF($H47=1,IF(AND(I47<>"",J47<>""),I47/J47/12,""),IF($H47=2,IF(AND(K47<>"",L47<>"",M47<>""),K47*L47*M47,""),IF($H47=3,IF(AND(N47<>"",O47<>""),N47/O47/12,""),IF($H47=4,IF(AND(I47<>"",J47<>""),I47/J47/12,0)+IF(AND(K47<>"",L47<>"",M47<>""),K47*L47*M47,0),IF($H47=5,IF(AND(I47<>"",J47<>""),I47/J47/12,0)+IF(AND(N47<>"",O47<>""),N47/O47/12,0),IF($H47=6,IF(AND(K47<>"",L47<>"",M47<>""),K47*L47*M47,0)+IF(AND(N47<>"",O47<>""),N47/O47/12,0),"")))))) -> 56250 | Q47: 1 | R47: 1200000 | S47: 1 | Y47: =IF($Q47=1,IF(AND(R47<>"",S47<>""),R47/S47/12,""),IF($Q47=2,IF(AND(T47<>"",U47<>"",V47<>""),T47*U47*V47,""),IF($Q47=3,IF(AND(W47<>"",X47<>""),W47/X47/12,""),IF($Q47=4,IF(AND(R47<>"",S47<>""),R47/S47/12,0)+IF(AND(T47<>"",U47<>"",V47<>""),T47*U47*V47,0),IF($Q47=5,IF(AND(R47<>"",S47<>""),R47/S47/12,0)+IF(AND(W47<>"",X47<>""),W47/X47/12,0),IF($Q47=6,IF(AND(T47<>"",U47<>"",V47<>""),T47*U47*V47,0)+IF(AND(W47<>"",X47<>""),W47/X47/12,0),"")))))) -> 100000 | Z47: 1 | AC47: 1 | AD47: 1 | AE47: 30000 | AH47: =IF($Z47=1,IF(AND(AA47<>"",AB47<>""),AA47/AB47/12,""),IF($Z47=2,IF(AND(AC47<>"",AD47<>"",AE47<>""),AC47*AD47*AE47,""),IF($Z47=3,IF(AND(AF47<>"",AG47<>""),AF47/AG47/12,""),IF($Z47=4,IF(AND(AA47<>"",AB47<>""),AA47/AB47/12,0)+IF(AND(AC47<>"",AD47<>"",AE47<>""),AC47*AD47*AE47,0),IF($Z47=5,IF(AND(AA47<>"",AB47<>""),AA47/AB47/12,0)+IF(AND(AF47<>"",AG47<>""),AF47/AG47/12,0),IF($Z47=6,IF(AND(AC47<>"",AD47<>"",AE47<>""),AC47*AD47*AE47,0)+IF(AND(AF47<>"",AG47<>""),AF47/AG47/12,0),"")))))) | AI47: =IF(매핑v2!H44="○",P47,"") -> 56250 | AJ47: =IF(매핑v2!H44="○","○","X") -> ○ | AK47: =IF(매핑v2!H44="○",Y47,"") -> 100000 | AL47: =IF(매핑v2!H44="○","○","X") -> ○ | AM47: =IF(매핑v2!H44="○",AH47,"") | AN47: =IF(매핑v2!H44="○","○","X") -> ○ | AO47: =IF(매핑v2!I44="○",P47,"") -> 56250 | AP47: =IF(매핑v2!I44="○","○","X") -> ○ | AQ47: =IF(매핑v2!I44="○",Y47,"") -> 100000 | AR47: =IF(매핑v2!I44="○","○","X") -> ○ | AS47: =IF(매핑v2!I44="○",AH47,"") | AT47: =IF(매핑v2!I44="○","○","X") -> ○ | AU47: =IF(매핑v2!J44="○",P47,"") -> 56250 | AV47: =IF(매핑v2!J44="○","○","X") -> ○ | AW47: =IF(매핑v2!J44="○",Y47,"") -> 100000 | AX47: =IF(매핑v2!J44="○","○","X") -> ○ | AY47: =IF(매핑v2!J44="○",AH47,"") | AZ47: =IF(매핑v2!J44="○","○","X") -> ○ | BA47: =IF(매핑v2!K44="○",P47,"") | BB47: =IF(매핑v2!K44="○","○","X") -> X | BC47: =IF(매핑v2!K44="○",Y47,"") | BD47: =IF(매핑v2!K44="○","○","X") -> X | BE47: =IF(매핑v2!K44="○",AH47,"") | BF47: =IF(매핑v2!K44="○","○","X") -> X | BG47: =IF(매핑v2!L44="○",P47,"") -> 56250 | BH47: =IF(매핑v2!L44="○","○","X") -> ○ | BI47: =IF(매핑v2!L44="○",Y47,"") -> 100000 | BJ47: ○ | BK47: X | BL47: ○ | BM47: ○ | BN47: X | BO47: X
A48: 47 | B48: 취미 | C48: 반려식물 | D48: DIY | E48: 소형 포트 화분 직접 육성 | F48: 대형 완성 화분 구매 및 폐기 반복 | G48: 산이나 들에서 흙 파오기 육체 노동 | H48: 2 | K48: 1 | L48: 1 | M48: 3000 | P48: =IF($H48=1,IF(AND(I48<>"",J48<>""),I48/J48/12,""),IF($H48=2,IF(AND(K48<>"",L48<>"",M48<>""),K48*L48*M48,""),IF($H48=3,IF(AND(N48<>"",O48<>""),N48/O48/12,""),IF($H48=4,IF(AND(I48<>"",J48<>""),I48/J48/12,0)+IF(AND(K48<>"",L48<>"",M48<>""),K48*L48*M48,0),IF($H48=5,IF(AND(I48<>"",J48<>""),I48/J48/12,0)+IF(AND(N48<>"",O48<>""),N48/O48/12,0),IF($H48=6,IF(AND(K48<>"",L48<>"",M48<>""),K48*L48*M48,0)+IF(AND(N48<>"",O48<>""),N48/O48/12,0),"")))))) -> 3000 | Q48: 1 | R48: 200000 | S48: 1 | Y48: =IF($Q48=1,IF(AND(R48<>"",S48<>""),R48/S48/12,""),IF($Q48=2,IF(AND(T48<>"",U48<>"",V48<>""),T48*U48*V48,""),IF($Q48=3,IF(AND(W48<>"",X48<>""),W48/X48/12,""),IF($Q48=4,IF(AND(R48<>"",S48<>""),R48/S48/12,0)+IF(AND(T48<>"",U48<>"",V48<>""),T48*U48*V48,0),IF($Q48=5,IF(AND(R48<>"",S48<>""),R48/S48/12,0)+IF(AND(W48<>"",X48<>""),W48/X48/12,0),IF($Q48=6,IF(AND(T48<>"",U48<>"",V48<>""),T48*U48*V48,0)+IF(AND(W48<>"",X48<>""),W48/X48/12,0),"")))))) -> 16666.667 | Z48: 2 | AC48: 1 | AD48: 1 | AE48: 2000 | AH48: =IF($Z48=1,IF(AND(AA48<>"",AB48<>""),AA48/AB48/12,""),IF($Z48=2,IF(AND(AC48<>"",AD48<>"",AE48<>""),AC48*AD48*AE48,""),IF($Z48=3,IF(AND(AF48<>"",AG48<>""),AF48/AG48/12,""),IF($Z48=4,IF(AND(AA48<>"",AB48<>""),AA48/AB48/12,0)+IF(AND(AC48<>"",AD48<>"",AE48<>""),AC48*AD48*AE48,0),IF($Z48=5,IF(AND(AA48<>"",AB48<>""),AA48/AB48/12,0)+IF(AND(AF48<>"",AG48<>""),AF48/AG48/12,0),IF($Z48=6,IF(AND(AC48<>"",AD48<>"",AE48<>""),AC48*AD48*AE48,0)+IF(AND(AF48<>"",AG48<>""),AF48/AG48/12,0),"")))))) -> 2000 | AI48: =IF(매핑v2!H45="○",P48,"") -> 3000 | AJ48: =IF(매핑v2!H45="○","○","X") -> ○ | AK48: =IF(매핑v2!H45="○",Y48,"") -> 16666.667 | AL48: =IF(매핑v2!H45="○","○","X") -> ○ | AM48: =IF(매핑v2!H45="○",AH48,"") -> 2000 | AN48: =IF(매핑v2!H45="○","○","X") -> ○ | AO48: =IF(매핑v2!I45="○",P48,"") -> 3000 | AP48: =IF(매핑v2!I45="○","○","X") -> ○ | AQ48: =IF(매핑v2!I45="○",Y48,"") -> 16666.667 | AR48: =IF(매핑v2!I45="○","○","X") -> ○ | AS48: =IF(매핑v2!I45="○",AH48,"") -> 2000 | AT48: =IF(매핑v2!I45="○","○","X") -> ○ | AU48: =IF(매핑v2!J45="○",P48,"") -> 3000 | AV48: =IF(매핑v2!J45="○","○","X") -> ○ | AW48: =IF(매핑v2!J45="○",Y48,"") -> 16666.667 | AX48: =IF(매핑v2!J45="○","○","X") -> ○ | AY48: =IF(매핑v2!J45="○",AH48,"") -> 2000 | AZ48: =IF(매핑v2!J45="○","○","X") -> ○ | BA48: =IF(매핑v2!K45="○",P48,"") -> 3000 | BB48: =IF(매핑v2!K45="○","○","X") -> ○ | BC48: =IF(매핑v2!K45="○",Y48,"") -> 16666.667 | BD48: =IF(매핑v2!K45="○","○","X") -> ○ | BE48: =IF(매핑v2!K45="○",AH48,"") -> 2000 | BF48: =IF(매핑v2!K45="○","○","X") -> ○ | BG48: =IF(매핑v2!L45="○",P48,"") -> 3000 | BH48: =IF(매핑v2!L45="○","○","X") -> ○ | BI48: =IF(매핑v2!L45="○",Y48,"") -> 16666.667 | BJ48: ○ | BK48: X | BL48: ○ | BM48: ○ | BN48: X | BO48: X
A49: 48 | B49: 취미 | C49: 여성 취미 (공예·요가·필라테스) | D49: 검증 | E49: 원데이 클래스로 먼저 체험 → 정기 등록 결정 | F49: 6개월치 풀 결제 + 장비 최고급 세팅 후 3주 만에 질려서 드롭(Drop) | G49: 무료 유튜브만 보며 집에서 혼자 하다 자세 망가지거나 흥미 잃음 | H49: 2 | K49: 1 | L49: 0.5 | M49: 50000 | P49: =IF($H49=1,IF(AND(I49<>"",J49<>""),I49/J49/12,""),IF($H49=2,IF(AND(K49<>"",L49<>"",M49<>""),K49*L49*M49,""),IF($H49=3,IF(AND(N49<>"",O49<>""),N49/O49/12,""),IF($H49=4,IF(AND(I49<>"",J49<>""),I49/J49/12,0)+IF(AND(K49<>"",L49<>"",M49<>""),K49*L49*M49,0),IF($H49=5,IF(AND(I49<>"",J49<>""),I49/J49/12,0)+IF(AND(N49<>"",O49<>""),N49/O49/12,0),IF($H49=6,IF(AND(K49<>"",L49<>"",M49<>""),K49*L49*M49,0)+IF(AND(N49<>"",O49<>""),N49/O49/12,0),"")))))) -> 25000 | Q49: 2 | T49: 1 | U49: 1 | V49: 150000 | Y49: =IF($Q49=1,IF(AND(R49<>"",S49<>""),R49/S49/12,""),IF($Q49=2,IF(AND(T49<>"",U49<>"",V49<>""),T49*U49*V49,""),IF($Q49=3,IF(AND(W49<>"",X49<>""),W49/X49/12,""),IF($Q49=4,IF(AND(R49<>"",S49<>""),R49/S49/12,0)+IF(AND(T49<>"",U49<>"",V49<>""),T49*U49*V49,0),IF($Q49=5,IF(AND(R49<>"",S49<>""),R49/S49/12,0)+IF(AND(W49<>"",X49<>""),W49/X49/12,0),IF($Q49=6,IF(AND(T49<>"",U49<>"",V49<>""),T49*U49*V49,0)+IF(AND(W49<>"",X49<>""),W49/X49/12,0),"")))))) -> 150000 | Z49: 2 | AH49: =IF($Z49=1,IF(AND(AA49<>"",AB49<>""),AA49/AB49/12,""),IF($Z49=2,IF(AND(AC49<>"",AD49<>"",AE49<>""),AC49*AD49*AE49,""),IF($Z49=3,IF(AND(AF49<>"",AG49<>""),AF49/AG49/12,""),IF($Z49=4,IF(AND(AA49<>"",AB49<>""),AA49/AB49/12,0)+IF(AND(AC49<>"",AD49<>"",AE49<>""),AC49*AD49*AE49,0),IF($Z49=5,IF(AND(AA49<>"",AB49<>""),AA49/AB49/12,0)+IF(AND(AF49<>"",AG49<>""),AF49/AG49/12,0),IF($Z49=6,IF(AND(AC49<>"",AD49<>"",AE49<>""),AC49*AD49*AE49,0)+IF(AND(AF49<>"",AG49<>""),AF49/AG49/12,0),"")))))) | AI49: =IF(매핑v2!H46="○",P49,"") | AJ49: =IF(매핑v2!H46="○","○","X") -> X | AK49: =IF(매핑v2!H46="○",Y49,"") | AL49: =IF(매핑v2!H46="○","○","X") -> X | AM49: =IF(매핑v2!H46="○",AH49,"") | AN49: =IF(매핑v2!H46="○","○","X") -> X | AO49: =IF(매핑v2!I46="○",P49,"") -> 25000 | AP49: =IF(매핑v2!I46="○","○","X") -> ○ | AQ49: =IF(매핑v2!I46="○",Y49,"") -> 150000 | AR49: =IF(매핑v2!I46="○","○","X") -> ○ | AS49: =IF(매핑v2!I46="○",AH49,"") | AT49: =IF(매핑v2!I46="○","○","X") -> ○ | AU49: =IF(매핑v2!J46="○",P49,"") -> 25000 | AV49: =IF(매핑v2!J46="○","○","X") -> ○ | AW49: =IF(매핑v2!J46="○",Y49,"") -> 150000 | AX49: =IF(매핑v2!J46="○","○","X") -> ○ | AY49: =IF(매핑v2!J46="○",AH49,"") | AZ49: =IF(매핑v2!J46="○","○","X") -> ○ | BA49: =IF(매핑v2!K46="○",P49,"") -> 25000 | BB49: =IF(매핑v2!K46="○","○","X") -> ○ | BC49: =IF(매핑v2!K46="○",Y49,"") -> 150000 | BD49: =IF(매핑v2!K46="○","○","X") -> ○ | BE49: =IF(매핑v2!K46="○",AH49,"") | BF49: =IF(매핑v2!K46="○","○","X") -> ○ | BG49: =IF(매핑v2!L46="○",P49,"") | BH49: =IF(매핑v2!L46="○","○","X") -> X | BI49: =IF(매핑v2!L46="○",Y49,"") | BJ49: ○ | BK49: X | BL49: X | BM49: ○ | BN49: X | BO49: X
A50: 49 | B50: 취미 | C50: 반려동물 사료 | D50: right spec | E50: 성분표 기반 선택 / 대용량 직구 | F50: 수의사·인플루언서 추천 최고가 유기농 브랜드 맹목적 정기 배송 | G50: 마트 제일 싼 대포장 사료 먹이다 신장결석 등 거대 병원비 폭탄 맞음 | H50: 2 | K50: 1 | L50: 1 | M50: 30000 | P50: =IF($H50=1,IF(AND(I50<>"",J50<>""),I50/J50/12,""),IF($H50=2,IF(AND(K50<>"",L50<>"",M50<>""),K50*L50*M50,""),IF($H50=3,IF(AND(N50<>"",O50<>""),N50/O50/12,""),IF($H50=4,IF(AND(I50<>"",J50<>""),I50/J50/12,0)+IF(AND(K50<>"",L50<>"",M50<>""),K50*L50*M50,0),IF($H50=5,IF(AND(I50<>"",J50<>""),I50/J50/12,0)+IF(AND(N50<>"",O50<>""),N50/O50/12,0),IF($H50=6,IF(AND(K50<>"",L50<>"",M50<>""),K50*L50*M50,0)+IF(AND(N50<>"",O50<>""),N50/O50/12,0),"")))))) -> 30000 | Q50: 2 | T50: 1 | U50: 1 | V50: 200000 | Y50: =IF($Q50=1,IF(AND(R50<>"",S50<>""),R50/S50/12,""),IF($Q50=2,IF(AND(T50<>"",U50<>"",V50<>""),T50*U50*V50,""),IF($Q50=3,IF(AND(W50<>"",X50<>""),W50/X50/12,""),IF($Q50=4,IF(AND(R50<>"",S50<>""),R50/S50/12,0)+IF(AND(T50<>"",U50<>"",V50<>""),T50*U50*V50,0),IF($Q50=5,IF(AND(R50<>"",S50<>""),R50/S50/12,0)+IF(AND(W50<>"",X50<>""),W50/X50/12,0),IF($Q50=6,IF(AND(T50<>"",U50<>"",V50<>""),T50*U50*V50,0)+IF(AND(W50<>"",X50<>""),W50/X50/12,0),"")))))) -> 200000 | Z50: 2 | AC50: 1 | AD50: 1 | AE50: =10000+50000 -> 60000 | AH50: =IF($Z50=1,IF(AND(AA50<>"",AB50<>""),AA50/AB50/12,""),IF($Z50=2,IF(AND(AC50<>"",AD50<>"",AE50<>""),AC50*AD50*AE50,""),IF($Z50=3,IF(AND(AF50<>"",AG50<>""),AF50/AG50/12,""),IF($Z50=4,IF(AND(AA50<>"",AB50<>""),AA50/AB50/12,0)+IF(AND(AC50<>"",AD50<>"",AE50<>""),AC50*AD50*AE50,0),IF($Z50=5,IF(AND(AA50<>"",AB50<>""),AA50/AB50/12,0)+IF(AND(AF50<>"",AG50<>""),AF50/AG50/12,0),IF($Z50=6,IF(AND(AC50<>"",AD50<>"",AE50<>""),AC50*AD50*AE50,0)+IF(AND(AF50<>"",AG50<>""),AF50/AG50/12,0),"")))))) -> 60000 | AI50: =IF(매핑v2!H47="○",P50,"") | AJ50: =IF(매핑v2!H47="○","○","X") -> X | AK50: =IF(매핑v2!H47="○",Y50,"") | AL50: =IF(매핑v2!H47="○","○","X") -> X | AM50: =IF(매핑v2!H47="○",AH50,"") | AN50: =IF(매핑v2!H47="○","○","X") -> X | AO50: =IF(매핑v2!I47="○",P50,"") | AP50: =IF(매핑v2!I47="○","○","X") -> X | AQ50: =IF(매핑v2!I47="○",Y50,"") | AR50: =IF(매핑v2!I47="○","○","X") -> X | AS50: =IF(매핑v2!I47="○",AH50,"") | AT50: =IF(매핑v2!I47="○","○","X") -> X | AU50: =IF(매핑v2!J47="○",P50,"") | AV50: =IF(매핑v2!J47="○","○","X") -> X | AW50: =IF(매핑v2!J47="○",Y50,"") | AX50: =IF(매핑v2!J47="○","○","X") -> X | AY50: =IF(매핑v2!J47="○",AH50,"") | AZ50: =IF(매핑v2!J47="○","○","X") -> X | BA50: =IF(매핑v2!K47="○",P50,"") | BB50: =IF(매핑v2!K47="○","○","X") -> X | BC50: =IF(매핑v2!K47="○",Y50,"") | BD50: =IF(매핑v2!K47="○","○","X") -> X | BE50: =IF(매핑v2!K47="○",AH50,"") | BF50: =IF(매핑v2!K47="○","○","X") -> X | BG50: =IF(매핑v2!L47="○",P50,"") | BH50: =IF(매핑v2!L47="○","○","X") -> X | BI50: =IF(매핑v2!L47="○",Y50,"") | BJ50: ○ | BK50: X | BL50: ○ | BM50: ○ | BN50: X | BO50: X
A51: 50 | B51: 취미 | C51: 반려동물 병원 | D51: 유지보수 | E51: 예방접종·정기검진 준수로 치료비 예방 | F51: 과잉 진료하는 24시간 대형 병원 VIP / 불필요한 고가 영양제 영수증 폭탄 | G51: 돈 아깝다고 정기 백신 안 맞히다 파보장염 등 큰 병 터져 수백만 원 지출 | H51: 2 | K51: 1 | L51: 0.25 | M51: 50000 | P51: =IF($H51=1,IF(AND(I51<>"",J51<>""),I51/J51/12,""),IF($H51=2,IF(AND(K51<>"",L51<>"",M51<>""),K51*L51*M51,""),IF($H51=3,IF(AND(N51<>"",O51<>""),N51/O51/12,""),IF($H51=4,IF(AND(I51<>"",J51<>""),I51/J51/12,0)+IF(AND(K51<>"",L51<>"",M51<>""),K51*L51*M51,0),IF($H51=5,IF(AND(I51<>"",J51<>""),I51/J51/12,0)+IF(AND(N51<>"",O51<>""),N51/O51/12,0),IF($H51=6,IF(AND(K51<>"",L51<>"",M51<>""),K51*L51*M51,0)+IF(AND(N51<>"",O51<>""),N51/O51/12,0),"")))))) -> 12500 | Q51: 2 | T51: 1 | U51: 1 | V51: 100000 | Y51: =IF($Q51=1,IF(AND(R51<>"",S51<>""),R51/S51/12,""),IF($Q51=2,IF(AND(T51<>"",U51<>"",V51<>""),T51*U51*V51,""),IF($Q51=3,IF(AND(W51<>"",X51<>""),W51/X51/12,""),IF($Q51=4,IF(AND(R51<>"",S51<>""),R51/S51/12,0)+IF(AND(T51<>"",U51<>"",V51<>""),T51*U51*V51,0),IF($Q51=5,IF(AND(R51<>"",S51<>""),R51/S51/12,0)+IF(AND(W51<>"",X51<>""),W51/X51/12,0),IF($Q51=6,IF(AND(T51<>"",U51<>"",V51<>""),T51*U51*V51,0)+IF(AND(W51<>"",X51<>""),W51/X51/12,0),"")))))) -> 100000 | Z51: 3 | AF51: 1000000 | AG51: 1 | AH51: =IF($Z51=1,IF(AND(AA51<>"",AB51<>""),AA51/AB51/12,""),IF($Z51=2,IF(AND(AC51<>"",AD51<>"",AE51<>""),AC51*AD51*AE51,""),IF($Z51=3,IF(AND(AF51<>"",AG51<>""),AF51/AG51/12,""),IF($Z51=4,IF(AND(AA51<>"",AB51<>""),AA51/AB51/12,0)+IF(AND(AC51<>"",AD51<>"",AE51<>""),AC51*AD51*AE51,0),IF($Z51=5,IF(AND(AA51<>"",AB51<>""),AA51/AB51/12,0)+IF(AND(AF51<>"",AG51<>""),AF51/AG51/12,0),IF($Z51=6,IF(AND(AC51<>"",AD51<>"",AE51<>""),AC51*AD51*AE51,0)+IF(AND(AF51<>"",AG51<>""),AF51/AG51/12,0),"")))))) -> 83333.333 | AI51: =IF(매핑v2!H48="○",P51,"") | AJ51: =IF(매핑v2!H48="○","○","X") -> X | AK51: =IF(매핑v2!H48="○",Y51,"") | AL51: =IF(매핑v2!H48="○","○","X") -> X | AM51: =IF(매핑v2!H48="○",AH51,"") | AN51: =IF(매핑v2!H48="○","○","X") -> X | AO51: =IF(매핑v2!I48="○",P51,"") | AP51: =IF(매핑v2!I48="○","○","X") -> X | AQ51: =IF(매핑v2!I48="○",Y51,"") | AR51: =IF(매핑v2!I48="○","○","X") -> X | AS51: =IF(매핑v2!I48="○",AH51,"") | AT51: =IF(매핑v2!I48="○","○","X") -> X | AU51: =IF(매핑v2!J48="○",P51,"") | AV51: =IF(매핑v2!J48="○","○","X") -> X | AW51: =IF(매핑v2!J48="○",Y51,"") | AX51: =IF(매핑v2!J48="○","○","X") -> X | AY51: =IF(매핑v2!J48="○",AH51,"") | AZ51: =IF(매핑v2!J48="○","○","X") -> X | BA51: =IF(매핑v2!K48="○",P51,"") | BB51: =IF(매핑v2!K48="○","○","X") -> X | BC51: =IF(매핑v2!K48="○",Y51,"") | BD51: =IF(매핑v2!K48="○","○","X") -> X | BE51: =IF(매핑v2!K48="○",AH51,"") | BF51: =IF(매핑v2!K48="○","○","X") -> X | BG51: =IF(매핑v2!L48="○",P51,"") | BH51: =IF(매핑v2!L48="○","○","X") -> X | BI51: =IF(매핑v2!L48="○",Y51,"") | BJ51: ○ | BK51: X | BL51: X | BM51: ○ | BN51: X | BO51: X
A52: 51 | B52: 취미 | C52: 반려동물 미용 | D52: DIY | E52: 셀프 목욕·빗질 (반려동물과의 놀이 시간으로 인식) | F52: 매달 애견 스파·가위컷 전문 미용실에 10~15만 원씩 정기 상납 | G52: 싸구려 이발기 사서 억지로 밀다 피부에 상처 내고 관계 나빠짐 | H52: 2 | K52: 1 | L52: 1 | M52: 10000 | P52: =IF($H52=1,IF(AND(I52<>"",J52<>""),I52/J52/12,""),IF($H52=2,IF(AND(K52<>"",L52<>"",M52<>""),K52*L52*M52,""),IF($H52=3,IF(AND(N52<>"",O52<>""),N52/O52/12,""),IF($H52=4,IF(AND(I52<>"",J52<>""),I52/J52/12,0)+IF(AND(K52<>"",L52<>"",M52<>""),K52*L52*M52,0),IF($H52=5,IF(AND(I52<>"",J52<>""),I52/J52/12,0)+IF(AND(N52<>"",O52<>""),N52/O52/12,0),IF($H52=6,IF(AND(K52<>"",L52<>"",M52<>""),K52*L52*M52,0)+IF(AND(N52<>"",O52<>""),N52/O52/12,0),"")))))) -> 10000 | Q52: 2 | T52: 1 | U52: 1 | V52: 50000 | Y52: =IF($Q52=1,IF(AND(R52<>"",S52<>""),R52/S52/12,""),IF($Q52=2,IF(AND(T52<>"",U52<>"",V52<>""),T52*U52*V52,""),IF($Q52=3,IF(AND(W52<>"",X52<>""),W52/X52/12,""),IF($Q52=4,IF(AND(R52<>"",S52<>""),R52/S52/12,0)+IF(AND(T52<>"",U52<>"",V52<>""),T52*U52*V52,0),IF($Q52=5,IF(AND(R52<>"",S52<>""),R52/S52/12,0)+IF(AND(W52<>"",X52<>""),W52/X52/12,0),IF($Q52=6,IF(AND(T52<>"",U52<>"",V52<>""),T52*U52*V52,0)+IF(AND(W52<>"",X52<>""),W52/X52/12,0),"")))))) -> 50000 | Z52: 1 | AA52: 3000 | AB52: 1 | AH52: =IF($Z52=1,IF(AND(AA52<>"",AB52<>""),AA52/AB52/12,""),IF($Z52=2,IF(AND(AC52<>"",AD52<>"",AE52<>""),AC52*AD52*AE52,""),IF($Z52=3,IF(AND(AF52<>"",AG52<>""),AF52/AG52/12,""),IF($Z52=4,IF(AND(AA52<>"",AB52<>""),AA52/AB52/12,0)+IF(AND(AC52<>"",AD52<>"",AE52<>""),AC52*AD52*AE52,0),IF($Z52=5,IF(AND(AA52<>"",AB52<>""),AA52/AB52/12,0)+IF(AND(AF52<>"",AG52<>""),AF52/AG52/12,0),IF($Z52=6,IF(AND(AC52<>"",AD52<>"",AE52<>""),AC52*AD52*AE52,0)+IF(AND(AF52<>"",AG52<>""),AF52/AG52/12,0),"")))))) -> 250 | AI52: =IF(매핑v2!H49="○",P52,"") | AJ52: =IF(매핑v2!H49="○","○","X") -> X | AK52: =IF(매핑v2!H49="○",Y52,"") | AL52: =IF(매핑v2!H49="○","○","X") -> X | AM52: =IF(매핑v2!H49="○",AH52,"") | AN52: =IF(매핑v2!H49="○","○","X") -> X | AO52: =IF(매핑v2!I49="○",P52,"") | AP52: =IF(매핑v2!I49="○","○","X") -> X | AQ52: =IF(매핑v2!I49="○",Y52,"") | AR52: =IF(매핑v2!I49="○","○","X") -> X | AS52: =IF(매핑v2!I49="○",AH52,"") | AT52: =IF(매핑v2!I49="○","○","X") -> X | AU52: =IF(매핑v2!J49="○",P52,"") | AV52: =IF(매핑v2!J49="○","○","X") -> X | AW52: =IF(매핑v2!J49="○",Y52,"") | AX52: =IF(매핑v2!J49="○","○","X") -> X | AY52: =IF(매핑v2!J49="○",AH52,"") | AZ52: =IF(매핑v2!J49="○","○","X") -> X | BA52: =IF(매핑v2!K49="○",P52,"") | BB52: =IF(매핑v2!K49="○","○","X") -> X | BC52: =IF(매핑v2!K49="○",Y52,"") | BD52: =IF(매핑v2!K49="○","○","X") -> X | BE52: =IF(매핑v2!K49="○",AH52,"") | BF52: =IF(매핑v2!K49="○","○","X") -> X | BG52: =IF(매핑v2!L49="○",P52,"") | BH52: =IF(매핑v2!L49="○","○","X") -> X | BI52: =IF(매핑v2!L49="○",Y52,"") | BJ52: ○ | BK52: X | BL52: ○ | BM52: ○ | BN52: ○ | BO52: X
A53: 52 | B53: IT | C53: PC 업그레이드 | D53: right spec | E53: RAM/SSD 추가로 본체 교체 없이 수명 연장 | F53: 느려지면 완제품 교체 감가 상납 | G53: 사양 맞추려 밤새 커뮤니티 정독 노동 | H53: 1 | I53: 400000 | J53: 5 | P53: =IF($H53=1,IF(AND(I53<>"",J53<>""),I53/J53/12,""),IF($H53=2,IF(AND(K53<>"",L53<>"",M53<>""),K53*L53*M53,""),IF($H53=3,IF(AND(N53<>"",O53<>""),N53/O53/12,""),IF($H53=4,IF(AND(I53<>"",J53<>""),I53/J53/12,0)+IF(AND(K53<>"",L53<>"",M53<>""),K53*L53*M53,0),IF($H53=5,IF(AND(I53<>"",J53<>""),I53/J53/12,0)+IF(AND(N53<>"",O53<>""),N53/O53/12,0),IF($H53=6,IF(AND(K53<>"",L53<>"",M53<>""),K53*L53*M53,0)+IF(AND(N53<>"",O53<>""),N53/O53/12,0),"")))))) -> 6666.6667 | Q53: 1 | R53: 2000000 | S53: 2 | Y53: =IF($Q53=1,IF(AND(R53<>"",S53<>""),R53/S53/12,""),IF($Q53=2,IF(AND(T53<>"",U53<>"",V53<>""),T53*U53*V53,""),IF($Q53=3,IF(AND(W53<>"",X53<>""),W53/X53/12,""),IF($Q53=4,IF(AND(R53<>"",S53<>""),R53/S53/12,0)+IF(AND(T53<>"",U53<>"",V53<>""),T53*U53*V53,0),IF($Q53=5,IF(AND(R53<>"",S53<>""),R53/S53/12,0)+IF(AND(W53<>"",X53<>""),W53/X53/12,0),IF($Q53=6,IF(AND(T53<>"",U53<>"",V53<>""),T53*U53*V53,0)+IF(AND(W53<>"",X53<>""),W53/X53/12,0),"")))))) -> 83333.333 | Z53: 1 | AA53: 300000 | AB53: 2 | AH53: =IF($Z53=1,IF(AND(AA53<>"",AB53<>""),AA53/AB53/12,""),IF($Z53=2,IF(AND(AC53<>"",AD53<>"",AE53<>""),AC53*AD53*AE53,""),IF($Z53=3,IF(AND(AF53<>"",AG53<>""),AF53/AG53/12,""),IF($Z53=4,IF(AND(AA53<>"",AB53<>""),AA53/AB53/12,0)+IF(AND(AC53<>"",AD53<>"",AE53<>""),AC53*AD53*AE53,0),IF($Z53=5,IF(AND(AA53<>"",AB53<>""),AA53/AB53/12,0)+IF(AND(AF53<>"",AG53<>""),AF53/AG53/12,0),IF($Z53=6,IF(AND(AC53<>"",AD53<>"",AE53<>""),AC53*AD53*AE53,0)+IF(AND(AF53<>"",AG53<>""),AF53/AG53/12,0),"")))))) -> 12500 | AI53: =IF(매핑v2!H50="○",P53,"") -> 6666.6667 | AJ53: =IF(매핑v2!H50="○","○","X") -> ○ | AK53: =IF(매핑v2!H50="○",Y53,"") -> 83333.333 | AL53: =IF(매핑v2!H50="○","○","X") -> ○ | AM53: =IF(매핑v2!H50="○",AH53,"") -> 12500 | AN53: =IF(매핑v2!H50="○","○","X") -> ○ | AO53: =IF(매핑v2!I50="○",P53,"") -> 6666.6667 | AP53: =IF(매핑v2!I50="○","○","X") -> ○ | AQ53: =IF(매핑v2!I50="○",Y53,"") -> 83333.333 | AR53: =IF(매핑v2!I50="○","○","X") -> ○ | AS53: =IF(매핑v2!I50="○",AH53,"") -> 12500 | AT53: =IF(매핑v2!I50="○","○","X") -> ○ | AU53: =IF(매핑v2!J50="○",P53,"") -> 6666.6667 | AV53: =IF(매핑v2!J50="○","○","X") -> ○ | AW53: =IF(매핑v2!J50="○",Y53,"") -> 83333.333 | AX53: =IF(매핑v2!J50="○","○","X") -> ○ | AY53: =IF(매핑v2!J50="○",AH53,"") -> 12500 | AZ53: =IF(매핑v2!J50="○","○","X") -> ○ | BA53: =IF(매핑v2!K50="○",P53,"") -> 6666.6667 | BB53: =IF(매핑v2!K50="○","○","X") -> ○ | BC53: =IF(매핑v2!K50="○",Y53,"") -> 83333.333 | BD53: =IF(매핑v2!K50="○","○","X") -> ○ | BE53: =IF(매핑v2!K50="○",AH53,"") -> 12500 | BF53: =IF(매핑v2!K50="○","○","X") -> ○ | BG53: =IF(매핑v2!L50="○",P53,"") | BH53: =IF(매핑v2!L50="○","○","X") -> X | BI53: =IF(매핑v2!L50="○",Y53,"") | BJ53: ○ | BK53: X | BL53: ○ | BM53: ○ | BN53: ○ | BO53: X
